Workbook

Sheet Accueil
B1: AéroAtlas Composites SARL — DOSSIER DE CLÔTURE 2025 (CGNC)
B2: ="Société : "&Accueil!$C$8&" │ Exercice : "&Accueil!$C$11&" │ Date d'arrêté : "&Accueil!$C$12&" │ Responsable : "&Accueil!$C$15 -> Société : AéroAtlas Composites SARL │ Exercice : 2025 │ Date d'arrêté : 31/12/2025 │ Responsable : Karim El Fassi (DAF)
C4: Balance → CPC → ESG → Reporting KPI → Dashboard │ Document préparé pour l'expert-auditeur et les investisseurs
B5: ⚠ DONNÉES ILLUSTRATIVES — société et chiffres fictifs, à usage de démonstration du modèle de clôture
B7: IDENTITÉ DE L'ENTREPRISE
B8: Nom de l'entreprise | C8: AéroAtlas Composites SARL
B9: Forme juridique / Capital | C9: SARL au capital de 50 000 000,00 MAD
B10: Secteur | C10: Aéronautique — sous-traitance de rang 2 (usinage, composites, câblage)
B11: Exercice | C11: 2025
B12: Date d'arrêté | C12: 31/12/2025
B13: Date d'édition | C13: 03/10/2026
B14: Département | C14: Direction Administrative & Financière
B15: Responsable département | C15: Karim El Fassi (DAF)
B16: Site | C16: Midparc — zone d'accélération industrielle, Nouaceur (Casablanca)
B17: Référentiel | C17: CGNC — CPC / ESG modèles normaux ; CGI (IS 20 % — ZAI)
B18: Profil commercial | C18: 70 % du CA à l'export (facturé hors TVA) — 30 % local (TVA 20 %)
B20: SOMMAIRE
B21: Onglet | C21: Contenu | D21: Accès
B22: 1. Balance | C22: Balance générale CGNC classes 1 à 7, Déc. N-1 + 12 mois, contrôle d'équilibre mensuel | D22: Ouvrir ▸
B23: 2. CPC | C23: Compte de produits et charges détaillé (I à XVI), calcul automatique mensuel par racine de compte | D23: Ouvrir ▸
B24: 3. ESG | C24: État des soldes de gestion : TFR (marge → RN) et CAF / autofinancement, 12 mois | D24: Ouvrir ▸
B25: 4. Reporting | C25: Élasticité CA/REX, 17 KPI avec benchmark sectoriel, statuts colorés, commentaires et recommandations chiffrés | D25: Ouvrir ▸
B26: 5. DASHBOARD | C26: Vue direction générale : 4 cartes (CA, DSO, DPO, croissance RN) et 4 graphiques de tendance | D26: Ouvrir ▸
B27: 6. Lecture | C27: Dictionnaire des indicateurs en langage simple + glossaire | D27: Ouvrir ▸
B29: CONTRÔLES DE COHÉRENCE (calculés en temps réel)
B30: Balance équilibrée (13 colonnes) | C30: =IF(SUMPRODUCT(ABS(Balance!D5:P5))<0.01,"✔ Conforme","✖ À vérifier") -> ✔ Conforme
B31: Résultat CPC = Balance (13 colonnes) | C31: =IF(SUMPRODUCT(ABS(CPC!D66:P66))<0.01,"✔ Conforme","✖ À vérifier") -> ✔ Conforme
B32: RN et REX : ESG = CPC (13 colonnes) | C32: =IF(SUMPRODUCT(ABS(ESG!D47:P47))<0.01,"✔ Conforme","✖ À vérifier") -> ✔ Conforme
B33: Chiffre d'affaires 2025 | C33: =CPC!Q11 -> 142000000
B34: Résultat net 2025 | C34: =CPC!Q60 -> 10960000
B35: Capacité d'autofinancement 2025 | C35: =ESG!Q43 -> 19590000
B37: MODE D'EMPLOI
B38: 1. Balance : seule zone de saisie (chiffres en bleu). Pour utiliser une vraie balance, coller les comptes CGNC (4 chiffres) en colonne B, les intitulés en C et les montants signés (Débit +, Crédit −) en D:P, lignes 7 à 400.
B39: 2. Convention : classes 1 à 5 = soldes de fin de mois ; classes 6 et 7 = mouvements du mois. La colonne Déc. N-1 sert de référence pour les variations de janvier.
B40: 3. Vérifier que la ligne « Contrôle équilibre » de la Balance et les contrôles ci-dessus sont tous verts avant toute lecture.
B41: 4. CPC et ESG se calculent automatiquement par racine de compte : aucune saisie, aucun chiffre en dur.
B42: 5. Reporting : choisir le mois dans la cellule « Mois sélectionné » (liste déroulante). Le tableau des KPI, les statuts et les commentaires chiffrés se mettent à jour.
B43: 6. Les seuils du benchmark et les hypothèses (part export, TVA, jours/mois) sont modifiables dans le Reporting (cellules en bleu sur fond doré).
B44: 7. DASHBOARD : choisir le mois dans son propre sélecteur ; les 4 cartes affichent la valeur, l'évolution vs mois précédent et le statut. Les graphiques montrent les 12 mois.
B45: 8. Couleurs : vert = conforme │ bleu = neutre │ orange = vigilance │ rouge = alerte │ « — » = calcul impossible │ « n.s. » = non significatif. Définitions : onglet Lecture.

Sheet Balance
B1: BALANCE GÉNÉRALE MENSUELLE — CGNC (classes 1 à 7)
B2: ="Société : "&Accueil!$C$8&" │ Exercice : "&Accueil!$C$11&" │ Date d'arrêté : "&Accueil!$C$12&" │ Responsable : "&Accueil!$C$15 -> Société : AéroAtlas Composites SARL │ Exercice : 2025 │ Date d'arrêté : 31/12/2025 │ Responsable : Karim El Fassi (DAF)
B4: ← Accueil | C4: Convention : Débit = +, Crédit = − │ Classes 1 à 5 : soldes de fin de mois │ Classes 6 et 7 : mouvements du mois │ Déc. N-1 = référence
C5: CONTRÔLE ÉQUILIBRE (doit être = 0) | D5: =ROUND(SUMPRODUCT(($B$7:$B$400<>"")*D$7:D$400),2) -> 0 | E5: =ROUND(SUMPRODUCT(($B$7:$B$400<>"")*E$7:E$400),2) -> 0 | F5: =ROUND(SUMPRODUCT(($B$7:$B$400<>"")*F$7:F$400),2) -> 0 | G5: =ROUND(SUMPRODUCT(($B$7:$B$400<>"")*G$7:G$400),2) -> 0 | H5: =ROUND(SUMPRODUCT(($B$7:$B$400<>"")*H$7:H$400),2) -> 0 | I5: =ROUND(SUMPRODUCT(($B$7:$B$400<>"")*I$7:I$400),2) -> 0 | J5: =ROUND(SUMPRODUCT(($B$7:$B$400<>"")*J$7:J$400),2) -> 0 | K5: =ROUND(SUMPRODUCT(($B$7:$B$400<>"")*K$7:K$400),2) -> 0 | ... P5: =ROUND(SUMPRODUCT(($B$7:$B$400<>"")*P$7:P$400),2) -> 0
B6: N° compte | C6: Intitulé du compte (CGNC) | D6: Déc. N-1 | E6: Janvier | F6: Février | G6: Mars | H6: Avril | I6: Mai | J6: Juin | K6: Juillet | L6: Août | M6: Septembre | N6: Octobre | O6: Novembre | P6: Décembre
C7: CLASSE 1 — COMPTES DE FINANCEMENT PERMANENT (sous-total) | D7: =SUM(D8:D18) -> -125140000 | E7: =SUM(E8:E18) -> -1.2478684e+08 | F7: =SUM(F8:F18) -> -1.2496251e+08 | G7: =SUM(G8:G18) -> -1.254692e+08 | H7: =SUM(H8:H18) -> -1.2597533e+08 | I7: =SUM(I8:I18) -> -1.2627093e+08 | J7: =SUM(J8:J18) -> -1.2714189e+08 | K7: =SUM(K8:K18) -> -1.2826377e+08 | ... P7: =SUM(P8:P18) -> -1.2865043e+08
B8: 1111 | C8: Capital social | D8: -50000000 | E8: -50000000 | F8: -50000000 | G8: -50000000 | H8: -50000000 | I8: -50000000 | J8: -50000000 | K8: -50000000 | L8: -50000000 | M8: -50000000 | N8: -50000000 | O8: -50000000 | P8: -50000000
B9: 1140 | C9: Réserve légale | D9: -5000000 | E9: -5000000 | F9: -5000000 | G9: -5000000 | H9: -5000000 | I9: -5000000 | J9: -5000000 | K9: -5000000 | L9: -5000000 | M9: -5000000 | N9: -5000000 | O9: -5000000 | P9: -5000000
B10: 1161 | C10: Report à nouveau (solde créditeur) | D10: -10000000 | E10: -10000000 | F10: -10000000 | G10: -10000000 | H10: -10000000 | I10: -10000000 | J10: -18806840 | K10: -18806840 | L10: -18806840 | M10: -18806840 | N10: -18806840 | O10: -18806840 | P10: -18806840
B11: 1181 | C11: Résultats nets en instance d'affectation (solde créditeur) | D11: 0 | E11: -8806839.5 | F11: -8806839.5 | G11: -8806839.5 | H11: -8806839.5 | I11: -8806839.5 | J11: 0 | K11: 0 | L11: 0 | M11: 0 | N11: 0 | O11: 0 | P11: 0
B12: 1191 | C12: Résultat net de l'exercice (cumul à fin du mois précédent) | D12: -8600000 | E12: 0 | F12: -735670.37 | G12: -1802358.1 | H12: -2868491 | I12: -3724089.5 | J12: -5155051.5 | K12: -6836934.6 | L12: -8021757 | M12: -7624272.5 | N12: -7982071.9 | O12: -9140621.9 | P12: -10023589
B13: 1311 | C13: Subventions d'investissement reçues | D13: -1500000 | E13: -1500000 | F13: -1500000 | G13: -1500000 | H13: -1500000 | I13: -1500000 | J13: -1500000 | K13: -1500000 | L13: -1500000 | M13: -1500000 | N13: -1500000 | O13: -1500000 | P13: -1500000
B14: 1319 | C14: Subventions d'investissement inscrites au CPC | D14: 360000 | E14: 370000 | F14: 380000 | G14: 390000 | H14: 400000 | I14: 410000 | J14: 420000 | K14: 430000 | L14: 440000 | M14: 450000 | N14: 460000 | O14: 470000 | P14: 480000
B15: 1481 | C15: Emprunts auprès des établissements de crédit | D15: -50000000 | E15: -49450000 | F15: -48900000 | G15: -48350000 | H15: -47800000 | I15: -47250000 | J15: -46700000 | K15: -46150000 | L15: -45600000 | M15: -45050000 | N15: -44500000 | O15: -43950000 | P15: -43400000
B16: 1488 | C16: Dettes de financement diverses | D16: 0 | E16: 0 | F16: 0 | G16: 0 | H16: 0 | I16: 0 | J16: 0 | K16: 0 | L16: 0 | M16: 0 | N16: 0 | O16: 0 | P16: 0
B17: 1511 | C17: Provisions pour litiges | D17: -400000 | E17: -400000 | F17: -400000 | G17: -400000 | H17: -400000 | I17: -400000 | J17: -400000 | K17: -400000 | L17: -400000 | M17: -400000 | N17: -400000 | O17: -400000 | P17: -400000
B18: 1516 | C18: Provisions pour pertes de change | D18: 0 | E18: 0 | F18: 0 | G18: 0 | H18: 0 | I18: 0 | J18: 0 | K18: 0 | L18: 0 | M18: 0 | N18: 0 | O18: 0 | P18: 0
C19: CLASSE 2 — COMPTES D'ACTIF IMMOBILISÉ (sous-total) | D19: =SUM(D20:D35) -> 97000000 | E19: =SUM(E20:E35) -> 96266667 | F19: =SUM(F20:F35) -> 95533333 | G19: =SUM(G20:G35) -> 94800000 | H19: =SUM(H20:H35) -> 98566667 | I19: =SUM(I20:I35) -> 97833333 | J19: =SUM(J20:J35) -> 97100000 | K19: =SUM(K20:K35) -> 96366667 | ... P19: =SUM(P20:P35) -> 94450000
B20: 2121 | C20: Frais d'acquisition des immobilisations | D20: 2000000 | E20: 2000000 | F20: 2000000 | G20: 2000000 | H20: 2000000 | I20: 2000000 | J20: 2000000 | K20: 2000000 | L20: 2000000 | M20: 2000000 | N20: 2000000 | O20: 2000000 | P20: 2000000
B21: 2220 | C21: Brevets, marques, droits et valeurs similaires | D21: 1800000 | E21: 1800000 | F21: 1800000 | G21: 1800000 | H21: 1800000 | I21: 1800000 | J21: 1800000 | K21: 1800000 | L21: 1800000 | M21: 1800000 | N21: 1800000 | O21: 1800000 | P21: 1800000
B22: 2310 | C22: Terrains | D22: 6000000 | E22: 6000000 | F22: 6000000 | G22: 6000000 | H22: 6000000 | I22: 6000000 | J22: 6000000 | K22: 6000000 | L22: 6000000 | M22: 6000000 | N22: 6000000 | O22: 6000000 | P22: 6000000
B23: 2321 | C23: Bâtiments | D23: 28000000 | E23: 28000000 | F23: 28000000 | G23: 28000000 | H23: 28000000 | I23: 28000000 | J23: 28000000 | K23: 28000000 | L23: 28000000 | M23: 28000000 | N23: 28000000 | O23: 28000000 | P23: 28000000
B24: 2332 | C24: Matériel et outillage | D24: 108000000 | E24: 108000000 | F24: 108000000 | G24: 108000000 | H24: 112500000 | I24: 112500000 | J24: 112500000 | K24: 112500000 | L24: 112500000 | M24: 114000000 | N24: 114000000 | O24: 114000000 | P24: 114000000
B25: 2340 | C25: Matériel de transport | D25: 3000000 | E25: 3000000 | F25: 3000000 | G25: 3000000 | H25: 3000000 | I25: 3000000 | J25: 3000000 | K25: 3000000 | L25: 3000000 | M25: 3000000 | N25: 1800000 | O25: 1800000 | P25: 1800000
B26: 2351 | C26: Mobilier de bureau | D26: 1200000 | E26: 1200000 | F26: 1200000 | G26: 1200000 | H26: 1200000 | I26: 1200000 | J26: 1200000 | K26: 1200000 | L26: 1200000 | M26: 1200000 | N26: 1200000 | O26: 1200000 | P26: 1200000
B27: 2355 | C27: Matériel informatique | D27: 2400000 | E27: 2400000 | F27: 2400000 | G27: 2400000 | H27: 2400000 | I27: 2400000 | J27: 2400000 | K27: 2400000 | L27: 2400000 | M27: 2900000 | N27: 2900000 | O27: 2900000 | P27: 2900000
B28: 2397 | C28: Avances et acomptes versés sur commandes d'immobilisations corporelles | D28: 0 | E28: 0 | F28: 0 | G28: 0 | H28: 0 | I28: 0 | J28: 0 | K28: 0 | L28: 0 | M28: 0 | N28: 0 | O28: 0 | P28: 0
B29: 2486 | C29: Dépôts et cautionnements versés | D29: 600000 | E29: 600000 | F29: 600000 | G29: 600000 | H29: 600000 | I29: 600000 | J29: 600000 | K29: 600000 | L29: 600000 | M29: 600000 | N29: 600000 | O29: 600000 | P29: 600000
B30: 2812 | C30: Amortissements des charges à répartir | D30: -800000 | E30: -833333.33 | F30: -866666.66 | G30: -899999.99 | H30: -933333.32 | I30: -966666.65 | J30: -999999.98 | K30: -1033333.3 | L30: -1066666.6 | M30: -1100000 | N30: -1133333.3 | O30: -1166666.6 | P30: -1200000
B31: 2822 | C31: Amortissements des brevets, marques, droits et valeurs similaires | D31: -600000 | E31: -625000 | F31: -650000 | G31: -675000 | H31: -700000 | I31: -725000 | J31: -750000 | K31: -775000 | L31: -800000 | M31: -825000 | N31: -850000 | O31: -875000 | P31: -900000
... B35: 2835 | C35: Amortissements du mobilier, matériel de bureau et aménagements divers | D35: -1500000 | E35: -1548333.3 | F35: -1596666.7 | G35: -1645000 | H35: -1693333.3 | I35: -1741666.7 | J35: -1790000 | K35: -1838333.3 | L35: -1886666.7 | M35: -1935000 | N35: -1983333.3 | O35: -2031666.7 | P35: -2080000
C36: CLASSE 3 — COMPTES D'ACTIF CIRCULANT (HORS TRÉSORERIE) (sous-total) | D36: =SUM(D37:D51) -> 51961368 | E36: =SUM(E37:E51) -> 51017864 | F36: =SUM(F37:F51) -> 50828439 | G36: =SUM(G37:G51) -> 50968015 | H36: =SUM(H37:H51) -> 51769296 | I36: =SUM(I37:I51) -> 52926022 | J36: =SUM(J37:J51) -> 54304844 | K36: =SUM(K37:K51) -> 54080248 | ... P36: =SUM(P37:P51) -> 56600208
B37: 3111 | C37: Marchandises | D37: 0 | E37: 0 | F37: 0 | G37: 0 | H37: 0 | I37: 0 | J37: 0 | K37: 0 | L37: 0 | M37: 0 | N37: 0 | O37: 0 | P37: 0
B38: 3121 | C38: Matières premières | D38: 7744000 | E38: 7920000 | F38: 8184000 | G38: 8448000 | H38: 8272000 | I38: 8360000 | J38: 8536000 | K38: 8712000 | L38: 9152000 | M38: 8624000 | N38: 8360000 | O38: 8184000 | P38: 8008000
B39: 3122 | C39: Matières et fournitures consommables | D39: 1056000 | E39: 1080000 | F39: 1116000 | G39: 1152000 | H39: 1128000 | I39: 1140000 | J39: 1164000 | K39: 1188000 | L39: 1248000 | M39: 1176000 | N39: 1140000 | O39: 1116000 | P39: 1092000
B40: 3131 | C40: Biens en cours | D40: 3850000 | E40: 3905000 | F40: 4015000 | G40: 4125000 | H40: 4180000 | I40: 4290000 | J40: 4345000 | K40: 4510000 | L40: 4620000 | M40: 4565000 | N40: 4620000 | O40: 4730000 | P40: 4510000
B41: 3151 | C41: Produits finis | D41: 3150000 | E41: 3195000 | F41: 3285000 | G41: 3375000 | H41: 3420000 | I41: 3510000 | J41: 3555000 | K41: 3690000 | L41: 3780000 | M41: 3735000 | N41: 3780000 | O41: 3870000 | P41: 3690000
B42: 3411 | C42: Fournisseurs - avances et acomptes versés sur commandes d'exploitation | D42: 792249.71 | E42: 819650.44 | F42: 787069.34 | G42: 749215.23 | H42: 725600.68 | I42: 807202.46 | J42: 729724.43 | K42: 770049.34 | L42: 748182.08 | M42: 813619.46 | N42: 831407.01 | O42: 862946.23 | P42: 806093.01
B43: 3421 | C43: Clients | D43: 28719640 | E43: 27598160 | F43: 27061800 | G43: 28280800 | H43: 29158480 | I43: 29938640 | J43: 30572520 | K43: 29938640 | L43: 24770080 | M43: 24672560 | N43: 27890720 | O43: 30377480 | P43: 31986560
B44: 3424 | C44: Clients douteux ou litigieux | D44: 1400000 | E44: 1400000 | F44: 1400000 | G44: 1400000 | H44: 1400000 | I44: 1400000 | J44: 1400000 | K44: 1400000 | L44: 1400000 | M44: 1400000 | N44: 1400000 | O44: 1400000 | P44: 1400000
B45: 3425 | C45: Clients - effets à recevoir | D45: 2497360 | E45: 2399840 | F45: 2353200 | G45: 2459200 | H45: 2535520 | I45: 2603360 | J45: 2658480 | K45: 2603360 | L45: 2153920 | M45: 2145440 | N45: 2425280 | O45: 2641520 | P45: 2781440
B46: 3431 | C46: Avances et acomptes au personnel | D46: 140065.22 | E46: 167081.31 | F46: 137127.63 | G46: 136599.35 | H46: 178467.75 | I46: 126310.07 | J46: 137417.79 | K46: 156419.43 | L46: 157794.96 | M46: 140577.2 | N46: 138003.36 | O46: 176022.58 | P46: 130809.61
B47: 3453 | C47: Acomptes sur impôts sur les résultats | D47: 2400000 | E47: 2400000 | F47: 2400000 | G47: 600000 | H47: 600000 | I47: 600000 | J47: 1200000 | K47: 1200000 | L47: 1200000 | M47: 1800000 | N47: 1800000 | O47: 1800000 | P47: 2400000
B48: 3455 | C48: État - TVA récupérable | D48: 612052.57 | E48: 583131.97 | F48: 589241.86 | G48: 642199.95 | H48: 621227.43 | I48: 650509.89 | J48: 656701.65 | K48: 611779.38 | L48: 456639.28 | M48: 631303.88 | N48: 655344.09 | O48: 631615.09 | P48: 695305.51
... B51: 3942 | C51: Provisions pour dépréciation des clients et comptes rattachés | D51: -1300000 | E51: -1300000 | F51: -1300000 | G51: -1150000 | H51: -1150000 | I51: -1150000 | J51: -1250000 | K51: -1250000 | L51: -1250000 | M51: -1100000 | N51: -1100000 | O51: -1100000 | P51: -1200000
C52: CLASSE 4 — COMPTES DE PASSIF CIRCULANT (HORS TRÉSORERIE) (sous-total) | D52: =SUM(D53:D64) -> -28691010 | E52: =SUM(E53:E64) -> -28046445 | F52: =SUM(F53:F64) -> -28001979 | G52: =SUM(G53:G64) -> -26332246 | H52: =SUM(H53:H64) -> -31592258 | I52: =SUM(I53:I64) -> -30437684 | J52: =SUM(J53:J64) -> -28869492 | K52: =SUM(K53:K64) -> -28912642 | ... P52: =SUM(P53:P64) -> -31062348
B53: 4411 | C53: Fournisseurs | D53: -20286067 | E53: -19764244 | F53: -19370001 | G53: -19905542 | H53: -20458300 | I53: -21093419 | J53: -21478516 | K53: -21161514 | L53: -18263292 | M53: -18097458 | N53: -19472354 | O53: -21205957 | P53: -22046478
B54: 4415 | C54: Fournisseurs - effets à payer | D54: 0 | E54: 0 | F54: 0 | G54: 0 | H54: 0 | I54: 0 | J54: 0 | K54: 0 | L54: 0 | M54: 0 | N54: 0 | O54: 0 | P54: 0
B55: 4417 | C55: Fournisseurs - factures non parvenues | D55: -865477.86 | E55: -899342.42 | F55: -932888.74 | G55: -871045.23 | H55: -921922.12 | I55: -969219.02 | J55: -822890.01 | K55: -955303.95 | L55: -840095.2 | M55: -956986.18 | N55: -833593.13 | O55: -946838.88 | P55: -973801.46
B56: 4432 | C56: Rémunérations dues au personnel | D56: -305388.02 | E56: -248788.65 | F56: -248054.06 | G56: -251671.48 | H56: -248835.22 | I56: -253050.46 | J56: -250362.66 | K56: -249540.69 | L56: -232154.58 | M56: -253138.6 | N56: -253479.33 | O56: -250253.22 | P56: -320671.04
B57: 4441 | C57: Caisse nationale de sécurité sociale | D57: -802015.95 | E57: -644811.89 | F57: -657138.23 | G57: -655904.03 | H57: -658789.09 | I57: -658525.49 | J57: -656297.61 | K57: -653666.03 | L57: -609036.36 | M57: -659998.74 | N57: -656386.43 | O57: -653356.43 | P57: -836089.67
B58: 4443 | C58: Caisses de retraite | D58: -200000 | E58: -200000 | F58: -200000 | G58: -200000 | H58: -200000 | I58: -200000 | J58: -200000 | K58: -200000 | L58: -200000 | M58: -200000 | N58: -200000 | O58: -200000 | P58: -200000
B59: 4452 | C59: État - impôts, taxes et assimilés | D59: -458082.03 | E59: -373182.98 | F59: -372081.09 | G59: -377507.23 | H59: -373252.84 | I59: -379575.69 | J59: -375543.99 | K59: -374311.04 | L59: -348231.87 | M59: -379707.9 | N59: -380218.99 | O59: -375379.82 | P59: -481006.56
B60: 4453 | C60: État - impôts sur les résultats | D60: -2500000 | E60: -2683917.6 | F60: -2950589.5 | G60: -717122.71 | H60: -931022.35 | I60: -1288762.8 | J60: -1709233.6 | K60: -2005439.2 | L60: -1906068.1 | M60: -1995517.9 | N60: -2285155.4 | O60: -2505897.1 | P60: -2740000
B61: 4455 | C61: État - TVA facturée | D61: -673979.74 | E61: -632157.01 | F61: -671226.71 | G61: -753452.87 | H61: -700136.05 | I61: -745131.4 | J61: -776648.63 | K61: -712866.6 | L61: -455584.28 | M61: -730763.23 | N61: -784109.27 | O61: -734065.7 | P61: -864301.32
B62: 4463 | C62: Comptes courants des associés créditeurs | D62: -2000000 | E62: -2000000 | F62: -2000000 | G62: -2000000 | H62: -2000000 | I62: -2000000 | J62: -2000000 | K62: -2000000 | L62: -2000000 | M62: -2000000 | N62: -2000000 | O62: -2000000 | P62: -2000000
B63: 4481 | C63: Dettes sur acquisitions d'immobilisations | D63: -300000 | E63: -300000 | F63: -300000 | G63: -300000 | H63: -4800000 | I63: -2550000 | J63: -300000 | K63: -300000 | L63: -300000 | M63: -2300000 | N63: -300000 | O63: -300000 | P63: -300000
B64: 4491 | C64: Produits constatés d'avance | D64: -300000 | E64: -300000 | F64: -300000 | G64: -300000 | H64: -300000 | I64: -300000 | J64: -300000 | K64: -300000 | L64: -300000 | M64: -300000 | N64: -300000 | O64: -300000 | P64: -300000
C65: CLASSE 5 — COMPTES DE TRÉSORERIE (sous-total) | D65: =SUM(D66:D69) -> 5076482.4 | E65: =SUM(E66:E69) -> 6284424 | F65: =SUM(F66:F69) -> 7669405 | G65: =SUM(G66:G69) -> 7099561.5 | H65: =SUM(H66:H69) -> 8087224.5 | I65: =SUM(I66:I69) -> 7380219.3 | J65: =SUM(J66:J69) -> 6288422.6 | K65: =SUM(K66:K69) -> 7914323.5 | ... P65: =SUM(P66:P69) -> 9598979.5
B66: 5111 | C66: Chèques et valeurs à encaisser | D66: 0 | E66: 0 | F66: 0 | G66: 0 | H66: 0 | I66: 0 | J66: 0 | K66: 0 | L66: 0 | M66: 0 | N66: 0 | O66: 0 | P66: 0
B67: 5141 | C67: Banques (soldes débiteurs) | D67: 10026482 | E67: 11234424 | F67: 12619405 | G67: 12049561 | H67: 13037225 | I67: 12330219 | J67: 11238423 | K67: 13864323 | L67: 17325624 | M67: 16158981 | N67: 13045337 | O67: 13409259 | P67: 14548979
B68: 5161 | C68: Caisses | D68: 50000 | E68: 50000 | F68: 50000 | G68: 50000 | H68: 50000 | I68: 50000 | J68: 50000 | K68: 50000 | L68: 50000 | M68: 50000 | N68: 50000 | O68: 50000 | P68: 50000
B69: 5530 | C69: Crédits de trésorerie | D69: -5000000 | E69: -5000000 | F69: -5000000 | G69: -5000000 | H69: -5000000 | I69: -5000000 | J69: -5000000 | K69: -6000000 | L69: -8000000 | M69: -6000000 | N69: -5000000 | O69: -5000000 | P69: -5000000
C70: CLASSE 6 — COMPTES DE CHARGES (sous-total) | D70: =SUM(D71:D110) -> 11585423 | E70: =SUM(E71:E110) -> 10355579 | F70: =SUM(F71:F110) -> 10505032 | G70: =SUM(G71:G110) -> 11796923 | H70: =SUM(H71:H110) -> 11367193 | I70: =SUM(I71:I110) -> 11572309 | J70: =SUM(J71:J110) -> 11681670 | K70: =SUM(K71:K110) -> 10897678 | ... P70: =SUM(P71:P110) -> 13228444
B71: 6111 | C71: Achats de marchandises | D71: 33756.48 | E71: 32185.14 | F71: 33236.86 | G71: 37072.63 | H71: 35194.96 | I71: 37313.05 | J71: 37801.13 | K71: 34094.72 | L71: 21714.83 | M71: 35368.06 | N71: 37930.71 | O71: 36328.78 | P71: 41759.13
B72: 6114 | C72: Variation des stocks de marchandises | D72: 0 | E72: 0 | F72: 0 | G72: 0 | H72: 0 | I72: 0 | J72: 0 | K72: 0 | L72: 0 | M72: 0 | N72: 0 | O72: 0 | P72: 0
B73: 6121 | C73: Achats de matières premières | D73: 4559807 | E73: 4214345.8 | F73: 4361758.4 | G73: 4792541.2 | H73: 4664646.6 | I73: 4950931.2 | J73: 5064270.2 | K73: 4519129.3 | L73: 2936664.9 | M73: 4765506.8 | N73: 4950165.3 | O73: 4755522.8 | P73: 5424517.5
B74: 6122 | C74: Achats de matières et fournitures consommables | D74: 172657.65 | E74: 165696.6 | F74: 166695.52 | G74: 183675.99 | H74: 173003.88 | I74: 183737.28 | J74: 186651.33 | K74: 170042.9 | L74: 131312.85 | M74: 175701.48 | N74: 186725.77 | O74: 181793.98 | P74: 194962.43
B75: 6123 | C75: Achats d'emballages | D75: 48529.52 | E75: 45084.59 | F75: 47091.26 | G75: 52933.38 | H75: 50801.91 | I75: 53523.1 | J75: 54184.82 | K75: 48400.03 | L75: 31697.49 | M75: 50741.03 | N75: 54456.53 | O75: 51918.95 | P75: 59166.92
B76: 6124 | C76: Variation des stocks de matières et fournitures | D76: -100000 | E76: -200000 | F76: -300000 | G76: -300000 | H76: 200000 | I76: -100000 | J76: -200000 | K76: -200000 | L76: -500000 | M76: 600000 | N76: 300000 | O76: 200000 | P76: 200000
B77: 6125 | C77: Achats non stockés de matières et fournitures | D77: 245521.12 | E77: 236099.08 | F77: 238396.71 | G77: 259645.61 | H77: 248050.63 | I77: 257421.83 | J77: 260668.32 | K77: 248001.87 | L77: 201907.75 | M77: 250377.23 | N77: 262349.22 | O77: 258871.89 | P77: 278209.84
B78: 6126 | C78: Achats de travaux, études et prestations de services | D78: 99161.26 | E78: 90375.66 | F78: 96407.02 | G78: 104515.76 | H78: 101935.95 | I78: 106891.1 | J78: 107229.9 | K78: 98480.6 | L78: 61716.09 | M78: 101368.07 | N78: 107958.51 | O78: 105588.85 | P78: 117532.49
B79: 6131 | C79: Locations et charges locatives | D79: 300000 | E79: 300000 | F79: 300000 | G79: 300000 | H79: 300000 | I79: 300000 | J79: 300000 | K79: 300000 | L79: 300000 | M79: 300000 | N79: 300000 | O79: 300000 | P79: 300000
B80: 6132 | C80: Redevances de crédit-bail | D80: 0 | E80: 0 | F80: 0 | G80: 0 | H80: 0 | I80: 0 | J80: 0 | K80: 0 | L80: 0 | M80: 0 | N80: 0 | O80: 0 | P80: 0
B81: 6133 | C81: Entretien et réparations | D81: 199786.16 | E81: 192855.92 | F81: 194722.8 | G81: 201164.87 | H81: 203324.45 | I81: 203319.27 | J81: 207959.41 | K81: 202525.92 | L81: 174157.97 | M81: 197287.49 | N81: 204924.14 | O81: 204728.63 | P81: 213029.11
B82: 6134 | C82: Primes d'assurances | D82: 108333.33 | E82: 108333.33 | F82: 108333.33 | G82: 108333.33 | H82: 108333.33 | I82: 108333.33 | J82: 108333.33 | K82: 108333.33 | L82: 108333.33 | M82: 108333.33 | N82: 108333.33 | O82: 108333.33 | P82: 108333.33
... B110: 6701 | C110: Impôts sur les bénéfices | D110: 51709.88 | E110: 183917.58 | F110: 266671.94 | G110: 266533.19 | H110: 213899.64 | I110: 357740.48 | J110: 420470.8 | K110: 296205.59 | L110: -99371.13 | M110: 89449.86 | N110: 289637.48 | O110: 220741.68 | P110: 234102.89
C111: CLASSE 7 — COMPTES DE PRODUITS (sous-total) | D111: =SUM(D112:D132) -> -11792262 | E111: =SUM(E112:E132) -> -11091249 | F111: =SUM(F112:F132) -> -11571720 | G111: =SUM(G112:G132) -> -12863056 | H111: =SUM(H112:H132) -> -12222792 | I111: =SUM(I112:I132) -> -13003271 | J111: =SUM(J112:J132) -> -13363553 | K111: =SUM(K112:K132) -> -12082500 | ... P111: =SUM(P112:P132) -> -14164856
B112: 7111 | C112: Ventes de marchandises au Maroc | D112: -48759.93 | E112: -46033.13 | F112: -47260.36 | G112: -51367.28 | H112: -48774.59 | I112: -54751.3 | J112: -54310.72 | K112: -47737.13 | L112: -31081.64 | M112: -49725.94 | N112: -54951.81 | O112: -53474.87 | P112: -58145.28
B113: 7112 | C113: Ventes de marchandises à l'étranger | D113: 0 | E113: 0 | F113: 0 | G113: 0 | H113: 0 | I113: 0 | J113: 0 | K113: 0 | L113: 0 | M113: 0 | N113: 0 | O113: 0 | P113: 0
B114: 7121 | C114: Ventes de biens produits au Maroc | D114: -2946953.7 | E114: -2763928.3 | F114: -2951667.9 | G114: -3320563 | H114: -3076730.5 | I114: -3256735.6 | J114: -3413387.5 | K114: -3143426.1 | L114: -2000503.7 | M114: -3213422.8 | N114: -3456482.6 | O114: -3211290.3 | P114: -3805503.2
B115: 7122 | C115: Ventes de biens produits à l'étranger | D115: -7321087.4 | E115: -6901728.7 | F115: -7073382.5 | G115: -7761603.1 | H115: -7580196.7 | I115: -7994833.4 | J115: -8019753.8 | K115: -7232092.3 | L115: -4606631.2 | M115: -7606735.3 | N115: -7982403.3 | O115: -7762698.2 | P115: -8785553.6
B116: 7124 | C116: Ventes de services produits au Maroc | D116: -342093.35 | E116: -320320.81 | F116: -325467.32 | G116: -361115.06 | H116: -342096.62 | I116: -379036.66 | J116: -379789.2 | K116: -340380.43 | L116: -225282.65 | M116: -357041.66 | N116: -373543.38 | O116: -370627.47 | P116: -418977.72
B117: 7125 | C117: Ventes de services produits à l'étranger | D117: -809013.91 | E117: -737486.24 | F117: -770483.91 | G117: -871132.54 | H117: -819123.03 | I117: -879509.6 | J117: -897003.01 | K117: -803574.75 | L117: -515447.45 | M117: -839448.57 | N117: -897050.31 | O117: -866973.25 | P117: -992939.87
B118: 7126 | C118: Redevances pour brevets, marques, droits et valeurs similaires | D118: 0 | E118: 0 | F118: 0 | G118: 0 | H118: 0 | I118: 0 | J118: 0 | K118: 0 | L118: 0 | M118: 0 | N118: 0 | O118: 0 | P118: 0
B119: 7127 | C119: Ventes de produits accessoires | D119: -32091.67 | E119: -30502.78 | F119: -31737.95 | G119: -34218.95 | H119: -33078.53 | I119: -35133.45 | J119: -35755.72 | K119: -32789.29 | L119: -21053.43 | M119: -33625.76 | N119: -35568.57 | O119: -34935.89 | P119: -38880.41
B120: 7132 | C120: Variation des stocks de produits (biens en cours, produits finis) | D120: -100000 | E120: -100000 | F120: -200000 | G120: -200000 | H120: -100000 | I120: -200000 | J120: -100000 | K120: -300000 | L120: -200000 | M120: 100000 | N120: -100000 | O120: -200000 | P120: 400000
B121: 7140 | C121: Immobilisations produites par l'entreprise pour elle-même | D121: 0 | E121: 0 | F121: 0 | G121: 0 | H121: 0 | I121: 0 | J121: 0 | K121: 0 | L121: 0 | M121: 0 | N121: 0 | O121: 0 | P121: 0
B122: 7161 | C122: Subventions d'exploitation reçues de l'exercice | D122: 0 | E122: 0 | F122: 0 | G122: 0 | H122: 0 | I122: 0 | J122: -250000 | K122: 0 | L122: 0 | M122: 0 | N122: 0 | O122: 0 | P122: -250000
B123: 7182 | C123: Revenus des immeubles non affectés à l'exploitation | D123: -41666.67 | E123: -41666.67 | F123: -41666.67 | G123: -41666.67 | H123: -41666.67 | I123: -41666.67 | J123: -41666.67 | K123: -41666.67 | L123: -41666.67 | M123: -41666.67 | N123: -41666.67 | O123: -41666.67 | P123: -41666.67
... B132: 7581 | C132: Pénalités et dédits reçus | D132: 0 | E132: 0 | F132: 0 | G132: 0 | H132: 0 | I132: 0 | J132: 0 | K132: 0 | L132: 0 | M132: 0 | N132: 0 | O132: 0 | P132: 0
C134: Saisie : chiffres en bleu = données sources (seule zone saisie du fichier). Pour coller une vraie balance : comptes en colonne B (4 chiffres), montants signés en D:P, lignes 7 à 400. Les sous-totaux de classe (sans n° de compte) sont ignorés par les formules.

Sheet CPC
B1: COMPTE DE PRODUITS ET CHARGES (CPC) — MODÈLE CGNC DÉTAILLÉ
B2: ="Société : "&Accueil!$C$8&" │ Exercice : "&Accueil!$C$11&" │ Date d'arrêté : "&Accueil!$C$12&" │ Responsable : "&Accueil!$C$15 -> Société : AéroAtlas Composites SARL │ Exercice : 2025 │ Date d'arrêté : 31/12/2025 │ Responsable : Karim El Fassi (DAF)
B4: ← Accueil | C4: Calcul automatique depuis l'onglet Balance, par racine de compte, mois par mois │ Montants en MAD │ Déc. N-1 = référence (hors total)
B6: Rubriques | C6: Comptes | D6: Déc. N-1 | E6: Janvier | F6: Février | G6: Mars | H6: Avril | I6: Mai | J6: Juin | K6: Juillet | L6: Août | M6: Septembre | N6: Octobre | O6: Novembre | P6: Décembre | Q6: TOTAL 2025
B7: EXPLOITATION
B8: I PRODUITS D'EXPLOITATION
B9: Ventes de marchandises (en l'état) | C9: 711 | D9: =-SUMPRODUCT(((LEFT(Balance!$B$7:$B$400,3)="711"))*Balance!D$7:D$400) -> 48759.93 | E9: =-SUMPRODUCT(((LEFT(Balance!$B$7:$B$400,3)="711"))*Balance!E$7:E$400) -> 46033.13 | F9: =-SUMPRODUCT(((LEFT(Balance!$B$7:$B$400,3)="711"))*Balance!F$7:F$400) -> 47260.36 | G9: =-SUMPRODUCT(((LEFT(Balance!$B$7:$B$400,3)="711"))*Balance!G$7:G$400) -> 51367.28 | H9: =-SUMPRODUCT(((LEFT(Balance!$B$7:$B$400,3)="711"))*Balance!H$7:H$400) -> 48774.59 | I9: =-SUMPRODUCT(((LEFT(Balance!$B$7:$B$400,3)="711"))*Balance!I$7:I$400) -> 54751.3 | J9: =-SUMPRODUCT(((LEFT(Balance!$B$7:$B$400,3)="711"))*Balance!J$7:J$400) -> 54310.72 | K9: =-SUMPRODUCT(((LEFT(Balance!$B$7:$B$400,3)="711"))*Balance!K$7:K$400) -> 47737.13 | ... P9: =-SUMPRODUCT(((LEFT(Balance!$B$7:$B$400,3)="711"))*Balance!P$7:P$400) -> 58145.28 | Q9: =SUM(E9:P9) -> 597614.05
B10: Ventes de biens et services produits | C10: 712 | D10: =-SUMPRODUCT(((LEFT(Balance!$B$7:$B$400,3)="712"))*Balance!D$7:D$400) -> 11451240 | E10: =-SUMPRODUCT(((LEFT(Balance!$B$7:$B$400,3)="712"))*Balance!E$7:E$400) -> 10753967 | F10: =-SUMPRODUCT(((LEFT(Balance!$B$7:$B$400,3)="712"))*Balance!F$7:F$400) -> 11152740 | G10: =-SUMPRODUCT(((LEFT(Balance!$B$7:$B$400,3)="712"))*Balance!G$7:G$400) -> 12348633 | H10: =-SUMPRODUCT(((LEFT(Balance!$B$7:$B$400,3)="712"))*Balance!H$7:H$400) -> 11851225 | I10: =-SUMPRODUCT(((LEFT(Balance!$B$7:$B$400,3)="712"))*Balance!I$7:I$400) -> 12545249 | J10: =-SUMPRODUCT(((LEFT(Balance!$B$7:$B$400,3)="712"))*Balance!J$7:J$400) -> 12745689 | K10: =-SUMPRODUCT(((LEFT(Balance!$B$7:$B$400,3)="712"))*Balance!K$7:K$400) -> 11552263 | ... P10: =-SUMPRODUCT(((LEFT(Balance!$B$7:$B$400,3)="712"))*Balance!P$7:P$400) -> 14041855 | Q10: =SUM(E10:P10) -> 1.4140239e+08
B11: Chiffre d'affaires | C11: 711+712 | D11: =D9+D10 -> 11500000 | E11: =E9+E10 -> 10800000 | F11: =F9+F10 -> 11200000 | G11: =G9+G10 -> 12400000 | H11: =H9+H10 -> 11900000 | I11: =I9+I10 -> 12600000 | J11: =J9+J10 -> 12800000 | K11: =K9+K10 -> 11600000 | ... P11: =P9+P10 -> 14100000 | Q11: =SUM(E11:P11) -> 142000000
B12: Variation de stocks de produits (±) | C12: 713 | D12: =-SUMPRODUCT(((LEFT(Balance!$B$7:$B$400,3)="713"))*Balance!D$7:D$400) -> 100000 | E12: =-SUMPRODUCT(((LEFT(Balance!$B$7:$B$400,3)="713"))*Balance!E$7:E$400) -> 100000 | F12: =-SUMPRODUCT(((LEFT(Balance!$B$7:$B$400,3)="713"))*Balance!F$7:F$400) -> 200000 | G12: =-SUMPRODUCT(((LEFT(Balance!$B$7:$B$400,3)="713"))*Balance!G$7:G$400) -> 200000 | H12: =-SUMPRODUCT(((LEFT(Balance!$B$7:$B$400,3)="713"))*Balance!H$7:H$400) -> 100000 | I12: =-SUMPRODUCT(((LEFT(Balance!$B$7:$B$400,3)="713"))*Balance!I$7:I$400) -> 200000 | J12: =-SUMPRODUCT(((LEFT(Balance!$B$7:$B$400,3)="713"))*Balance!J$7:J$400) -> 100000 | K12: =-SUMPRODUCT(((LEFT(Balance!$B$7:$B$400,3)="713"))*Balance!K$7:K$400) -> 300000 | ... P12: =-SUMPRODUCT(((LEFT(Balance!$B$7:$B$400,3)="713"))*Balance!P$7:P$400) -> -400000 | Q12: =SUM(E12:P12) -> 1200000
B13: Immobilisations produites par l'entreprise pour elle-même | C13: 714 | D13: =-SUMPRODUCT(((LEFT(Balance!$B$7:$B$400,3)="714"))*Balance!D$7:D$400) -> 0 | E13: =-SUMPRODUCT(((LEFT(Balance!$B$7:$B$400,3)="714"))*Balance!E$7:E$400) -> 0 | F13: =-SUMPRODUCT(((LEFT(Balance!$B$7:$B$400,3)="714"))*Balance!F$7:F$400) -> 0 | G13: =-SUMPRODUCT(((LEFT(Balance!$B$7:$B$400,3)="714"))*Balance!G$7:G$400) -> 0 | H13: =-SUMPRODUCT(((LEFT(Balance!$B$7:$B$400,3)="714"))*Balance!H$7:H$400) -> 0 | I13: =-SUMPRODUCT(((LEFT(Balance!$B$7:$B$400,3)="714"))*Balance!I$7:I$400) -> 0 | J13: =-SUMPRODUCT(((LEFT(Balance!$B$7:$B$400,3)="714"))*Balance!J$7:J$400) -> 0 | K13: =-SUMPRODUCT(((LEFT(Balance!$B$7:$B$400,3)="714"))*Balance!K$7:K$400) -> 0 | ... P13: =-SUMPRODUCT(((LEFT(Balance!$B$7:$B$400,3)="714"))*Balance!P$7:P$400) -> 0 | Q13: =SUM(E13:P13) -> 0
B14: Subventions d'exploitation | C14: 716 | D14: =-SUMPRODUCT(((LEFT(Balance!$B$7:$B$400,3)="716"))*Balance!D$7:D$400) -> 0 | E14: =-SUMPRODUCT(((LEFT(Balance!$B$7:$B$400,3)="716"))*Balance!E$7:E$400) -> 0 | F14: =-SUMPRODUCT(((LEFT(Balance!$B$7:$B$400,3)="716"))*Balance!F$7:F$400) -> 0 | G14: =-SUMPRODUCT(((LEFT(Balance!$B$7:$B$400,3)="716"))*Balance!G$7:G$400) -> 0 | H14: =-SUMPRODUCT(((LEFT(Balance!$B$7:$B$400,3)="716"))*Balance!H$7:H$400) -> 0 | I14: =-SUMPRODUCT(((LEFT(Balance!$B$7:$B$400,3)="716"))*Balance!I$7:I$400) -> 0 | J14: =-SUMPRODUCT(((LEFT(Balance!$B$7:$B$400,3)="716"))*Balance!J$7:J$400) -> 250000 | K14: =-SUMPRODUCT(((LEFT(Balance!$B$7:$B$400,3)="716"))*Balance!K$7:K$400) -> 0 | ... P14: =-SUMPRODUCT(((LEFT(Balance!$B$7:$B$400,3)="716"))*Balance!P$7:P$400) -> 250000 | Q14: =SUM(E14:P14) -> 500000
B15: Autres produits d'exploitation | C15: 718 | D15: =-SUMPRODUCT(((LEFT(Balance!$B$7:$B$400,3)="718"))*Balance!D$7:D$400) -> 41666.67 | E15: =-SUMPRODUCT(((LEFT(Balance!$B$7:$B$400,3)="718"))*Balance!E$7:E$400) -> 41666.67 | F15: =-SUMPRODUCT(((LEFT(Balance!$B$7:$B$400,3)="718"))*Balance!F$7:F$400) -> 41666.67 | G15: =-SUMPRODUCT(((LEFT(Balance!$B$7:$B$400,3)="718"))*Balance!G$7:G$400) -> 41666.67 | H15: =-SUMPRODUCT(((LEFT(Balance!$B$7:$B$400,3)="718"))*Balance!H$7:H$400) -> 41666.67 | I15: =-SUMPRODUCT(((LEFT(Balance!$B$7:$B$400,3)="718"))*Balance!I$7:I$400) -> 41666.67 | J15: =-SUMPRODUCT(((LEFT(Balance!$B$7:$B$400,3)="718"))*Balance!J$7:J$400) -> 41666.67 | K15: =-SUMPRODUCT(((LEFT(Balance!$B$7:$B$400,3)="718"))*Balance!K$7:K$400) -> 41666.67 | ... P15: =-SUMPRODUCT(((LEFT(Balance!$B$7:$B$400,3)="718"))*Balance!P$7:P$400) -> 41666.67 | Q15: =SUM(E15:P15) -> 500000.04
B16: Reprises d'exploitation ; transferts de charges | C16: 719 | D16: =-SUMPRODUCT(((LEFT(Balance!$B$7:$B$400,3)="719"))*Balance!D$7:D$400) -> 0 | E16: =-SUMPRODUCT(((LEFT(Balance!$B$7:$B$400,3)="719"))*Balance!E$7:E$400) -> 0 | F16: =-SUMPRODUCT(((LEFT(Balance!$B$7:$B$400,3)="719"))*Balance!F$7:F$400) -> 0 | G16: =-SUMPRODUCT(((LEFT(Balance!$B$7:$B$400,3)="719"))*Balance!G$7:G$400) -> 150000 | H16: =-SUMPRODUCT(((LEFT(Balance!$B$7:$B$400,3)="719"))*Balance!H$7:H$400) -> 0 | I16: =-SUMPRODUCT(((LEFT(Balance!$B$7:$B$400,3)="719"))*Balance!I$7:I$400) -> 0 | J16: =-SUMPRODUCT(((LEFT(Balance!$B$7:$B$400,3)="719"))*Balance!J$7:J$400) -> 0 | K16: =-SUMPRODUCT(((LEFT(Balance!$B$7:$B$400,3)="719"))*Balance!K$7:K$400) -> 0 | ... P16: =-SUMPRODUCT(((LEFT(Balance!$B$7:$B$400,3)="719"))*Balance!P$7:P$400) -> 0 | Q16: =SUM(E16:P16) -> 300000
B17: TOTAL I | D17: =D11+D12+D13+D14+D15+D16 -> 11641667 | E17: =E11+E12+E13+E14+E15+E16 -> 10941667 | F17: =F11+F12+F13+F14+F15+F16 -> 11441667 | G17: =G11+G12+G13+G14+G15+G16 -> 12791667 | H17: =H11+H12+H13+H14+H15+H16 -> 12041667 | I17: =I11+I12+I13+I14+I15+I16 -> 12841667 | J17: =J11+J12+J13+J14+J15+J16 -> 13191667 | K17: =K11+K12+K13+K14+K15+K16 -> 11941667 | ... P17: =P11+P12+P13+P14+P15+P16 -> 13991667 | Q17: =SUM(E17:P17) -> 1.445e+08
B18: II CHARGES D'EXPLOITATION
B19: Achats revendus de marchandises | C19: 611 | D19: =SUMPRODUCT(((LEFT(Balance!$B$7:$B$400,3)="611"))*Balance!D$7:D$400) -> 33756.48 | E19: =SUMPRODUCT(((LEFT(Balance!$B$7:$B$400,3)="611"))*Balance!E$7:E$400) -> 32185.14 | F19: =SUMPRODUCT(((LEFT(Balance!$B$7:$B$400,3)="611"))*Balance!F$7:F$400) -> 33236.86 | G19: =SUMPRODUCT(((LEFT(Balance!$B$7:$B$400,3)="611"))*Balance!G$7:G$400) -> 37072.63 | H19: =SUMPRODUCT(((LEFT(Balance!$B$7:$B$400,3)="611"))*Balance!H$7:H$400) -> 35194.96 | I19: =SUMPRODUCT(((LEFT(Balance!$B$7:$B$400,3)="611"))*Balance!I$7:I$400) -> 37313.05 | J19: =SUMPRODUCT(((LEFT(Balance!$B$7:$B$400,3)="611"))*Balance!J$7:J$400) -> 37801.13 | K19: =SUMPRODUCT(((LEFT(Balance!$B$7:$B$400,3)="611"))*Balance!K$7:K$400) -> 34094.72 | ... P19: =SUMPRODUCT(((LEFT(Balance!$B$7:$B$400,3)="611"))*Balance!P$7:P$400) -> 41759.13 | Q19: =SUM(E19:P19) -> 420000
B20: Achats consommés de matières et fournitures | C20: 612 | D20: =SUMPRODUCT(((LEFT(Balance!$B$7:$B$400,3)="612"))*Balance!D$7:D$400) -> 5025676.6 | E20: =SUMPRODUCT(((LEFT(Balance!$B$7:$B$400,3)="612"))*Balance!E$7:E$400) -> 4551601.7 | F20: =SUMPRODUCT(((LEFT(Balance!$B$7:$B$400,3)="612"))*Balance!F$7:F$400) -> 4610348.9 | G20: =SUMPRODUCT(((LEFT(Balance!$B$7:$B$400,3)="612"))*Balance!G$7:G$400) -> 5093312 | H20: =SUMPRODUCT(((LEFT(Balance!$B$7:$B$400,3)="612"))*Balance!H$7:H$400) -> 5438439 | I20: =SUMPRODUCT(((LEFT(Balance!$B$7:$B$400,3)="612"))*Balance!I$7:I$400) -> 5452504.5 | J20: =SUMPRODUCT(((LEFT(Balance!$B$7:$B$400,3)="612"))*Balance!J$7:J$400) -> 5473004.6 | K20: =SUMPRODUCT(((LEFT(Balance!$B$7:$B$400,3)="612"))*Balance!K$7:K$400) -> 4884054.7 | ... P20: =SUMPRODUCT(((LEFT(Balance!$B$7:$B$400,3)="612"))*Balance!P$7:P$400) -> 6274389.2 | Q20: =SUM(E20:P20) -> 62000000
B21: Autres charges externes | C21: 613 / 614 | D21: =SUMPRODUCT(((LEFT(Balance!$B$7:$B$400,3)="613")+(LEFT(Balance!$B$7:$B$400,3)="614"))*Balance!D$7:D$400) -> 1158379.1 | E21: =SUMPRODUCT(((LEFT(Balance!$B$7:$B$400,3)="613")+(LEFT(Balance!$B$7:$B$400,3)="614"))*Balance!E$7:E$400) -> 1146546 | F21: =SUMPRODUCT(((LEFT(Balance!$B$7:$B$400,3)="613")+(LEFT(Balance!$B$7:$B$400,3)="614"))*Balance!F$7:F$400) -> 1122853.7 | G21: =SUMPRODUCT(((LEFT(Balance!$B$7:$B$400,3)="613")+(LEFT(Balance!$B$7:$B$400,3)="614"))*Balance!G$7:G$400) -> 1209678.1 | H21: =SUMPRODUCT(((LEFT(Balance!$B$7:$B$400,3)="613")+(LEFT(Balance!$B$7:$B$400,3)="614"))*Balance!H$7:H$400) -> 1164908.9 | I21: =SUMPRODUCT(((LEFT(Balance!$B$7:$B$400,3)="613")+(LEFT(Balance!$B$7:$B$400,3)="614"))*Balance!I$7:I$400) -> 1197993.7 | J21: =SUMPRODUCT(((LEFT(Balance!$B$7:$B$400,3)="613")+(LEFT(Balance!$B$7:$B$400,3)="614"))*Balance!J$7:J$400) -> 1185017.4 | K21: =SUMPRODUCT(((LEFT(Balance!$B$7:$B$400,3)="613")+(LEFT(Balance!$B$7:$B$400,3)="614"))*Balance!K$7:K$400) -> 1169684.8 | ... P21: =SUMPRODUCT(((LEFT(Balance!$B$7:$B$400,3)="613")+(LEFT(Balance!$B$7:$B$400,3)="614"))*Balance!P$7:P$400) -> 1231499.8 | Q21: =SUM(E21:P21) -> 14000000
B22: Impôts et taxes | C22: 616 | D22: =SUMPRODUCT(((LEFT(Balance!$B$7:$B$400,3)="616"))*Balance!D$7:D$400) -> 127825.77 | E22: =SUMPRODUCT(((LEFT(Balance!$B$7:$B$400,3)="616"))*Balance!E$7:E$400) -> 124008.07 | F22: =SUMPRODUCT(((LEFT(Balance!$B$7:$B$400,3)="616"))*Balance!F$7:F$400) -> 122433.54 | G22: =SUMPRODUCT(((LEFT(Balance!$B$7:$B$400,3)="616"))*Balance!G$7:G$400) -> 121085.58 | H22: =SUMPRODUCT(((LEFT(Balance!$B$7:$B$400,3)="616"))*Balance!H$7:H$400) -> 126320.6 | I22: =SUMPRODUCT(((LEFT(Balance!$B$7:$B$400,3)="616"))*Balance!I$7:I$400) -> 130520.87 | J22: =SUMPRODUCT(((LEFT(Balance!$B$7:$B$400,3)="616"))*Balance!J$7:J$400) -> 121765.77 | K22: =SUMPRODUCT(((LEFT(Balance!$B$7:$B$400,3)="616"))*Balance!K$7:K$400) -> 126809.99 | ... P22: =SUMPRODUCT(((LEFT(Balance!$B$7:$B$400,3)="616"))*Balance!P$7:P$400) -> 124656.9 | Q22: =SUM(E22:P22) -> 1500000
B23: Charges de personnel | C23: 617 | D23: =SUMPRODUCT(((LEFT(Balance!$B$7:$B$400,3)="617"))*Balance!D$7:D$400) -> 3979693.9 | E23: =SUMPRODUCT(((LEFT(Balance!$B$7:$B$400,3)="617"))*Balance!E$7:E$400) -> 3242539.6 | F23: =SUMPRODUCT(((LEFT(Balance!$B$7:$B$400,3)="617"))*Balance!F$7:F$400) -> 3247018.7 | G23: =SUMPRODUCT(((LEFT(Balance!$B$7:$B$400,3)="617"))*Balance!G$7:G$400) -> 3298230 | H23: =SUMPRODUCT(((LEFT(Balance!$B$7:$B$400,3)="617"))*Balance!H$7:H$400) -> 3270907.5 | I23: =SUMPRODUCT(((LEFT(Balance!$B$7:$B$400,3)="617"))*Balance!I$7:I$400) -> 3300900.7 | J23: =SUMPRODUCT(((LEFT(Balance!$B$7:$B$400,3)="617"))*Balance!J$7:J$400) -> 3270750.3 | K23: =SUMPRODUCT(((LEFT(Balance!$B$7:$B$400,3)="617"))*Balance!K$7:K$400) -> 3275585.1 | ... P23: =SUMPRODUCT(((LEFT(Balance!$B$7:$B$400,3)="617"))*Balance!P$7:P$400) -> 4155077.2 | Q23: =SUM(E23:P23) -> 40000000
B24: Autres charges d'exploitation | C24: 618 | D24: =SUMPRODUCT(((LEFT(Balance!$B$7:$B$400,3)="618"))*Balance!D$7:D$400) -> 0 | E24: =SUMPRODUCT(((LEFT(Balance!$B$7:$B$400,3)="618"))*Balance!E$7:E$400) -> 0 | F24: =SUMPRODUCT(((LEFT(Balance!$B$7:$B$400,3)="618"))*Balance!F$7:F$400) -> 0 | G24: =SUMPRODUCT(((LEFT(Balance!$B$7:$B$400,3)="618"))*Balance!G$7:G$400) -> 0 | H24: =SUMPRODUCT(((LEFT(Balance!$B$7:$B$400,3)="618"))*Balance!H$7:H$400) -> 0 | I24: =SUMPRODUCT(((LEFT(Balance!$B$7:$B$400,3)="618"))*Balance!I$7:I$400) -> 0 | J24: =SUMPRODUCT(((LEFT(Balance!$B$7:$B$400,3)="618"))*Balance!J$7:J$400) -> 0 | K24: =SUMPRODUCT(((LEFT(Balance!$B$7:$B$400,3)="618"))*Balance!K$7:K$400) -> 0 | ... P24: =SUMPRODUCT(((LEFT(Balance!$B$7:$B$400,3)="618"))*Balance!P$7:P$400) -> 0 | Q24: =SUM(E24:P24) -> 100000
B25: Dotations d'exploitation | C25: 619 | D25: =SUMPRODUCT(((LEFT(Balance!$B$7:$B$400,3)="619"))*Balance!D$7:D$400) -> 813333.33 | E25: =SUMPRODUCT(((LEFT(Balance!$B$7:$B$400,3)="619"))*Balance!E$7:E$400) -> 733333.33 | F25: =SUMPRODUCT(((LEFT(Balance!$B$7:$B$400,3)="619"))*Balance!F$7:F$400) -> 733333.33 | G25: =SUMPRODUCT(((LEFT(Balance!$B$7:$B$400,3)="619"))*Balance!G$7:G$400) -> 733333.33 | H25: =SUMPRODUCT(((LEFT(Balance!$B$7:$B$400,3)="619"))*Balance!H$7:H$400) -> 733333.33 | I25: =SUMPRODUCT(((LEFT(Balance!$B$7:$B$400,3)="619"))*Balance!I$7:I$400) -> 733333.33 | J25: =SUMPRODUCT(((LEFT(Balance!$B$7:$B$400,3)="619"))*Balance!J$7:J$400) -> 833333.33 | K25: =SUMPRODUCT(((LEFT(Balance!$B$7:$B$400,3)="619"))*Balance!K$7:K$400) -> 733333.33 | ... P25: =SUMPRODUCT(((LEFT(Balance!$B$7:$B$400,3)="619"))*Balance!P$7:P$400) -> 833333.33 | Q25: =SUM(E25:P25) -> 9000000
B26: TOTAL II | D26: =D19+D20+D21+D22+D23+D24+D25 -> 11138665 | E26: =E19+E20+E21+E22+E23+E24+E25 -> 9830213.8 | F26: =F19+F20+F21+F22+F23+F24+F25 -> 9869225.1 | G26: =G19+G20+G21+G22+G23+G24+G25 -> 10492712 | H26: =H19+H20+H21+H22+H23+H24+H25 -> 10769104 | I26: =I19+I20+I21+I22+I23+I24+I25 -> 10852566 | J26: =J19+J20+J21+J22+J23+J24+J25 -> 10921672 | K26: =K19+K20+K21+K22+K23+K24+K25 -> 10223563 | ... P26: =P19+P20+P21+P22+P23+P24+P25 -> 12660715 | Q26: =SUM(E26:P26) -> 1.2702e+08
B27: III RÉSULTAT D'EXPLOITATION (I − II) | D27: =D17-D26 -> 503001.5 | E27: =E17-E26 -> 1111452.9 | F27: =F17-F26 -> 1572441.6 | G27: =G17-G26 -> 2298955.1 | H27: =H17-H26 -> 1272562.4 | I27: =I17-I26 -> 1989100.6 | J27: =J17-J26 -> 2269994.2 | K27: =K17-K26 -> 1718104.1 | ... P27: =P17-P26 -> 1330951.2 | Q27: =SUM(E27:P27) -> 17480000
B28: FINANCIER
B29: IV PRODUITS FINANCIERS
B30: Produits des titres de participation et autres titres immobilisés | C30: 732 | D30: =-SUMPRODUCT(((LEFT(Balance!$B$7:$B$400,3)="732"))*Balance!D$7:D$400) -> 0 | E30: =-SUMPRODUCT(((LEFT(Balance!$B$7:$B$400,3)="732"))*Balance!E$7:E$400) -> 0 | F30: =-SUMPRODUCT(((LEFT(Balance!$B$7:$B$400,3)="732"))*Balance!F$7:F$400) -> 0 | G30: =-SUMPRODUCT(((LEFT(Balance!$B$7:$B$400,3)="732"))*Balance!G$7:G$400) -> 0 | H30: =-SUMPRODUCT(((LEFT(Balance!$B$7:$B$400,3)="732"))*Balance!H$7:H$400) -> 0 | I30: =-SUMPRODUCT(((LEFT(Balance!$B$7:$B$400,3)="732"))*Balance!I$7:I$400) -> 0 | J30: =-SUMPRODUCT(((LEFT(Balance!$B$7:$B$400,3)="732"))*Balance!J$7:J$400) -> 0 | K30: =-SUMPRODUCT(((LEFT(Balance!$B$7:$B$400,3)="732"))*Balance!K$7:K$400) -> 0 | ... P30: =-SUMPRODUCT(((LEFT(Balance!$B$7:$B$400,3)="732"))*Balance!P$7:P$400) -> 0 | Q30: =SUM(E30:P30) -> 0
B31: Gains de change | C31: 733 | D31: =-SUMPRODUCT(((LEFT(Balance!$B$7:$B$400,3)="733"))*Balance!D$7:D$400) -> 120000 | E31: =-SUMPRODUCT(((LEFT(Balance!$B$7:$B$400,3)="733"))*Balance!E$7:E$400) -> 120000 | F31: =-SUMPRODUCT(((LEFT(Balance!$B$7:$B$400,3)="733"))*Balance!F$7:F$400) -> 100000 | G31: =-SUMPRODUCT(((LEFT(Balance!$B$7:$B$400,3)="733"))*Balance!G$7:G$400) -> 40000 | H31: =-SUMPRODUCT(((LEFT(Balance!$B$7:$B$400,3)="733"))*Balance!H$7:H$400) -> 150000 | I31: =-SUMPRODUCT(((LEFT(Balance!$B$7:$B$400,3)="733"))*Balance!I$7:I$400) -> 130000 | J31: =-SUMPRODUCT(((LEFT(Balance!$B$7:$B$400,3)="733"))*Balance!J$7:J$400) -> 140000 | K31: =-SUMPRODUCT(((LEFT(Balance!$B$7:$B$400,3)="733"))*Balance!K$7:K$400) -> 110000 | ... P31: =-SUMPRODUCT(((LEFT(Balance!$B$7:$B$400,3)="733"))*Balance!P$7:P$400) -> 140000 | Q31: =SUM(E31:P31) -> 1400000
B32: Intérêts et autres produits financiers | C32: 738 | D32: =-SUMPRODUCT(((LEFT(Balance!$B$7:$B$400,3)="738"))*Balance!D$7:D$400) -> 20595.43 | E32: =-SUMPRODUCT(((LEFT(Balance!$B$7:$B$400,3)="738"))*Balance!E$7:E$400) -> 19582.63 | F32: =-SUMPRODUCT(((LEFT(Balance!$B$7:$B$400,3)="738"))*Balance!F$7:F$400) -> 20053.32 | G32: =-SUMPRODUCT(((LEFT(Balance!$B$7:$B$400,3)="738"))*Balance!G$7:G$400) -> 21389.3 | H32: =-SUMPRODUCT(((LEFT(Balance!$B$7:$B$400,3)="738"))*Balance!H$7:H$400) -> 21125.16 | I32: =-SUMPRODUCT(((LEFT(Balance!$B$7:$B$400,3)="738"))*Balance!I$7:I$400) -> 21604.6 | J32: =-SUMPRODUCT(((LEFT(Balance!$B$7:$B$400,3)="738"))*Balance!J$7:J$400) -> 21886.58 | K32: =-SUMPRODUCT(((LEFT(Balance!$B$7:$B$400,3)="738"))*Balance!K$7:K$400) -> 20833.48 | ... P32: =-SUMPRODUCT(((LEFT(Balance!$B$7:$B$400,3)="738"))*Balance!P$7:P$400) -> 23189.36 | Q32: =SUM(E32:P32) -> 249999.97
B33: Reprises financières ; transferts de charges | C33: 739 | D33: =-SUMPRODUCT(((LEFT(Balance!$B$7:$B$400,3)="739"))*Balance!D$7:D$400) -> 0 | E33: =-SUMPRODUCT(((LEFT(Balance!$B$7:$B$400,3)="739"))*Balance!E$7:E$400) -> 0 | F33: =-SUMPRODUCT(((LEFT(Balance!$B$7:$B$400,3)="739"))*Balance!F$7:F$400) -> 0 | G33: =-SUMPRODUCT(((LEFT(Balance!$B$7:$B$400,3)="739"))*Balance!G$7:G$400) -> 0 | H33: =-SUMPRODUCT(((LEFT(Balance!$B$7:$B$400,3)="739"))*Balance!H$7:H$400) -> 0 | I33: =-SUMPRODUCT(((LEFT(Balance!$B$7:$B$400,3)="739"))*Balance!I$7:I$400) -> 0 | J33: =-SUMPRODUCT(((LEFT(Balance!$B$7:$B$400,3)="739"))*Balance!J$7:J$400) -> 0 | K33: =-SUMPRODUCT(((LEFT(Balance!$B$7:$B$400,3)="739"))*Balance!K$7:K$400) -> 0 | ... P33: =-SUMPRODUCT(((LEFT(Balance!$B$7:$B$400,3)="739"))*Balance!P$7:P$400) -> 0 | Q33: =SUM(E33:P33) -> 0
B34: TOTAL IV | D34: =D30+D31+D32+D33 -> 140595.43 | E34: =E30+E31+E32+E33 -> 139582.63 | F34: =F30+F31+F32+F33 -> 120053.32 | G34: =G30+G31+G32+G33 -> 61389.3 | H34: =H30+H31+H32+H33 -> 171125.16 | I34: =I30+I31+I32+I33 -> 151604.6 | J34: =J30+J31+J32+J33 -> 161886.58 | K34: =K30+K31+K32+K33 -> 130833.48 | ... P34: =P30+P31+P32+P33 -> 163189.36 | Q34: =SUM(E34:P34) -> 1650000
B35: V CHARGES FINANCIÈRES
B36: Charges d'intérêts | C36: 631 | D36: =SUMPRODUCT(((LEFT(Balance!$B$7:$B$400,3)="631"))*Balance!D$7:D$400) -> 282826.99 | E36: =SUMPRODUCT(((LEFT(Balance!$B$7:$B$400,3)="631"))*Balance!E$7:E$400) -> 280012.79 | F36: =SUMPRODUCT(((LEFT(Balance!$B$7:$B$400,3)="631"))*Balance!F$7:F$400) -> 277198.59 | G36: =SUMPRODUCT(((LEFT(Balance!$B$7:$B$400,3)="631"))*Balance!G$7:G$400) -> 274384.39 | H36: =SUMPRODUCT(((LEFT(Balance!$B$7:$B$400,3)="631"))*Balance!H$7:H$400) -> 271570.2 | I36: =SUMPRODUCT(((LEFT(Balance!$B$7:$B$400,3)="631"))*Balance!I$7:I$400) -> 268756 | J36: =SUMPRODUCT(((LEFT(Balance!$B$7:$B$400,3)="631"))*Balance!J$7:J$400) -> 265941.8 | K36: =SUMPRODUCT(((LEFT(Balance!$B$7:$B$400,3)="631"))*Balance!K$7:K$400) -> 265685.96 | ... P36: =SUMPRODUCT(((LEFT(Balance!$B$7:$B$400,3)="631"))*Balance!P$7:P$400) -> 249056.6 | Q36: =SUM(E36:P36) -> 3200000
B37: Pertes de change | C37: 633 | D37: =SUMPRODUCT(((LEFT(Balance!$B$7:$B$400,3)="633"))*Balance!D$7:D$400) -> 100000 | E37: =SUMPRODUCT(((LEFT(Balance!$B$7:$B$400,3)="633"))*Balance!E$7:E$400) -> 50000 | F37: =SUMPRODUCT(((LEFT(Balance!$B$7:$B$400,3)="633"))*Balance!F$7:F$400) -> 80000 | G37: =SUMPRODUCT(((LEFT(Balance!$B$7:$B$400,3)="633"))*Balance!G$7:G$400) -> 750000 | H37: =SUMPRODUCT(((LEFT(Balance!$B$7:$B$400,3)="633"))*Balance!H$7:H$400) -> 100000 | I37: =SUMPRODUCT(((LEFT(Balance!$B$7:$B$400,3)="633"))*Balance!I$7:I$400) -> 80000 | J37: =SUMPRODUCT(((LEFT(Balance!$B$7:$B$400,3)="633"))*Balance!J$7:J$400) -> 60000 | K37: =SUMPRODUCT(((LEFT(Balance!$B$7:$B$400,3)="633"))*Balance!K$7:K$400) -> 100000 | ... P37: =SUMPRODUCT(((LEFT(Balance!$B$7:$B$400,3)="633"))*Balance!P$7:P$400) -> 70000 | Q37: =SUM(E37:P37) -> 1800000
B38: Autres charges financières | C38: 638 | D38: =SUMPRODUCT(((LEFT(Balance!$B$7:$B$400,3)="638"))*Balance!D$7:D$400) -> 12220.52 | E38: =SUMPRODUCT(((LEFT(Balance!$B$7:$B$400,3)="638"))*Balance!E$7:E$400) -> 11434.78 | F38: =SUMPRODUCT(((LEFT(Balance!$B$7:$B$400,3)="638"))*Balance!F$7:F$400) -> 11936.62 | G38: =SUMPRODUCT(((LEFT(Balance!$B$7:$B$400,3)="638"))*Balance!G$7:G$400) -> 13294 | H38: =SUMPRODUCT(((LEFT(Balance!$B$7:$B$400,3)="638"))*Balance!H$7:H$400) -> 12619.19 | I38: =SUMPRODUCT(((LEFT(Balance!$B$7:$B$400,3)="638"))*Balance!I$7:I$400) -> 13246.78 | J38: =SUMPRODUCT(((LEFT(Balance!$B$7:$B$400,3)="638"))*Balance!J$7:J$400) -> 13584.99 | K38: =SUMPRODUCT(((LEFT(Balance!$B$7:$B$400,3)="638"))*Balance!K$7:K$400) -> 12223.61 | ... P38: =SUMPRODUCT(((LEFT(Balance!$B$7:$B$400,3)="638"))*Balance!P$7:P$400) -> 14569.51 | Q38: =SUM(E38:P38) -> 150000
B39: Dotations financières | C39: 639 | D39: =SUMPRODUCT(((LEFT(Balance!$B$7:$B$400,3)="639"))*Balance!D$7:D$400) -> 0 | E39: =SUMPRODUCT(((LEFT(Balance!$B$7:$B$400,3)="639"))*Balance!E$7:E$400) -> 0 | F39: =SUMPRODUCT(((LEFT(Balance!$B$7:$B$400,3)="639"))*Balance!F$7:F$400) -> 0 | G39: =SUMPRODUCT(((LEFT(Balance!$B$7:$B$400,3)="639"))*Balance!G$7:G$400) -> 0 | H39: =SUMPRODUCT(((LEFT(Balance!$B$7:$B$400,3)="639"))*Balance!H$7:H$400) -> 0 | I39: =SUMPRODUCT(((LEFT(Balance!$B$7:$B$400,3)="639"))*Balance!I$7:I$400) -> 0 | J39: =SUMPRODUCT(((LEFT(Balance!$B$7:$B$400,3)="639"))*Balance!J$7:J$400) -> 0 | K39: =SUMPRODUCT(((LEFT(Balance!$B$7:$B$400,3)="639"))*Balance!K$7:K$400) -> 0 | ... P39: =SUMPRODUCT(((LEFT(Balance!$B$7:$B$400,3)="639"))*Balance!P$7:P$400) -> 0 | Q39: =SUM(E39:P39) -> 0
B40: TOTAL V | D40: =D36+D37+D38+D39 -> 395047.51 | E40: =E36+E37+E38+E39 -> 341447.57 | F40: =F36+F37+F38+F39 -> 369135.21 | G40: =G36+G37+G38+G39 -> 1037678.4 | H40: =H36+H37+H38+H39 -> 384189.39 | I40: =I36+I37+I38+I39 -> 362002.78 | J40: =J36+J37+J38+J39 -> 339526.79 | K40: =K36+K37+K38+K39 -> 377909.57 | ... P40: =P36+P37+P38+P39 -> 333626.11 | Q40: =SUM(E40:P40) -> 5150000
B41: VI RÉSULTAT FINANCIER (IV − V) | D41: =D34-D40 -> -254452.08 | E41: =E34-E40 -> -201864.94 | F41: =F34-F40 -> -249081.89 | G41: =G34-G40 -> -976289.09 | H41: =H34-H40 -> -213064.23 | I41: =I34-I40 -> -210398.18 | J41: =J34-J40 -> -177640.21 | K41: =K34-K40 -> -247076.09 | ... P41: =P34-P40 -> -170436.75 | Q41: =SUM(E41:P41) -> -3500000
B42: VII RÉSULTAT COURANT (III + VI) | D42: =D27+D41 -> 248549.42 | E42: =E27+E41 -> 909587.95 | F42: =F27+F41 -> 1323359.7 | G42: =G27+G41 -> 1322666 | H42: =H27+H41 -> 1059498.2 | I42: =I27+I41 -> 1778702.4 | J42: =J27+J41 -> 2092354 | K42: =K27+K41 -> 1471028 | ... P42: =P27+P41 -> 1160514.4 | Q42: =SUM(E42:P42) -> 13980000
B43: NON COURANT
B44: VIII PRODUITS NON COURANTS
B45: Produits des cessions d'immobilisations | C45: 751 | D45: =-SUMPRODUCT(((LEFT(Balance!$B$7:$B$400,3)="751"))*Balance!D$7:D$400) -> 0 | E45: =-SUMPRODUCT(((LEFT(Balance!$B$7:$B$400,3)="751"))*Balance!E$7:E$400) -> 0 | F45: =-SUMPRODUCT(((LEFT(Balance!$B$7:$B$400,3)="751"))*Balance!F$7:F$400) -> 0 | G45: =-SUMPRODUCT(((LEFT(Balance!$B$7:$B$400,3)="751"))*Balance!G$7:G$400) -> 0 | H45: =-SUMPRODUCT(((LEFT(Balance!$B$7:$B$400,3)="751"))*Balance!H$7:H$400) -> 0 | I45: =-SUMPRODUCT(((LEFT(Balance!$B$7:$B$400,3)="751"))*Balance!I$7:I$400) -> 0 | J45: =-SUMPRODUCT(((LEFT(Balance!$B$7:$B$400,3)="751"))*Balance!J$7:J$400) -> 0 | K45: =-SUMPRODUCT(((LEFT(Balance!$B$7:$B$400,3)="751"))*Balance!K$7:K$400) -> 0 | ... P45: =-SUMPRODUCT(((LEFT(Balance!$B$7:$B$400,3)="751"))*Balance!P$7:P$400) -> 0 | Q45: =SUM(E45:P45) -> 300000
B46: Subventions d'équilibre | C46: 756 | D46: =-SUMPRODUCT(((LEFT(Balance!$B$7:$B$400,3)="756"))*Balance!D$7:D$400) -> 0 | E46: =-SUMPRODUCT(((LEFT(Balance!$B$7:$B$400,3)="756"))*Balance!E$7:E$400) -> 0 | F46: =-SUMPRODUCT(((LEFT(Balance!$B$7:$B$400,3)="756"))*Balance!F$7:F$400) -> 0 | G46: =-SUMPRODUCT(((LEFT(Balance!$B$7:$B$400,3)="756"))*Balance!G$7:G$400) -> 0 | H46: =-SUMPRODUCT(((LEFT(Balance!$B$7:$B$400,3)="756"))*Balance!H$7:H$400) -> 0 | I46: =-SUMPRODUCT(((LEFT(Balance!$B$7:$B$400,3)="756"))*Balance!I$7:I$400) -> 0 | J46: =-SUMPRODUCT(((LEFT(Balance!$B$7:$B$400,3)="756"))*Balance!J$7:J$400) -> 0 | K46: =-SUMPRODUCT(((LEFT(Balance!$B$7:$B$400,3)="756"))*Balance!K$7:K$400) -> 0 | ... P46: =-SUMPRODUCT(((LEFT(Balance!$B$7:$B$400,3)="756"))*Balance!P$7:P$400) -> 0 | Q46: =SUM(E46:P46) -> 0
B47: Reprises sur subventions d'investissement | C47: 757 | D47: =-SUMPRODUCT(((LEFT(Balance!$B$7:$B$400,3)="757"))*Balance!D$7:D$400) -> 10000 | E47: =-SUMPRODUCT(((LEFT(Balance!$B$7:$B$400,3)="757"))*Balance!E$7:E$400) -> 10000 | F47: =-SUMPRODUCT(((LEFT(Balance!$B$7:$B$400,3)="757"))*Balance!F$7:F$400) -> 10000 | G47: =-SUMPRODUCT(((LEFT(Balance!$B$7:$B$400,3)="757"))*Balance!G$7:G$400) -> 10000 | H47: =-SUMPRODUCT(((LEFT(Balance!$B$7:$B$400,3)="757"))*Balance!H$7:H$400) -> 10000 | I47: =-SUMPRODUCT(((LEFT(Balance!$B$7:$B$400,3)="757"))*Balance!I$7:I$400) -> 10000 | J47: =-SUMPRODUCT(((LEFT(Balance!$B$7:$B$400,3)="757"))*Balance!J$7:J$400) -> 10000 | K47: =-SUMPRODUCT(((LEFT(Balance!$B$7:$B$400,3)="757"))*Balance!K$7:K$400) -> 10000 | ... P47: =-SUMPRODUCT(((LEFT(Balance!$B$7:$B$400,3)="757"))*Balance!P$7:P$400) -> 10000 | Q47: =SUM(E47:P47) -> 120000
B48: Autres produits non courants | C48: 758 | D48: =-SUMPRODUCT(((LEFT(Balance!$B$7:$B$400,3)="758"))*Balance!D$7:D$400) -> 0 | E48: =-SUMPRODUCT(((LEFT(Balance!$B$7:$B$400,3)="758"))*Balance!E$7:E$400) -> 0 | F48: =-SUMPRODUCT(((LEFT(Balance!$B$7:$B$400,3)="758"))*Balance!F$7:F$400) -> 0 | G48: =-SUMPRODUCT(((LEFT(Balance!$B$7:$B$400,3)="758"))*Balance!G$7:G$400) -> 0 | H48: =-SUMPRODUCT(((LEFT(Balance!$B$7:$B$400,3)="758"))*Balance!H$7:H$400) -> 0 | I48: =-SUMPRODUCT(((LEFT(Balance!$B$7:$B$400,3)="758"))*Balance!I$7:I$400) -> 0 | J48: =-SUMPRODUCT(((LEFT(Balance!$B$7:$B$400,3)="758"))*Balance!J$7:J$400) -> 0 | K48: =-SUMPRODUCT(((LEFT(Balance!$B$7:$B$400,3)="758"))*Balance!K$7:K$400) -> 0 | ... P48: =-SUMPRODUCT(((LEFT(Balance!$B$7:$B$400,3)="758"))*Balance!P$7:P$400) -> 0 | Q48: =SUM(E48:P48) -> 0
B49: Reprises non courantes ; transferts de charges | C49: 759 | D49: =-SUMPRODUCT(((LEFT(Balance!$B$7:$B$400,3)="759"))*Balance!D$7:D$400) -> 0 | E49: =-SUMPRODUCT(((LEFT(Balance!$B$7:$B$400,3)="759"))*Balance!E$7:E$400) -> 0 | F49: =-SUMPRODUCT(((LEFT(Balance!$B$7:$B$400,3)="759"))*Balance!F$7:F$400) -> 0 | G49: =-SUMPRODUCT(((LEFT(Balance!$B$7:$B$400,3)="759"))*Balance!G$7:G$400) -> 0 | H49: =-SUMPRODUCT(((LEFT(Balance!$B$7:$B$400,3)="759"))*Balance!H$7:H$400) -> 0 | I49: =-SUMPRODUCT(((LEFT(Balance!$B$7:$B$400,3)="759"))*Balance!I$7:I$400) -> 0 | J49: =-SUMPRODUCT(((LEFT(Balance!$B$7:$B$400,3)="759"))*Balance!J$7:J$400) -> 0 | K49: =-SUMPRODUCT(((LEFT(Balance!$B$7:$B$400,3)="759"))*Balance!K$7:K$400) -> 0 | ... P49: =-SUMPRODUCT(((LEFT(Balance!$B$7:$B$400,3)="759"))*Balance!P$7:P$400) -> 0 | Q49: =SUM(E49:P49) -> 0
B50: TOTAL VIII | D50: =D45+D46+D47+D48+D49 -> 10000 | E50: =E45+E46+E47+E48+E49 -> 10000 | F50: =F45+F46+F47+F48+F49 -> 10000 | G50: =G45+G46+G47+G48+G49 -> 10000 | H50: =H45+H46+H47+H48+H49 -> 10000 | I50: =I45+I46+I47+I48+I49 -> 10000 | J50: =J45+J46+J47+J48+J49 -> 10000 | K50: =K45+K46+K47+K48+K49 -> 10000 | ... P50: =P45+P46+P47+P48+P49 -> 10000 | Q50: =SUM(E50:P50) -> 420000
B51: IX CHARGES NON COURANTES
B52: Valeurs nettes d'amortissements des immobilisations cédées | C52: 651 | D52: =SUMPRODUCT(((LEFT(Balance!$B$7:$B$400,3)="651"))*Balance!D$7:D$400) -> 0 | E52: =SUMPRODUCT(((LEFT(Balance!$B$7:$B$400,3)="651"))*Balance!E$7:E$400) -> 0 | F52: =SUMPRODUCT(((LEFT(Balance!$B$7:$B$400,3)="651"))*Balance!F$7:F$400) -> 0 | G52: =SUMPRODUCT(((LEFT(Balance!$B$7:$B$400,3)="651"))*Balance!G$7:G$400) -> 0 | H52: =SUMPRODUCT(((LEFT(Balance!$B$7:$B$400,3)="651"))*Balance!H$7:H$400) -> 0 | I52: =SUMPRODUCT(((LEFT(Balance!$B$7:$B$400,3)="651"))*Balance!I$7:I$400) -> 0 | J52: =SUMPRODUCT(((LEFT(Balance!$B$7:$B$400,3)="651"))*Balance!J$7:J$400) -> 0 | K52: =SUMPRODUCT(((LEFT(Balance!$B$7:$B$400,3)="651"))*Balance!K$7:K$400) -> 0 | ... P52: =SUMPRODUCT(((LEFT(Balance!$B$7:$B$400,3)="651"))*Balance!P$7:P$400) -> 0 | Q52: =SUM(E52:P52) -> 250000
B53: Subventions accordées | C53: 656 | D53: =SUMPRODUCT(((LEFT(Balance!$B$7:$B$400,3)="656"))*Balance!D$7:D$400) -> 0 | E53: =SUMPRODUCT(((LEFT(Balance!$B$7:$B$400,3)="656"))*Balance!E$7:E$400) -> 0 | F53: =SUMPRODUCT(((LEFT(Balance!$B$7:$B$400,3)="656"))*Balance!F$7:F$400) -> 0 | G53: =SUMPRODUCT(((LEFT(Balance!$B$7:$B$400,3)="656"))*Balance!G$7:G$400) -> 0 | H53: =SUMPRODUCT(((LEFT(Balance!$B$7:$B$400,3)="656"))*Balance!H$7:H$400) -> 0 | I53: =SUMPRODUCT(((LEFT(Balance!$B$7:$B$400,3)="656"))*Balance!I$7:I$400) -> 0 | J53: =SUMPRODUCT(((LEFT(Balance!$B$7:$B$400,3)="656"))*Balance!J$7:J$400) -> 0 | K53: =SUMPRODUCT(((LEFT(Balance!$B$7:$B$400,3)="656"))*Balance!K$7:K$400) -> 0 | ... P53: =SUMPRODUCT(((LEFT(Balance!$B$7:$B$400,3)="656"))*Balance!P$7:P$400) -> 0 | Q53: =SUM(E53:P53) -> 0
B54: Autres charges non courantes | C54: 658 | D54: =SUMPRODUCT(((LEFT(Balance!$B$7:$B$400,3)="658"))*Balance!D$7:D$400) -> 0 | E54: =SUMPRODUCT(((LEFT(Balance!$B$7:$B$400,3)="658"))*Balance!E$7:E$400) -> 0 | F54: =SUMPRODUCT(((LEFT(Balance!$B$7:$B$400,3)="658"))*Balance!F$7:F$400) -> 0 | G54: =SUMPRODUCT(((LEFT(Balance!$B$7:$B$400,3)="658"))*Balance!G$7:G$400) -> 0 | H54: =SUMPRODUCT(((LEFT(Balance!$B$7:$B$400,3)="658"))*Balance!H$7:H$400) -> 0 | I54: =SUMPRODUCT(((LEFT(Balance!$B$7:$B$400,3)="658"))*Balance!I$7:I$400) -> 0 | J54: =SUMPRODUCT(((LEFT(Balance!$B$7:$B$400,3)="658"))*Balance!J$7:J$400) -> 0 | K54: =SUMPRODUCT(((LEFT(Balance!$B$7:$B$400,3)="658"))*Balance!K$7:K$400) -> 0 | ... P54: =SUMPRODUCT(((LEFT(Balance!$B$7:$B$400,3)="658"))*Balance!P$7:P$400) -> 0 | Q54: =SUM(E54:P54) -> 450000
B55: Dotations non courantes aux amortissements et aux provisions | C55: 659 | D55: =SUMPRODUCT(((LEFT(Balance!$B$7:$B$400,3)="659"))*Balance!D$7:D$400) -> 0 | E55: =SUMPRODUCT(((LEFT(Balance!$B$7:$B$400,3)="659"))*Balance!E$7:E$400) -> 0 | F55: =SUMPRODUCT(((LEFT(Balance!$B$7:$B$400,3)="659"))*Balance!F$7:F$400) -> 0 | G55: =SUMPRODUCT(((LEFT(Balance!$B$7:$B$400,3)="659"))*Balance!G$7:G$400) -> 0 | H55: =SUMPRODUCT(((LEFT(Balance!$B$7:$B$400,3)="659"))*Balance!H$7:H$400) -> 0 | I55: =SUMPRODUCT(((LEFT(Balance!$B$7:$B$400,3)="659"))*Balance!I$7:I$400) -> 0 | J55: =SUMPRODUCT(((LEFT(Balance!$B$7:$B$400,3)="659"))*Balance!J$7:J$400) -> 0 | K55: =SUMPRODUCT(((LEFT(Balance!$B$7:$B$400,3)="659"))*Balance!K$7:K$400) -> 0 | ... P55: =SUMPRODUCT(((LEFT(Balance!$B$7:$B$400,3)="659"))*Balance!P$7:P$400) -> 0 | Q55: =SUM(E55:P55) -> 0
B56: TOTAL IX | D56: =D52+D53+D54+D55 -> 0 | E56: =E52+E53+E54+E55 -> 0 | F56: =F52+F53+F54+F55 -> 0 | G56: =G52+G53+G54+G55 -> 0 | H56: =H52+H53+H54+H55 -> 0 | I56: =I52+I53+I54+I55 -> 0 | J56: =J52+J53+J54+J55 -> 0 | K56: =K52+K53+K54+K55 -> 0 | ... P56: =P52+P53+P54+P55 -> 0 | Q56: =SUM(E56:P56) -> 700000
B57: X RÉSULTAT NON COURANT (VIII − IX) | D57: =D50-D56 -> 10000 | E57: =E50-E56 -> 10000 | F57: =F50-F56 -> 10000 | G57: =G50-G56 -> 10000 | H57: =H50-H56 -> 10000 | I57: =I50-I56 -> 10000 | J57: =J50-J56 -> 10000 | K57: =K50-K56 -> 10000 | ... P57: =P50-P56 -> 10000 | Q57: =SUM(E57:P57) -> -280000
B58: XI RÉSULTAT AVANT IMPÔTS (VII + X) | D58: =D42+D57 -> 258549.42 | E58: =E42+E57 -> 919587.95 | F58: =F42+F57 -> 1333359.7 | G58: =G42+G57 -> 1332666 | H58: =H42+H57 -> 1069498.2 | I58: =I42+I57 -> 1788702.4 | J58: =J42+J57 -> 2102354 | K58: =K42+K57 -> 1481028 | ... P58: =P42+P57 -> 1170514.4 | Q58: =SUM(E58:P58) -> 13700000
B59: XII IMPÔTS SUR LES RÉSULTATS | C59: 670 | D59: =SUMPRODUCT(((LEFT(Balance!$B$7:$B$400,3)="670"))*Balance!D$7:D$400) -> 51709.88 | E59: =SUMPRODUCT(((LEFT(Balance!$B$7:$B$400,3)="670"))*Balance!E$7:E$400) -> 183917.58 | F59: =SUMPRODUCT(((LEFT(Balance!$B$7:$B$400,3)="670"))*Balance!F$7:F$400) -> 266671.94 | G59: =SUMPRODUCT(((LEFT(Balance!$B$7:$B$400,3)="670"))*Balance!G$7:G$400) -> 266533.19 | H59: =SUMPRODUCT(((LEFT(Balance!$B$7:$B$400,3)="670"))*Balance!H$7:H$400) -> 213899.64 | I59: =SUMPRODUCT(((LEFT(Balance!$B$7:$B$400,3)="670"))*Balance!I$7:I$400) -> 357740.48 | J59: =SUMPRODUCT(((LEFT(Balance!$B$7:$B$400,3)="670"))*Balance!J$7:J$400) -> 420470.8 | K59: =SUMPRODUCT(((LEFT(Balance!$B$7:$B$400,3)="670"))*Balance!K$7:K$400) -> 296205.59 | ... P59: =SUMPRODUCT(((LEFT(Balance!$B$7:$B$400,3)="670"))*Balance!P$7:P$400) -> 234102.89 | Q59: =SUM(E59:P59) -> 2740000
B60: XIII RÉSULTAT NET (XI − XII) | D60: =D58-D59 -> 206839.54 | E60: =E58-E59 -> 735670.37 | F60: =F58-F59 -> 1066687.8 | G60: =G58-G59 -> 1066132.8 | H60: =H58-H59 -> 855598.55 | I60: =I58-I59 -> 1430961.9 | J60: =J58-J59 -> 1681883.2 | K60: =K58-K59 -> 1184822.4 | ... P60: =P58-P59 -> 936411.55 | Q60: =SUM(E60:P60) -> 10960000
B61: TOTAUX
B62: XIV TOTAL DES PRODUITS (I + IV + VIII) | D62: =D17+D34+D50 -> 11792262 | E62: =E17+E34+E50 -> 11091249 | F62: =F17+F34+F50 -> 11571720 | G62: =G17+G34+G50 -> 12863056 | H62: =H17+H34+H50 -> 12222792 | I62: =I17+I34+I50 -> 13003271 | J62: =J17+J34+J50 -> 13363553 | K62: =K17+K34+K50 -> 12082500 | ... P62: =P17+P34+P50 -> 14164856 | Q62: =SUM(E62:P62) -> 1.4657e+08
B63: XV TOTAL DES CHARGES (II + V + IX + XII) | D63: =D26+D40+D56+D59 -> 11585423 | E63: =E26+E40+E56+E59 -> 10355579 | F63: =F26+F40+F56+F59 -> 10505032 | G63: =G26+G40+G56+G59 -> 11796923 | H63: =H26+H40+H56+H59 -> 11367193 | I63: =I26+I40+I56+I59 -> 11572309 | J63: =J26+J40+J56+J59 -> 11681670 | K63: =K26+K40+K56+K59 -> 10897678 | ... P63: =P26+P40+P56+P59 -> 13228444 | Q63: =SUM(E63:P63) -> 1.3561e+08
B64: XVI RÉSULTAT NET (XIV − XV) | D64: =D62-D63 -> 206839.54 | E64: =E62-E63 -> 735670.37 | F64: =F62-F63 -> 1066687.8 | G64: =G62-G63 -> 1066132.8 | H64: =H62-H63 -> 855598.55 | I64: =I62-I63 -> 1430961.9 | J64: =J62-J63 -> 1681883.2 | K64: =K62-K63 -> 1184822.4 | ... P64: =P62-P63 -> 936411.55 | Q64: =SUM(E64:P64) -> 10960000
B66: CONTRÔLE : Résultat net CPC − Résultat Balance (−Σ classes 6 et 7) = 0 | D66: =ROUND(D60+(SUMPRODUCT((LEFT(Balance!$B$7:$B$400,1)="6")*Balance!D$7:D$400)+SUMPRODUCT((LEFT(Balance!$B$7:$B$400,1)="7")*Balance!D$7:D$400)),2) -> 0 | E66: =ROUND(E60+(SUMPRODUCT((LEFT(Balance!$B$7:$B$400,1)="6")*Balance!E$7:E$400)+SUMPRODUCT((LEFT(Balance!$B$7:$B$400,1)="7")*Balance!E$7:E$400)),2) -> 0 | F66: =ROUND(F60+(SUMPRODUCT((LEFT(Balance!$B$7:$B$400,1)="6")*Balance!F$7:F$400)+SUMPRODUCT((LEFT(Balance!$B$7:$B$400,1)="7")*Balance!F$7:F$400)),2) -> 0 | G66: =ROUND(G60+(SUMPRODUCT((LEFT(Balance!$B$7:$B$400,1)="6")*Balance!G$7:G$400)+SUMPRODUCT((LEFT(Balance!$B$7:$B$400,1)="7")*Balance!G$7:G$400)),2) -> 0 | H66: =ROUND(H60+(SUMPRODUCT((LEFT(Balance!$B$7:$B$400,1)="6")*Balance!H$7:H$400)+SUMPRODUCT((LEFT(Balance!$B$7:$B$400,1)="7")*Balance!H$7:H$400)),2) -> 0 | I66: =ROUND(I60+(SUMPRODUCT((LEFT(Balance!$B$7:$B$400,1)="6")*Balance!I$7:I$400)+SUMPRODUCT((LEFT(Balance!$B$7:$B$400,1)="7")*Balance!I$7:I$400)),2) -> 0 | J66: =ROUND(J60+(SUMPRODUCT((LEFT(Balance!$B$7:$B$400,1)="6")*Balance!J$7:J$400)+SUMPRODUCT((LEFT(Balance!$B$7:$B$400,1)="7")*Balance!J$7:J$400)),2) -> 0 | K66: =ROUND(K60+(SUMPRODUCT((LEFT(Balance!$B$7:$B$400,1)="6")*Balance!K$7:K$400)+SUMPRODUCT((LEFT(Balance!$B$7:$B$400,1)="7")*Balance!K$7:K$400)),2) -> 0 | ... P66: =ROUND(P60+(SUMPRODUCT((LEFT(Balance!$B$7:$B$400,1)="6")*Balance!P$7:P$400)+SUMPRODUCT((LEFT(Balance!$B$7:$B$400,1)="7")*Balance!P$7:P$400)),2) -> 0 | Q66: =ROUND(SUM(E66:P66),2) -> 0
B67: Signes : produits et charges présentés en valeur positive (signes de la Balance inversés pour les produits). Résultats négatifs précédés de « − ».

Sheet ESG
B1: ÉTAT DES SOLDES DE GESTION (ESG) — MODÈLE CGNC
B2: ="Société : "&Accueil!$C$8&" │ Exercice : "&Accueil!$C$11&" │ Date d'arrêté : "&Accueil!$C$12&" │ Responsable : "&Accueil!$C$15 -> Société : AéroAtlas Composites SARL │ Exercice : 2025 │ Date d'arrêté : 31/12/2025 │ Responsable : Karim El Fassi (DAF)
B4: ← Accueil | C4: I. Tableau de formation des résultats (TFR) │ II. Capacité d'autofinancement (CAF) — Autofinancement │ Liens : CPC + Balance
B6: Soldes de gestion | C6: Réf. | D6: Déc. N-1 | E6: Janvier | F6: Février | G6: Mars | H6: Avril | I6: Mai | J6: Juin | K6: Juillet | L6: Août | M6: Septembre | N6: Octobre | O6: Novembre | P6: Décembre | Q6: TOTAL 2025
B7: I. TABLEAU DE FORMATION DES RÉSULTATS (TFR)
B8: 1 Ventes de marchandises (en l'état) | C8: CPC | D8: =CPC!D9 -> 48759.93 | E8: =CPC!E9 -> 46033.13 | F8: =CPC!F9 -> 47260.36 | G8: =CPC!G9 -> 51367.28 | H8: =CPC!H9 -> 48774.59 | I8: =CPC!I9 -> 54751.3 | J8: =CPC!J9 -> 54310.72 | K8: =CPC!K9 -> 47737.13 | ... P8: =CPC!P9 -> 58145.28 | Q8: =SUM(E8:P8) -> 597614.05
B9: 2 − Achats revendus de marchandises | C9: CPC | D9: =CPC!D19 -> 33756.48 | E9: =CPC!E19 -> 32185.14 | F9: =CPC!F19 -> 33236.86 | G9: =CPC!G19 -> 37072.63 | H9: =CPC!H19 -> 35194.96 | I9: =CPC!I19 -> 37313.05 | J9: =CPC!J19 -> 37801.13 | K9: =CPC!K19 -> 34094.72 | ... P9: =CPC!P19 -> 41759.13 | Q9: =SUM(E9:P9) -> 420000
B10: I = MARGE BRUTE SUR VENTES EN L'ÉTAT | D10: =D8-D9 -> 15003.45 | E10: =E8-E9 -> 13847.99 | F10: =F8-F9 -> 14023.5 | G10: =G8-G9 -> 14294.65 | H10: =H8-H9 -> 13579.63 | I10: =I8-I9 -> 17438.25 | J10: =J8-J9 -> 16509.59 | K10: =K8-K9 -> 13642.41 | ... P10: =P8-P9 -> 16386.15 | Q10: =SUM(E10:P10) -> 177614.05
B11: 3 Ventes de biens et services produits | C11: CPC | D11: =CPC!D10 -> 11451240 | E11: =CPC!E10 -> 10753967 | F11: =CPC!F10 -> 11152740 | G11: =CPC!G10 -> 12348633 | H11: =CPC!H10 -> 11851225 | I11: =CPC!I10 -> 12545249 | J11: =CPC!J10 -> 12745689 | K11: =CPC!K10 -> 11552263 | ... P11: =CPC!P10 -> 14041855 | Q11: =SUM(E11:P11) -> 1.4140239e+08
B12: 4 Variation de stocks de produits | C12: CPC | D12: =CPC!D12 -> 100000 | E12: =CPC!E12 -> 100000 | F12: =CPC!F12 -> 200000 | G12: =CPC!G12 -> 200000 | H12: =CPC!H12 -> 100000 | I12: =CPC!I12 -> 200000 | J12: =CPC!J12 -> 100000 | K12: =CPC!K12 -> 300000 | ... P12: =CPC!P12 -> -400000 | Q12: =SUM(E12:P12) -> 1200000
B13: 5 Immobilisations produites par l'entreprise pour elle-même | C13: CPC | D13: =CPC!D13 -> 0 | E13: =CPC!E13 -> 0 | F13: =CPC!F13 -> 0 | G13: =CPC!G13 -> 0 | H13: =CPC!H13 -> 0 | I13: =CPC!I13 -> 0 | J13: =CPC!J13 -> 0 | K13: =CPC!K13 -> 0 | ... P13: =CPC!P13 -> 0 | Q13: =SUM(E13:P13) -> 0
B14: II + PRODUCTION DE L'EXERCICE (3 + 4 + 5) | D14: =D11+D12+D13 -> 11551240 | E14: =E11+E12+E13 -> 10853967 | F14: =F11+F12+F13 -> 11352740 | G14: =G11+G12+G13 -> 12548633 | H14: =H11+H12+H13 -> 11951225 | I14: =I11+I12+I13 -> 12745249 | J14: =J11+J12+J13 -> 12845689 | K14: =K11+K12+K13 -> 11852263 | ... P14: =P11+P12+P13 -> 13641855 | Q14: =SUM(E14:P14) -> 1.4260239e+08
B15: 6 Achats consommés de matières et fournitures | C15: CPC | D15: =CPC!D20 -> 5025676.6 | E15: =CPC!E20 -> 4551601.7 | F15: =CPC!F20 -> 4610348.9 | G15: =CPC!G20 -> 5093312 | H15: =CPC!H20 -> 5438439 | I15: =CPC!I20 -> 5452504.5 | J15: =CPC!J20 -> 5473004.6 | K15: =CPC!K20 -> 4884054.7 | ... P15: =CPC!P20 -> 6274389.2 | Q15: =SUM(E15:P15) -> 62000000
B16: 7 Autres charges externes | C16: CPC | D16: =CPC!D21 -> 1158379.1 | E16: =CPC!E21 -> 1146546 | F16: =CPC!F21 -> 1122853.7 | G16: =CPC!G21 -> 1209678.1 | H16: =CPC!H21 -> 1164908.9 | I16: =CPC!I21 -> 1197993.7 | J16: =CPC!J21 -> 1185017.4 | K16: =CPC!K21 -> 1169684.8 | ... P16: =CPC!P21 -> 1231499.8 | Q16: =SUM(E16:P16) -> 14000000
B17: III − CONSOMMATION DE L'EXERCICE (6 + 7) | D17: =D15+D16 -> 6184055.7 | E17: =E15+E16 -> 5698147.7 | F17: =F15+F16 -> 5733202.6 | G17: =G15+G16 -> 6302990.1 | H17: =H15+H16 -> 6603347.8 | I17: =I15+I16 -> 6650498.1 | J17: =J15+J16 -> 6658021.9 | K17: =K15+K16 -> 6053739.5 | ... P17: =P15+P16 -> 7505888.9 | Q17: =SUM(E17:P17) -> 76000000
B18: IV = VALEUR AJOUTÉE (I + II − III) | D18: =D10+D14-D17 -> 5382187.8 | E18: =E10+E14-E17 -> 5169667.2 | F18: =F10+F14-F17 -> 5633560.5 | G18: =G10+G14-G17 -> 6259937.3 | H18: =H10+H14-H17 -> 5361457.2 | I18: =I10+I14-I17 -> 6112188.8 | J18: =J10+J14-J17 -> 6204176.9 | K18: =K10+K14-K17 -> 5812165.8 | ... P18: =P10+P14-P17 -> 6152352 | Q18: =SUM(E18:P18) -> 66780000
B19: 8 + Subventions d'exploitation | C19: CPC | D19: =CPC!D14 -> 0 | E19: =CPC!E14 -> 0 | F19: =CPC!F14 -> 0 | G19: =CPC!G14 -> 0 | H19: =CPC!H14 -> 0 | I19: =CPC!I14 -> 0 | J19: =CPC!J14 -> 250000 | K19: =CPC!K14 -> 0 | ... P19: =CPC!P14 -> 250000 | Q19: =SUM(E19:P19) -> 500000
B20: 9 − Impôts et taxes | C20: CPC | D20: =CPC!D22 -> 127825.77 | E20: =CPC!E22 -> 124008.07 | F20: =CPC!F22 -> 122433.54 | G20: =CPC!G22 -> 121085.58 | H20: =CPC!H22 -> 126320.6 | I20: =CPC!I22 -> 130520.87 | J20: =CPC!J22 -> 121765.77 | K20: =CPC!K22 -> 126809.99 | ... P20: =CPC!P22 -> 124656.9 | Q20: =SUM(E20:P20) -> 1500000
B21: 10 − Charges de personnel | C21: CPC | D21: =CPC!D23 -> 3979693.9 | E21: =CPC!E23 -> 3242539.6 | F21: =CPC!F23 -> 3247018.7 | G21: =CPC!G23 -> 3298230 | H21: =CPC!H23 -> 3270907.5 | I21: =CPC!I23 -> 3300900.7 | J21: =CPC!J23 -> 3270750.3 | K21: =CPC!K23 -> 3275585.1 | ... P21: =CPC!P23 -> 4155077.2 | Q21: =SUM(E21:P21) -> 40000000
B22: V = EXCÉDENT BRUT D'EXPLOITATION (EBE) ou INSUFFISANCE (IBE) | D22: =D18+D19-D20-D21 -> 1274668.2 | E22: =E18+E19-E20-E21 -> 1803119.6 | F22: =F18+F19-F20-F21 -> 2264108.3 | G22: =G18+G19-G20-G21 -> 2840621.7 | H22: =H18+H19-H20-H21 -> 1964229.1 | I22: =I18+I19-I20-I21 -> 2680767.3 | J22: =J18+J19-J20-J21 -> 3061660.9 | K22: =K18+K19-K20-K21 -> 2409770.7 | ... P22: =P18+P19-P20-P21 -> 2122617.9 | Q22: =SUM(E22:P22) -> 25780000
B23: 11 + Autres produits d'exploitation | C23: CPC | D23: =CPC!D15 -> 41666.67 | E23: =CPC!E15 -> 41666.67 | F23: =CPC!F15 -> 41666.67 | G23: =CPC!G15 -> 41666.67 | H23: =CPC!H15 -> 41666.67 | I23: =CPC!I15 -> 41666.67 | J23: =CPC!J15 -> 41666.67 | K23: =CPC!K15 -> 41666.67 | ... P23: =CPC!P15 -> 41666.67 | Q23: =SUM(E23:P23) -> 500000.04
B24: 12 − Autres charges d'exploitation | C24: CPC | D24: =CPC!D24 -> 0 | E24: =CPC!E24 -> 0 | F24: =CPC!F24 -> 0 | G24: =CPC!G24 -> 0 | H24: =CPC!H24 -> 0 | I24: =CPC!I24 -> 0 | J24: =CPC!J24 -> 0 | K24: =CPC!K24 -> 0 | ... P24: =CPC!P24 -> 0 | Q24: =SUM(E24:P24) -> 100000
B25: 13 + Reprises d'exploitation, transferts de charges | C25: CPC | D25: =CPC!D16 -> 0 | E25: =CPC!E16 -> 0 | F25: =CPC!F16 -> 0 | G25: =CPC!G16 -> 150000 | H25: =CPC!H16 -> 0 | I25: =CPC!I16 -> 0 | J25: =CPC!J16 -> 0 | K25: =CPC!K16 -> 0 | ... P25: =CPC!P16 -> 0 | Q25: =SUM(E25:P25) -> 300000
B26: 14 − Dotations d'exploitation | C26: CPC | D26: =CPC!D25 -> 813333.33 | E26: =CPC!E25 -> 733333.33 | F26: =CPC!F25 -> 733333.33 | G26: =CPC!G25 -> 733333.33 | H26: =CPC!H25 -> 733333.33 | I26: =CPC!I25 -> 733333.33 | J26: =CPC!J25 -> 833333.33 | K26: =CPC!K25 -> 733333.33 | ... P26: =CPC!P25 -> 833333.33 | Q26: =SUM(E26:P26) -> 9000000
B27: VI = RÉSULTAT D'EXPLOITATION (+ ou −) | D27: =D22+D23-D24+D25-D26 -> 503001.5 | E27: =E22+E23-E24+E25-E26 -> 1111452.9 | F27: =F22+F23-F24+F25-F26 -> 1572441.6 | G27: =G22+G23-G24+G25-G26 -> 2298955.1 | H27: =H22+H23-H24+H25-H26 -> 1272562.4 | I27: =I22+I23-I24+I25-I26 -> 1989100.6 | J27: =J22+J23-J24+J25-J26 -> 2269994.2 | K27: =K22+K23-K24+K25-K26 -> 1718104.1 | ... P27: =P22+P23-P24+P25-P26 -> 1330951.2 | Q27: =SUM(E27:P27) -> 17480000
B28: VII ± RÉSULTAT FINANCIER | C28: CPC | D28: =CPC!D41 -> -254452.08 | E28: =CPC!E41 -> -201864.94 | F28: =CPC!F41 -> -249081.89 | G28: =CPC!G41 -> -976289.09 | H28: =CPC!H41 -> -213064.23 | I28: =CPC!I41 -> -210398.18 | J28: =CPC!J41 -> -177640.21 | K28: =CPC!K41 -> -247076.09 | ... P28: =CPC!P41 -> -170436.75 | Q28: =SUM(E28:P28) -> -3500000
B29: VIII = RÉSULTAT COURANT (+ ou −) | D29: =D27+D28 -> 248549.42 | E29: =E27+E28 -> 909587.95 | F29: =F27+F28 -> 1323359.7 | G29: =G27+G28 -> 1322666 | H29: =H27+H28 -> 1059498.2 | I29: =I27+I28 -> 1778702.4 | J29: =J27+J28 -> 2092354 | K29: =K27+K28 -> 1471028 | ... P29: =P27+P28 -> 1160514.4 | Q29: =SUM(E29:P29) -> 13980000
B30: IX ± RÉSULTAT NON COURANT | C30: CPC | D30: =CPC!D57 -> 10000 | E30: =CPC!E57 -> 10000 | F30: =CPC!F57 -> 10000 | G30: =CPC!G57 -> 10000 | H30: =CPC!H57 -> 10000 | I30: =CPC!I57 -> 10000 | J30: =CPC!J57 -> 10000 | K30: =CPC!K57 -> 10000 | ... P30: =CPC!P57 -> 10000 | Q30: =SUM(E30:P30) -> -280000
B31: 15 − Impôts sur les résultats | C31: CPC | D31: =CPC!D59 -> 51709.88 | E31: =CPC!E59 -> 183917.58 | F31: =CPC!F59 -> 266671.94 | G31: =CPC!G59 -> 266533.19 | H31: =CPC!H59 -> 213899.64 | I31: =CPC!I59 -> 357740.48 | J31: =CPC!J59 -> 420470.8 | K31: =CPC!K59 -> 296205.59 | ... P31: =CPC!P59 -> 234102.89 | Q31: =SUM(E31:P31) -> 2740000
B32: X = RÉSULTAT NET DE L'EXERCICE | D32: =D29+D30-D31 -> 206839.54 | E32: =E29+E30-E31 -> 735670.37 | F32: =F29+F30-F31 -> 1066687.8 | G32: =G29+G30-G31 -> 1066132.8 | H32: =H29+H30-H31 -> 855598.55 | I32: =I29+I30-I31 -> 1430961.9 | J32: =J29+J30-J31 -> 1681883.2 | K32: =K29+K30-K31 -> 1184822.4 | ... P32: =P29+P30-P31 -> 936411.55 | Q32: =SUM(E32:P32) -> 10960000
B33: II. CAPACITÉ D'AUTOFINANCEMENT (CAF) — AUTOFINANCEMENT
B34: 1 Résultat net de l'exercice | C34: ESG X | D34: =D32 -> 206839.54 | E34: =E32 -> 735670.37 | F34: =F32 -> 1066687.8 | G34: =G32 -> 1066132.8 | H34: =H32 -> 855598.55 | I34: =I32 -> 1430961.9 | J34: =J32 -> 1681883.2 | K34: =K32 -> 1184822.4 | ... P34: =P32 -> 936411.55 | Q34: =SUM(E34:P34) -> 10960000
B35: 2 + Dotations d'exploitation (1) | C35: 6191-6195 | D35: =SUMPRODUCT(((LEFT(Balance!$B$7:$B$400,4)="6191")+(LEFT(Balance!$B$7:$B$400,4)="6192")+(LEFT(Balance!$B$7:$B$400,4)="6193")+(LEFT(Balance!$B$7:$B$400,4)="6194")+(LEFT(Balance!$B$7:$B$400,4)="6195"))*Balance!D$7:D$400) -> 733333.33 | E35: =SUMPRODUCT(((LEFT(Balance!$B$7:$B$400,4)="6191")+(LEFT(Balance!$B$7:$B$400,4)="6192")+(LEFT(Balance!$B$7:$B$400,4)="6193")+(LEFT(Balance!$B$7:$B$400,4)="6194")+(LEFT(Balance!$B$7:$B$400,4)="6195"))*Balance!E$7:E$400) -> 733333.33 | F35: =SUMPRODUCT(((LEFT(Balance!$B$7:$B$400,4)="6191")+(LEFT(Balance!$B$7:$B$400,4)="6192")+(LEFT(Balance!$B$7:$B$400,4)="6193")+(LEFT(Balance!$B$7:$B$400,4)="6194")+(LEFT(Balance!$B$7:$B$400,4)="6195"))*Balance!F$7:F$400) -> 733333.33 | G35: =SUMPRODUCT(((LEFT(Balance!$B$7:$B$400,4)="6191")+(LEFT(Balance!$B$7:$B$400,4)="6192")+(LEFT(Balance!$B$7:$B$400,4)="6193")+(LEFT(Balance!$B$7:$B$400,4)="6194")+(LEFT(Balance!$B$7:$B$400,4)="6195"))*Balance!G$7:G$400) -> 733333.33 | H35: =SUMPRODUCT(((LEFT(Balance!$B$7:$B$400,4)="6191")+(LEFT(Balance!$B$7:$B$400,4)="6192")+(LEFT(Balance!$B$7:$B$400,4)="6193")+(LEFT(Balance!$B$7:$B$400,4)="6194")+(LEFT(Balance!$B$7:$B$400,4)="6195"))*Balance!H$7:H$400) -> 733333.33 | I35: =SUMPRODUCT(((LEFT(Balance!$B$7:$B$400,4)="6191")+(LEFT(Balance!$B$7:$B$400,4)="6192")+(LEFT(Balance!$B$7:$B$400,4)="6193")+(LEFT(Balance!$B$7:$B$400,4)="6194")+(LEFT(Balance!$B$7:$B$400,4)="6195"))*Balance!I$7:I$400) -> 733333.33 | J35: =SUMPRODUCT(((LEFT(Balance!$B$7:$B$400,4)="6191")+(LEFT(Balance!$B$7:$B$400,4)="6192")+(LEFT(Balance!$B$7:$B$400,4)="6193")+(LEFT(Balance!$B$7:$B$400,4)="6194")+(LEFT(Balance!$B$7:$B$400,4)="6195"))*Balance!J$7:J$400) -> 733333.33 | K35: =SUMPRODUCT(((LEFT(Balance!$B$7:$B$400,4)="6191")+(LEFT(Balance!$B$7:$B$400,4)="6192")+(LEFT(Balance!$B$7:$B$400,4)="6193")+(LEFT(Balance!$B$7:$B$400,4)="6194")+(LEFT(Balance!$B$7:$B$400,4)="6195"))*Balance!K$7:K$400) -> 733333.33 | ... P35: =SUMPRODUCT(((LEFT(Balance!$B$7:$B$400,4)="6191")+(LEFT(Balance!$B$7:$B$400,4)="6192")+(LEFT(Balance!$B$7:$B$400,4)="6193")+(LEFT(Balance!$B$7:$B$400,4)="6194")+(LEFT(Balance!$B$7:$B$400,4)="6195"))*Balance!P$7:P$400) -> 733333.33 | Q35: =SUM(E35:P35) -> 8800000
B36: 3 + Dotations financières (1) | C36: 6392-6393 | D36: =SUMPRODUCT(((LEFT(Balance!$B$7:$B$400,4)="6392")+(LEFT(Balance!$B$7:$B$400,4)="6393"))*Balance!D$7:D$400) -> 0 | E36: =SUMPRODUCT(((LEFT(Balance!$B$7:$B$400,4)="6392")+(LEFT(Balance!$B$7:$B$400,4)="6393"))*Balance!E$7:E$400) -> 0 | F36: =SUMPRODUCT(((LEFT(Balance!$B$7:$B$400,4)="6392")+(LEFT(Balance!$B$7:$B$400,4)="6393"))*Balance!F$7:F$400) -> 0 | G36: =SUMPRODUCT(((LEFT(Balance!$B$7:$B$400,4)="6392")+(LEFT(Balance!$B$7:$B$400,4)="6393"))*Balance!G$7:G$400) -> 0 | H36: =SUMPRODUCT(((LEFT(Balance!$B$7:$B$400,4)="6392")+(LEFT(Balance!$B$7:$B$400,4)="6393"))*Balance!H$7:H$400) -> 0 | I36: =SUMPRODUCT(((LEFT(Balance!$B$7:$B$400,4)="6392")+(LEFT(Balance!$B$7:$B$400,4)="6393"))*Balance!I$7:I$400) -> 0 | J36: =SUMPRODUCT(((LEFT(Balance!$B$7:$B$400,4)="6392")+(LEFT(Balance!$B$7:$B$400,4)="6393"))*Balance!J$7:J$400) -> 0 | K36: =SUMPRODUCT(((LEFT(Balance!$B$7:$B$400,4)="6392")+(LEFT(Balance!$B$7:$B$400,4)="6393"))*Balance!K$7:K$400) -> 0 | ... P36: =SUMPRODUCT(((LEFT(Balance!$B$7:$B$400,4)="6392")+(LEFT(Balance!$B$7:$B$400,4)="6393"))*Balance!P$7:P$400) -> 0 | Q36: =SUM(E36:P36) -> 0
B37: 4 + Dotations non courantes (1) | C37: 6591-6595 | D37: =SUMPRODUCT(((LEFT(Balance!$B$7:$B$400,4)="6591")+(LEFT(Balance!$B$7:$B$400,4)="6592")+(LEFT(Balance!$B$7:$B$400,4)="6593")+(LEFT(Balance!$B$7:$B$400,4)="6594")+(LEFT(Balance!$B$7:$B$400,4)="6595"))*Balance!D$7:D$400) -> 0 | E37: =SUMPRODUCT(((LEFT(Balance!$B$7:$B$400,4)="6591")+(LEFT(Balance!$B$7:$B$400,4)="6592")+(LEFT(Balance!$B$7:$B$400,4)="6593")+(LEFT(Balance!$B$7:$B$400,4)="6594")+(LEFT(Balance!$B$7:$B$400,4)="6595"))*Balance!E$7:E$400) -> 0 | F37: =SUMPRODUCT(((LEFT(Balance!$B$7:$B$400,4)="6591")+(LEFT(Balance!$B$7:$B$400,4)="6592")+(LEFT(Balance!$B$7:$B$400,4)="6593")+(LEFT(Balance!$B$7:$B$400,4)="6594")+(LEFT(Balance!$B$7:$B$400,4)="6595"))*Balance!F$7:F$400) -> 0 | G37: =SUMPRODUCT(((LEFT(Balance!$B$7:$B$400,4)="6591")+(LEFT(Balance!$B$7:$B$400,4)="6592")+(LEFT(Balance!$B$7:$B$400,4)="6593")+(LEFT(Balance!$B$7:$B$400,4)="6594")+(LEFT(Balance!$B$7:$B$400,4)="6595"))*Balance!G$7:G$400) -> 0 | H37: =SUMPRODUCT(((LEFT(Balance!$B$7:$B$400,4)="6591")+(LEFT(Balance!$B$7:$B$400,4)="6592")+(LEFT(Balance!$B$7:$B$400,4)="6593")+(LEFT(Balance!$B$7:$B$400,4)="6594")+(LEFT(Balance!$B$7:$B$400,4)="6595"))*Balance!H$7:H$400) -> 0 | I37: =SUMPRODUCT(((LEFT(Balance!$B$7:$B$400,4)="6591")+(LEFT(Balance!$B$7:$B$400,4)="6592")+(LEFT(Balance!$B$7:$B$400,4)="6593")+(LEFT(Balance!$B$7:$B$400,4)="6594")+(LEFT(Balance!$B$7:$B$400,4)="6595"))*Balance!I$7:I$400) -> 0 | J37: =SUMPRODUCT(((LEFT(Balance!$B$7:$B$400,4)="6591")+(LEFT(Balance!$B$7:$B$400,4)="6592")+(LEFT(Balance!$B$7:$B$400,4)="6593")+(LEFT(Balance!$B$7:$B$400,4)="6594")+(LEFT(Balance!$B$7:$B$400,4)="6595"))*Balance!J$7:J$400) -> 0 | K37: =SUMPRODUCT(((LEFT(Balance!$B$7:$B$400,4)="6591")+(LEFT(Balance!$B$7:$B$400,4)="6592")+(LEFT(Balance!$B$7:$B$400,4)="6593")+(LEFT(Balance!$B$7:$B$400,4)="6594")+(LEFT(Balance!$B$7:$B$400,4)="6595"))*Balance!K$7:K$400) -> 0 | ... P37: =SUMPRODUCT(((LEFT(Balance!$B$7:$B$400,4)="6591")+(LEFT(Balance!$B$7:$B$400,4)="6592")+(LEFT(Balance!$B$7:$B$400,4)="6593")+(LEFT(Balance!$B$7:$B$400,4)="6594")+(LEFT(Balance!$B$7:$B$400,4)="6595"))*Balance!P$7:P$400) -> 0 | Q37: =SUM(E37:P37) -> 0
B38: 5 − Reprises d'exploitation (2) | C38: 7191-7195 | D38: =-SUMPRODUCT(((LEFT(Balance!$B$7:$B$400,4)="7191")+(LEFT(Balance!$B$7:$B$400,4)="7192")+(LEFT(Balance!$B$7:$B$400,4)="7193")+(LEFT(Balance!$B$7:$B$400,4)="7194")+(LEFT(Balance!$B$7:$B$400,4)="7195"))*Balance!D$7:D$400) -> 0 | E38: =-SUMPRODUCT(((LEFT(Balance!$B$7:$B$400,4)="7191")+(LEFT(Balance!$B$7:$B$400,4)="7192")+(LEFT(Balance!$B$7:$B$400,4)="7193")+(LEFT(Balance!$B$7:$B$400,4)="7194")+(LEFT(Balance!$B$7:$B$400,4)="7195"))*Balance!E$7:E$400) -> 0 | F38: =-SUMPRODUCT(((LEFT(Balance!$B$7:$B$400,4)="7191")+(LEFT(Balance!$B$7:$B$400,4)="7192")+(LEFT(Balance!$B$7:$B$400,4)="7193")+(LEFT(Balance!$B$7:$B$400,4)="7194")+(LEFT(Balance!$B$7:$B$400,4)="7195"))*Balance!F$7:F$400) -> 0 | G38: =-SUMPRODUCT(((LEFT(Balance!$B$7:$B$400,4)="7191")+(LEFT(Balance!$B$7:$B$400,4)="7192")+(LEFT(Balance!$B$7:$B$400,4)="7193")+(LEFT(Balance!$B$7:$B$400,4)="7194")+(LEFT(Balance!$B$7:$B$400,4)="7195"))*Balance!G$7:G$400) -> 0 | H38: =-SUMPRODUCT(((LEFT(Balance!$B$7:$B$400,4)="7191")+(LEFT(Balance!$B$7:$B$400,4)="7192")+(LEFT(Balance!$B$7:$B$400,4)="7193")+(LEFT(Balance!$B$7:$B$400,4)="7194")+(LEFT(Balance!$B$7:$B$400,4)="7195"))*Balance!H$7:H$400) -> 0 | I38: =-SUMPRODUCT(((LEFT(Balance!$B$7:$B$400,4)="7191")+(LEFT(Balance!$B$7:$B$400,4)="7192")+(LEFT(Balance!$B$7:$B$400,4)="7193")+(LEFT(Balance!$B$7:$B$400,4)="7194")+(LEFT(Balance!$B$7:$B$400,4)="7195"))*Balance!I$7:I$400) -> 0 | J38: =-SUMPRODUCT(((LEFT(Balance!$B$7:$B$400,4)="7191")+(LEFT(Balance!$B$7:$B$400,4)="7192")+(LEFT(Balance!$B$7:$B$400,4)="7193")+(LEFT(Balance!$B$7:$B$400,4)="7194")+(LEFT(Balance!$B$7:$B$400,4)="7195"))*Balance!J$7:J$400) -> 0 | K38: =-SUMPRODUCT(((LEFT(Balance!$B$7:$B$400,4)="7191")+(LEFT(Balance!$B$7:$B$400,4)="7192")+(LEFT(Balance!$B$7:$B$400,4)="7193")+(LEFT(Balance!$B$7:$B$400,4)="7194")+(LEFT(Balance!$B$7:$B$400,4)="7195"))*Balance!K$7:K$400) -> 0 | ... P38: =-SUMPRODUCT(((LEFT(Balance!$B$7:$B$400,4)="7191")+(LEFT(Balance!$B$7:$B$400,4)="7192")+(LEFT(Balance!$B$7:$B$400,4)="7193")+(LEFT(Balance!$B$7:$B$400,4)="7194")+(LEFT(Balance!$B$7:$B$400,4)="7195"))*Balance!P$7:P$400) -> 0 | Q38: =SUM(E38:P38) -> 0
B39: 6 − Reprises financières (2) | C39: 7392-7393 | D39: =-SUMPRODUCT(((LEFT(Balance!$B$7:$B$400,4)="7392")+(LEFT(Balance!$B$7:$B$400,4)="7393"))*Balance!D$7:D$400) -> 0 | E39: =-SUMPRODUCT(((LEFT(Balance!$B$7:$B$400,4)="7392")+(LEFT(Balance!$B$7:$B$400,4)="7393"))*Balance!E$7:E$400) -> 0 | F39: =-SUMPRODUCT(((LEFT(Balance!$B$7:$B$400,4)="7392")+(LEFT(Balance!$B$7:$B$400,4)="7393"))*Balance!F$7:F$400) -> 0 | G39: =-SUMPRODUCT(((LEFT(Balance!$B$7:$B$400,4)="7392")+(LEFT(Balance!$B$7:$B$400,4)="7393"))*Balance!G$7:G$400) -> 0 | H39: =-SUMPRODUCT(((LEFT(Balance!$B$7:$B$400,4)="7392")+(LEFT(Balance!$B$7:$B$400,4)="7393"))*Balance!H$7:H$400) -> 0 | I39: =-SUMPRODUCT(((LEFT(Balance!$B$7:$B$400,4)="7392")+(LEFT(Balance!$B$7:$B$400,4)="7393"))*Balance!I$7:I$400) -> 0 | J39: =-SUMPRODUCT(((LEFT(Balance!$B$7:$B$400,4)="7392")+(LEFT(Balance!$B$7:$B$400,4)="7393"))*Balance!J$7:J$400) -> 0 | K39: =-SUMPRODUCT(((LEFT(Balance!$B$7:$B$400,4)="7392")+(LEFT(Balance!$B$7:$B$400,4)="7393"))*Balance!K$7:K$400) -> 0 | ... P39: =-SUMPRODUCT(((LEFT(Balance!$B$7:$B$400,4)="7392")+(LEFT(Balance!$B$7:$B$400,4)="7393"))*Balance!P$7:P$400) -> 0 | Q39: =SUM(E39:P39) -> 0
B40: 7 − Reprises non courantes (2) (3) | C40: 757, 7591-95 | D40: =-SUMPRODUCT(((LEFT(Balance!$B$7:$B$400,3)="757")+(LEFT(Balance!$B$7:$B$400,4)="7591")+(LEFT(Balance!$B$7:$B$400,4)="7592")+(LEFT(Balance!$B$7:$B$400,4)="7593")+(LEFT(Balance!$B$7:$B$400,4)="7594")+(LEFT(Balance!$B$7:$B$400,4)="7595"))*Balance!D$7:D$400) -> 10000 | E40: =-SUMPRODUCT(((LEFT(Balance!$B$7:$B$400,3)="757")+(LEFT(Balance!$B$7:$B$400,4)="7591")+(LEFT(Balance!$B$7:$B$400,4)="7592")+(LEFT(Balance!$B$7:$B$400,4)="7593")+(LEFT(Balance!$B$7:$B$400,4)="7594")+(LEFT(Balance!$B$7:$B$400,4)="7595"))*Balance!E$7:E$400) -> 10000 | F40: =-SUMPRODUCT(((LEFT(Balance!$B$7:$B$400,3)="757")+(LEFT(Balance!$B$7:$B$400,4)="7591")+(LEFT(Balance!$B$7:$B$400,4)="7592")+(LEFT(Balance!$B$7:$B$400,4)="7593")+(LEFT(Balance!$B$7:$B$400,4)="7594")+(LEFT(Balance!$B$7:$B$400,4)="7595"))*Balance!F$7:F$400) -> 10000 | G40: =-SUMPRODUCT(((LEFT(Balance!$B$7:$B$400,3)="757")+(LEFT(Balance!$B$7:$B$400,4)="7591")+(LEFT(Balance!$B$7:$B$400,4)="7592")+(LEFT(Balance!$B$7:$B$400,4)="7593")+(LEFT(Balance!$B$7:$B$400,4)="7594")+(LEFT(Balance!$B$7:$B$400,4)="7595"))*Balance!G$7:G$400) -> 10000 | H40: =-SUMPRODUCT(((LEFT(Balance!$B$7:$B$400,3)="757")+(LEFT(Balance!$B$7:$B$400,4)="7591")+(LEFT(Balance!$B$7:$B$400,4)="7592")+(LEFT(Balance!$B$7:$B$400,4)="7593")+(LEFT(Balance!$B$7:$B$400,4)="7594")+(LEFT(Balance!$B$7:$B$400,4)="7595"))*Balance!H$7:H$400) -> 10000 | I40: =-SUMPRODUCT(((LEFT(Balance!$B$7:$B$400,3)="757")+(LEFT(Balance!$B$7:$B$400,4)="7591")+(LEFT(Balance!$B$7:$B$400,4)="7592")+(LEFT(Balance!$B$7:$B$400,4)="7593")+(LEFT(Balance!$B$7:$B$400,4)="7594")+(LEFT(Balance!$B$7:$B$400,4)="7595"))*Balance!I$7:I$400) -> 10000 | J40: =-SUMPRODUCT(((LEFT(Balance!$B$7:$B$400,3)="757")+(LEFT(Balance!$B$7:$B$400,4)="7591")+(LEFT(Balance!$B$7:$B$400,4)="7592")+(LEFT(Balance!$B$7:$B$400,4)="7593")+(LEFT(Balance!$B$7:$B$400,4)="7594")+(LEFT(Balance!$B$7:$B$400,4)="7595"))*Balance!J$7:J$400) -> 10000 | K40: =-SUMPRODUCT(((LEFT(Balance!$B$7:$B$400,3)="757")+(LEFT(Balance!$B$7:$B$400,4)="7591")+(LEFT(Balance!$B$7:$B$400,4)="7592")+(LEFT(Balance!$B$7:$B$400,4)="7593")+(LEFT(Balance!$B$7:$B$400,4)="7594")+(LEFT(Balance!$B$7:$B$400,4)="7595"))*Balance!K$7:K$400) -> 10000 | ... P40: =-SUMPRODUCT(((LEFT(Balance!$B$7:$B$400,3)="757")+(LEFT(Balance!$B$7:$B$400,4)="7591")+(LEFT(Balance!$B$7:$B$400,4)="7592")+(LEFT(Balance!$B$7:$B$400,4)="7593")+(LEFT(Balance!$B$7:$B$400,4)="7594")+(LEFT(Balance!$B$7:$B$400,4)="7595"))*Balance!P$7:P$400) -> 10000 | Q40: =SUM(E40:P40) -> 120000
B41: 8 − Produits des cessions d'immobilisations | C41: 751 | D41: =-SUMPRODUCT(((LEFT(Balance!$B$7:$B$400,3)="751"))*Balance!D$7:D$400) -> 0 | E41: =-SUMPRODUCT(((LEFT(Balance!$B$7:$B$400,3)="751"))*Balance!E$7:E$400) -> 0 | F41: =-SUMPRODUCT(((LEFT(Balance!$B$7:$B$400,3)="751"))*Balance!F$7:F$400) -> 0 | G41: =-SUMPRODUCT(((LEFT(Balance!$B$7:$B$400,3)="751"))*Balance!G$7:G$400) -> 0 | H41: =-SUMPRODUCT(((LEFT(Balance!$B$7:$B$400,3)="751"))*Balance!H$7:H$400) -> 0 | I41: =-SUMPRODUCT(((LEFT(Balance!$B$7:$B$400,3)="751"))*Balance!I$7:I$400) -> 0 | J41: =-SUMPRODUCT(((LEFT(Balance!$B$7:$B$400,3)="751"))*Balance!J$7:J$400) -> 0 | K41: =-SUMPRODUCT(((LEFT(Balance!$B$7:$B$400,3)="751"))*Balance!K$7:K$400) -> 0 | ... P41: =-SUMPRODUCT(((LEFT(Balance!$B$7:$B$400,3)="751"))*Balance!P$7:P$400) -> 0 | Q41: =SUM(E41:P41) -> 300000
B42: 9 + Valeurs nettes d'amortissements des immobilisations cédées | C42: 651 | D42: =SUMPRODUCT(((LEFT(Balance!$B$7:$B$400,3)="651"))*Balance!D$7:D$400) -> 0 | E42: =SUMPRODUCT(((LEFT(Balance!$B$7:$B$400,3)="651"))*Balance!E$7:E$400) -> 0 | F42: =SUMPRODUCT(((LEFT(Balance!$B$7:$B$400,3)="651"))*Balance!F$7:F$400) -> 0 | G42: =SUMPRODUCT(((LEFT(Balance!$B$7:$B$400,3)="651"))*Balance!G$7:G$400) -> 0 | H42: =SUMPRODUCT(((LEFT(Balance!$B$7:$B$400,3)="651"))*Balance!H$7:H$400) -> 0 | I42: =SUMPRODUCT(((LEFT(Balance!$B$7:$B$400,3)="651"))*Balance!I$7:I$400) -> 0 | J42: =SUMPRODUCT(((LEFT(Balance!$B$7:$B$400,3)="651"))*Balance!J$7:J$400) -> 0 | K42: =SUMPRODUCT(((LEFT(Balance!$B$7:$B$400,3)="651"))*Balance!K$7:K$400) -> 0 | ... P42: =SUMPRODUCT(((LEFT(Balance!$B$7:$B$400,3)="651"))*Balance!P$7:P$400) -> 0 | Q42: =SUM(E42:P42) -> 250000
B43: I CAPACITÉ D'AUTOFINANCEMENT (CAF) | D43: =D34+D35+D36+D37-D38-D39-D40-D41+D42 -> 930172.87 | E43: =E34+E35+E36+E37-E38-E39-E40-E41+E42 -> 1459003.7 | F43: =F34+F35+F36+F37-F38-F39-F40-F41+F42 -> 1790021.1 | G43: =G34+G35+G36+G37-G38-G39-G40-G41+G42 -> 1789466.1 | H43: =H34+H35+H36+H37-H38-H39-H40-H41+H42 -> 1578931.9 | I43: =I34+I35+I36+I37-I38-I39-I40-I41+I42 -> 2154295.3 | J43: =J34+J35+J36+J37-J38-J39-J40-J41+J42 -> 2405216.5 | K43: =K34+K35+K36+K37-K38-K39-K40-K41+K42 -> 1908155.7 | ... P43: =P34+P35+P36+P37-P38-P39-P40-P41+P42 -> 1659744.9 | Q43: =SUM(E43:P43) -> 19590000
B44: 10 − Distributions de bénéfices | C44: Saisie | D44: 0 | E44: 0 | F44: 0 | G44: 0 | H44: 0 | I44: 0 | J44: 0 | K44: 0 | L44: 0 | M44: 0 | N44: 0 | O44: 0 | P44: 0 | Q44: =SUM(E44:P44) -> 0
B45: II AUTOFINANCEMENT | D45: =D43-D44 -> 930172.87 | E45: =E43-E44 -> 1459003.7 | F45: =F43-F44 -> 1790021.1 | G45: =G43-G44 -> 1789466.1 | H45: =H43-H44 -> 1578931.9 | I45: =I43-I44 -> 2154295.3 | J45: =J43-J44 -> 2405216.5 | K45: =K43-K44 -> 1908155.7 | ... P45: =P43-P44 -> 1659744.9 | Q45: =SUM(E45:P45) -> 19590000
B47: CONTRÔLES : RN ESG − RN CPC = 0 │ REX ESG − REX CPC = 0 | D47: =ROUND(ABS(D32-CPC!D60)+ABS(D27-CPC!D27),2) -> 0 | E47: =ROUND(ABS(E32-CPC!E60)+ABS(E27-CPC!E27),2) -> 0 | F47: =ROUND(ABS(F32-CPC!F60)+ABS(F27-CPC!F27),2) -> 0 | G47: =ROUND(ABS(G32-CPC!G60)+ABS(G27-CPC!G27),2) -> 0 | H47: =ROUND(ABS(H32-CPC!H60)+ABS(H27-CPC!H27),2) -> 0 | I47: =ROUND(ABS(I32-CPC!I60)+ABS(I27-CPC!I27),2) -> 0 | J47: =ROUND(ABS(J32-CPC!J60)+ABS(J27-CPC!J27),2) -> 0 | K47: =ROUND(ABS(K32-CPC!K60)+ABS(K27-CPC!K27),2) -> 0 | ... Q47: =ROUND(ABS(Q32-CPC!Q60)+ABS(Q27-CPC!Q27),2) -> 0
B49: (1) À l'exclusion des dotations relatives aux actifs et passifs circulants et à la trésorerie.
B50: (2) À l'exclusion des reprises relatives aux actifs et passifs circulants et à la trésorerie.
B51: (3) Y compris les reprises sur subventions d'investissement.
B52: Distributions de bénéfices : 0 MAD en 2025 (résultat 2024 mis en réserve par l'AGO de juin) — seule saisie de l'onglet, en bleu.

Sheet Reporting
B1: REPORTING DE GESTION — KPI & BENCHMARK SECTORIEL
B2: ="Société : "&Accueil!$C$8&" │ Exercice : "&Accueil!$C$11&" │ Date d'arrêté : "&Accueil!$C$12&" │ Responsable : "&Accueil!$C$15 -> Société : AéroAtlas Composites SARL │ Exercice : 2025 │ Date d'arrêté : 31/12/2025 │ Responsable : Karim El Fassi (DAF)
B4: ← Accueil | C4: Toutes les valeurs sont liées aux onglets CPC, ESG et Balance │ Benchmark indicatif : sous-traitance aéronautique, Maroc
B5: MOIS SÉLECTIONNÉ ▸ | C5: Décembre | D5: =MATCH($C$5,$E$42:$P$42,0) -> 12 | G5: Part export (HT) | H5: 0.7 | I5: Taux de TVA | J5: 0.2 | K5: Jours / mois | L5: 30 | M5: ← Hypothèses de calcul (saisie, en bleu)
B7: A. ÉLASTICITÉ CA / REX — variations par rapport au mois précédent
B8: Indicateur | C8: Unité | D8: Déc. N-1 (réf.) | E8: Janvier | F8: Février | G8: Mars | H8: Avril | I8: Mai | J8: Juin | K8: Juillet | L8: Août | M8: Septembre | N8: Octobre | O8: Novembre | P8: Décembre | Q8: Cumul année
B9: Chiffre d'affaires (CA) | C9: MAD | D9: =CPC!D11 -> 11500000 | E9: =CPC!E11 -> 10800000 | F9: =CPC!F11 -> 11200000 | G9: =CPC!G11 -> 12400000 | H9: =CPC!H11 -> 11900000 | I9: =CPC!I11 -> 12600000 | J9: =CPC!J11 -> 12800000 | K9: =CPC!K11 -> 11600000 | ... P9: =CPC!P11 -> 14100000 | Q9: =SUM(E9:P9) -> 142000000
B10: Variation CA % | C10: % | D10: — | E10: =IFERROR(E9/D9-1,"—") -> -0.060869565 | F10: =IFERROR(F9/E9-1,"—") -> 0.037037037 | G10: =IFERROR(G9/F9-1,"—") -> 0.10714286 | H10: =IFERROR(H9/G9-1,"—") -> -0.040322581 | I10: =IFERROR(I9/H9-1,"—") -> 0.058823529 | J10: =IFERROR(J9/I9-1,"—") -> 0.015873016 | K10: =IFERROR(K9/J9-1,"—") -> -0.09375 | L10: =IFERROR(L9/K9-1,"—") -> -0.36206897 | ... P10: =IFERROR(P9/O9-1,"—") -> 0.14634146 | Q10: —
B11: Résultat d'exploitation (REX) | C11: MAD | D11: =CPC!D27 -> 503001.5 | E11: =CPC!E27 -> 1111452.9 | F11: =CPC!F27 -> 1572441.6 | G11: =CPC!G27 -> 2298955.1 | H11: =CPC!H27 -> 1272562.4 | I11: =CPC!I27 -> 1989100.6 | J11: =CPC!J27 -> 2269994.2 | K11: =CPC!K27 -> 1718104.1 | ... P11: =CPC!P27 -> 1330951.2 | Q11: =SUM(E11:P11) -> 17480000
B12: Variation REX % | C12: % | D12: — | E12: =IFERROR((E11-D11)/ABS(D11),"—") -> 1.2096413 | F12: =IFERROR((F11-E11)/ABS(E11),"—") -> 0.41476227 | G12: =IFERROR((G11-F11)/ABS(F11),"—") -> 0.4620289 | H12: =IFERROR((H11-G11)/ABS(G11),"—") -> -0.44646051 | I12: =IFERROR((I11-H11)/ABS(H11),"—") -> 0.56306722 | J12: =IFERROR((J11-I11)/ABS(I11),"—") -> 0.14121638 | K12: =IFERROR((K11-J11)/ABS(J11),"—") -> -0.24312403 | L12: =IFERROR((L11-K11)/ABS(K11),"—") -> -1.0958195 | ... P12: =IFERROR((P11-O11)/ABS(O11),"—") -> -0.13967388 | Q12: —
B13: Marge d'exploitation | C13: % | D13: =IFERROR(D11/D9,"—") -> 0.043739261 | E13: =IFERROR(E11/E9,"—") -> 0.1029123 | F13: =IFERROR(F11/F9,"—") -> 0.14039657 | G13: =IFERROR(G11/G9,"—") -> 0.1853996 | H13: =IFERROR(H11/H9,"—") -> 0.10693802 | I13: =IFERROR(I11/I9,"—") -> 0.15786513 | J13: =IFERROR(J11/J9,"—") -> 0.1773433 | K13: =IFERROR(K11/K9,"—") -> 0.14811242 | ... Q13: =IFERROR(Q11/Q9,"—") -> 0.12309859
B14: Élasticité REX / CA | C14: x | D14: — | E14: =IFERROR(IF(OR(ABS(E10)<0.02,D11<=0),"n.s.",ROUND(E12/E10,1)),"—") -> -19.9 | F14: =IFERROR(IF(OR(ABS(F10)<0.02,E11<=0),"n.s.",ROUND(F12/F10,1)),"—") -> 11.2 | G14: =IFERROR(IF(OR(ABS(G10)<0.02,F11<=0),"n.s.",ROUND(G12/G10,1)),"—") -> 4.3 | H14: =IFERROR(IF(OR(ABS(H10)<0.02,G11<=0),"n.s.",ROUND(H12/H10,1)),"—") -> 11.1 | I14: =IFERROR(IF(OR(ABS(I10)<0.02,H11<=0),"n.s.",ROUND(I12/I10,1)),"—") -> 9.6 | J14: =IFERROR(IF(OR(ABS(J10)<0.02,I11<=0),"n.s.",ROUND(J12/J10,1)),"—") -> n.s. | K14: =IFERROR(IF(OR(ABS(K10)<0.02,J11<=0),"n.s.",ROUND(K12/K10,1)),"—") -> 2.6 | L14: =IFERROR(IF(OR(ABS(L10)<0.02,K11<=0),"n.s.",ROUND(L12/L10,1)),"—") -> 3 | ... P14: =IFERROR(IF(OR(ABS(P10)<0.02,O11<=0),"n.s.",ROUND(P12/P10,1)),"—") -> -1 | Q14: —
B15: Lecture | D15: — | E15: =IF(ISNUMBER(E14),IF(E10>=0,IF(E14>1.2,"Levier fort",IF(E14>=0.8,"Proportionnel",IF(E14>0,"Marge érodée","REX stagne / sens contraire"))),IF(E14>1.2,"Chute amplifiée",IF(E14>=0.8,"Proportionnel",IF(E14>=0,"Baisse amortie","REX résiste")))),IF(E14="n.s.","n.s.","—")) -> REX résiste | F15: =IF(ISNUMBER(F14),IF(F10>=0,IF(F14>1.2,"Levier fort",IF(F14>=0.8,"Proportionnel",IF(F14>0,"Marge érodée","REX stagne / sens contraire"))),IF(F14>1.2,"Chute amplifiée",IF(F14>=0.8,"Proportionnel",IF(F14>=0,"Baisse amortie","REX résiste")))),IF(F14="n.s.","n.s.","—")) -> Levier fort | G15: =IF(ISNUMBER(G14),IF(G10>=0,IF(G14>1.2,"Levier fort",IF(G14>=0.8,"Proportionnel",IF(G14>0,"Marge érodée","REX stagne / sens contraire"))),IF(G14>1.2,"Chute amplifiée",IF(G14>=0.8,"Proportionnel",IF(G14>=0,"Baisse amortie","REX résiste")))),IF(G14="n.s.","n.s.","—")) -> Levier fort | H15: =IF(ISNUMBER(H14),IF(H10>=0,IF(H14>1.2,"Levier fort",IF(H14>=0.8,"Proportionnel",IF(H14>0,"Marge érodée","REX stagne / sens contraire"))),IF(H14>1.2,"Chute amplifiée",IF(H14>=0.8,"Proportionnel",IF(H14>=0,"Baisse amortie","REX résiste")))),IF(H14="n.s.","n.s.","—")) -> Chute amplifiée | I15: =IF(ISNUMBER(I14),IF(I10>=0,IF(I14>1.2,"Levier fort",IF(I14>=0.8,"Proportionnel",IF(I14>0,"Marge érodée","REX stagne / sens contraire"))),IF(I14>1.2,"Chute amplifiée",IF(I14>=0.8,"Proportionnel",IF(I14>=0,"Baisse amortie","REX résiste")))),IF(I14="n.s.","n.s.","—")) -> Levier fort | J15: =IF(ISNUMBER(J14),IF(J10>=0,IF(J14>1.2,"Levier fort",IF(J14>=0.8,"Proportionnel",IF(J14>0,"Marge érodée","REX stagne / sens contraire"))),IF(J14>1.2,"Chute amplifiée",IF(J14>=0.8,"Proportionnel",IF(J14>=0,"Baisse amortie","REX résiste")))),IF(J14="n.s.","n.s.","—")) -> n.s. | K15: =IF(ISNUMBER(K14),IF(K10>=0,IF(K14>1.2,"Levier fort",IF(K14>=0.8,"Proportionnel",IF(K14>0,"Marge érodée","REX stagne / sens contraire"))),IF(K14>1.2,"Chute amplifiée",IF(K14>=0.8,"Proportionnel",IF(K14>=0,"Baisse amortie","REX résiste")))),IF(K14="n.s.","n.s.","—")) -> Chute amplifiée | L15: =IF(ISNUMBER(L14),IF(L10>=0,IF(L14>1.2,"Levier fort",IF(L14>=0.8,"Proportionnel",IF(L14>0,"Marge érodée","REX stagne / sens contraire"))),IF(L14>1.2,"Chute amplifiée",IF(L14>=0.8,"Proportionnel",IF(L14>=0,"Baisse amortie","REX résiste")))),IF(L14="n.s.","n.s.","—")) -> Chute amplifiée | ... P15: =IF(ISNUMBER(P14),IF(P10>=0,IF(P14>1.2,"Levier fort",IF(P14>=0.8,"Proportionnel",IF(P14>0,"Marge érodée","REX stagne / sens contraire"))),IF(P14>1.2,"Chute amplifiée",IF(P14>=0.8,"Proportionnel",IF(P14>=0,"Baisse amortie","REX résiste")))),IF(P14="n.s.","n.s.","—")) -> REX stagne / sens contraire | Q15: —
B16: ① L'élasticité mesure de combien le résultat d'exploitation (REX) bouge quand le chiffre d'affaires bouge de 1 % (ex. 2,0 x : CA +5 % → REX +10 %).
B17: ② CA en hausse — vert « Levier fort » (> 1,2) : le résultat progresse plus vite que les ventes │ bleu « Proportionnel » (0,8 à 1,2) │ orange « Marge érodée » (0 à 0,8) │ rouge (≤ 0) : le REX ne suit pas.
B18: ③ CA en baisse, lecture inversée — rouge « Chute amplifiée » (> 1,2) : le résultat chute plus vite que les ventes │ vert « REX résiste » (< 0). « n.s. » = variation du CA < 2 % ou REX précédent ≤ 0.
B20: B. TABLEAU DES KPI — MOIS SÉLECTIONNÉ (statut coloré automatiquement selon le benchmark) | S20: Paramètres de seuil (modifiables)
B21: Intitulé KPI | C21: Méthode de calcul | F21: Résultat | G21: Seuil vert | H21: Seuil orange | I21: Seuil rouge | J21: Statut | K21: Commentaire : écart → cause → recommandation chiffrée | O21: Recommandation | S21: Seuil 1 | T21: Seuil 2 | U21: Seuil 3 | V21: Règle
B22: Poids de la masse salariale / CA | C22: Charges de personnel ÷ Chiffre d'affaires | F22: =INDEX($E$68:$P$68,$D$5) -> 0.29468633 | G22: ="≤ "&FIXED($S22*100,1)&" %" -> ≤ 28.0 % | H22: =FIXED($S22*100,1)&" %"&" à "&FIXED($T22*100,1)&" %" -> 28.0 % à 35.0 % | I22: ="> "&FIXED($T22*100,1)&" %" -> > 35.0 % | J22: =IF(ISNUMBER($F22),IF($F22<=$S22,"● Conforme",IF($F22<=$T22,"● Vigilance","● Alerte")),"—") -> ● Vigilance | K22: =IF(OR(NOT(ISNUMBER($F22)),$J22="—"),"—",IF($J22="● Conforme","Ratio "&FIXED(($F22)*100,1)&" %"&" ≤ seuil "&FIXED(($S22)*100,1)&" %"&" → productivité conforme au secteur → maintenir la flexibilité (intérim, heures sup.).","Écart +"&FIXED(ABS($F22-$S22)*100,1)&" pts"&" vs seuil "&FIXED(($S22)*100,1)&" %"&" → volume du mois insuffisant pour absorber une masse salariale fixe → revenir au seuil = "&FIXED((($F22-$S22)*INDEX($E$44:$P$44,$D$5))/1000,0)&" kMAD"&"/mois (intérim, heures sup., polyvalence).")) -> Écart +1.5 pts vs seuil 28.0 % → volume du mois insuffisant pour absorber une masse salariale fixe → revenir au seuil = 207 kMAD/mois (intérim, heures sup., polyvalence). | O22: =IF(NOT(ISNUMBER($F22)),"—",IF($J22="● Conforme","Maintenir : piloter l'intérim à moins de 5 % des effectifs.","Geler l'intérim, annualiser le temps de travail, lisser la charge sur les mois creux.")) -> Geler l'intérim, annualiser le temps de travail, lisser la charge sur les mois creux. | S22: 0.28 | T22: 0.35 | U22: — | V22: Plus bas = mieux
B23: CAF / CA | C23: Capacité d'autofinancement (ESG) ÷ CA | F23: =INDEX($E$69:$P$69,$D$5) -> 0.1177124 | G23: ="≥ "&FIXED($S23*100,1)&" %" -> ≥ 12.0 % | H23: =FIXED($T23*100,1)&" %"&" à "&FIXED($S23*100,1)&" %" -> 8.0 % à 12.0 % | I23: ="< "&FIXED($T23*100,1)&" %" -> < 8.0 % | J23: =IF(ISNUMBER($F23),IF($F23>=$S23,"● Conforme",IF($F23>=$T23,"● Vigilance","● Alerte")),"—") -> ● Vigilance | K23: =IF(OR(NOT(ISNUMBER($F23)),$J23="—"),"—",IF($J23="● Conforme","CAF "&FIXED(($F23)*100,1)&" %"&" du CA → "&FIXED((INDEX($E$51:$P$51,$D$5))/1000,0)&" kMAD"&" de cash généré sur le mois → finance investissements et remboursements.","Écart −"&FIXED(ABS($F23-$S23)*100,1)&" pts"&" sous le seuil "&FIXED(($S23)*100,1)&" %"&" → marge de cash insuffisante (activité, change, charges fixes) → atteindre le seuil = +"&FIXED((($S23-$F23)*INDEX($E$44:$P$44,$D$5))/1000,0)&" kMAD"&" de CAF/mois.")) -> Écart −0.2 pts sous le seuil 12.0 % → marge de cash insuffisante (activité, change, charges fixes) → atteindre le seuil = +32 kMAD de CAF/mois. | O23: =IF(NOT(ISNUMBER($F23)),"—",IF($J23="● Conforme","Affecter la CAF au désendettement et au CAPEX productif.","Revoir prix de vente, couverture de change et achats matières.")) -> Revoir prix de vente, couverture de change et achats matières. | S23: 0.12 | T23: 0.08 | U23: — | V23: Plus haut = mieux
B24: Taux de croissance du résultat net | C24: (RN mois − RN mois précédent) ÷ |RN mois précédent| | F24: =IFERROR(INDEX($E$70:$P$70,$D$5),"—") -> 0.060528667 | G24: ="≥ "&FIXED($S24*100,1)&" %" -> ≥ 5.0 % | H24: =FIXED($T24*100,1)&" %"&" à "&FIXED($S24*100,1)&" %" -> -5.0 % à 5.0 % | I24: ="< "&FIXED($T24*100,1)&" %" -> < -5.0 % | J24: =IF(ISNUMBER($F24),IF($F24>=$S24,"● Conforme",IF($F24>=$T24,"● Vigilance","● Alerte")),"—") -> ● Conforme | K24: =IF(OR(NOT(ISNUMBER($F24)),$J24="—"),"—",IF($J24="● Conforme","RN en hausse de "&FIXED(($F24)*100,1)&" %"&" vs M-1 (+"&FIXED((INDEX($E$50:$P$50,$D$5)-INDEX($D$50:$O$50,$D$5))/1000,0)&" kMAD"&") → dynamique favorable → sécuriser le carnet de commandes.","RN "&FIXED(($F24)*100,1)&" %"&" vs M-1 ("&FIXED((INDEX($E$50:$P$50,$D$5)-INDEX($D$50:$O$50,$D$5))/1000,0)&" kMAD"&") → recul lié au volume, au change ou aux charges du mois → plan d'action pour récupérer "&FIXED((ABS(INDEX($E$50:$P$50,$D$5)-INDEX($D$50:$O$50,$D$5)))/1000,0)&" kMAD"&".")) -> RN en hausse de 6.1 % vs M-1 (+53 kMAD) → dynamique favorable → sécuriser le carnet de commandes. | O24: =IF(NOT(ISNUMBER($F24)),"—",IF($J24="● Conforme","Consolider : verrouiller les contrats cadres donneurs d'ordre.","Analyser le mois (volume, change, non courant) et ajuster le plan de charge.")) -> Consolider : verrouiller les contrats cadres donneurs d'ordre. | S24: 0.05 | T24: -0.05 | U24: — | V24: Plus haut = mieux
B25: Densité des charges externes | C25: Autres charges externes (613/614) ÷ CA | F25: =INDEX($E$71:$P$71,$D$5) -> 0.087340408 | G25: ="≤ "&FIXED($S25*100,1)&" %" -> ≤ 12.0 % | H25: =FIXED($S25*100,1)&" %"&" à "&FIXED($T25*100,1)&" %" -> 12.0 % à 18.0 % | I25: ="> "&FIXED($T25*100,1)&" %" -> > 18.0 % | J25: =IF(ISNUMBER($F25),IF($F25<=$S25,"● Conforme",IF($F25<=$T25,"● Vigilance","● Alerte")),"—") -> ● Conforme | K25: =IF(OR(NOT(ISNUMBER($F25)),$J25="—"),"—",IF($J25="● Conforme","Densité "&FIXED(($F25)*100,1)&" %"&" ≤ "&FIXED(($S25)*100,1)&" %"&" → achats externes maîtrisés → renégocier annuellement les contrats cadres.","Écart +"&FIXED(ABS($F25-$S25)*100,1)&" pts"&" → sous-traitance, intérim ou entretien au-dessus de la norme → revenir au seuil = "&FIXED((($F25-$S25)*INDEX($E$44:$P$44,$D$5))/1000,0)&" kMAD"&"/mois d'économies.")) -> Densité 8.7 % ≤ 12.0 % → achats externes maîtrisés → renégocier annuellement les contrats cadres. | O25: =IF(NOT(ISNUMBER($F25)),"—",IF($J25="● Conforme","Renégocier annuellement les contrats de sous-traitance.","Appel d'offres sur maintenance, transport et intérim ; internaliser si rentable.")) -> Renégocier annuellement les contrats de sous-traitance. | S25: 0.12 | T25: 0.18 | U25: — | V25: Plus bas = mieux
B26: Marge d'exploitation (levier opérationnel) | C26: Résultat d'exploitation ÷ CA | F26: =INDEX($E$72:$P$72,$D$5) -> 0.094393701 | G26: ="≥ "&FIXED($S26*100,1)&" %" -> ≥ 10.0 % | H26: =FIXED($T26*100,1)&" %"&" à "&FIXED($S26*100,1)&" %" -> 5.0 % à 10.0 % | I26: ="< "&FIXED($T26*100,1)&" %" -> < 5.0 % | J26: =IF(ISNUMBER($F26),IF($F26>=$S26,"● Conforme",IF($F26>=$T26,"● Vigilance","● Alerte")),"—") -> ● Vigilance | K26: =IF(OR(NOT(ISNUMBER($F26)),$J26="—"),"—",IF($J26="● Conforme","Marge "&FIXED(($F26)*100,1)&" %"&" ≥ "&FIXED(($S26)*100,1)&" %"&" → au-dessus du seuil sectoriel → préserver le mix produits à forte valeur.","Écart −"&FIXED(ABS($F26-$S26)*100,1)&" pts"&" sous le seuil "&FIXED(($S26)*100,1)&" %"&" → charges fixes non absorbées par le volume → atteindre le seuil = +"&FIXED((($S26-$F26)*INDEX($E$44:$P$44,$D$5))/1000,0)&" kMAD"&" de REX/mois.")) -> Écart −0.6 pts sous le seuil 10.0 % → charges fixes non absorbées par le volume → atteindre le seuil = +79 kMAD de REX/mois. | O26: =IF(NOT(ISNUMBER($F26)),"—",IF($J26="● Conforme","Préserver le mix produits à forte valeur ajoutée.","Hausse tarifaire indexée matières + plan d'économies sur charges fixes.")) -> Hausse tarifaire indexée matières + plan d'économies sur charges fixes. | S26: 0.1 | T26: 0.05 | U26: — | V26: Plus haut = mieux
B27: Taux d'endettement (gearing) | C27: Dettes de financement ÷ Capitaux propres | F27: =INDEX($E$73:$P$73,$D$5) -> 0.5641891 | G27: ="≤ "&FIXED($S27,2)&" x" -> ≤ 0.80 x | H27: =FIXED($S27,2)&" x"&" à "&FIXED($T27,2)&" x" -> 0.80 x à 1.50 x | I27: ="> "&FIXED($T27,2)&" x" -> > 1.50 x | J27: =IF(ISNUMBER($F27),IF($F27<=$S27,"● Conforme",IF($F27<=$T27,"● Vigilance","● Alerte")),"—") -> ● Conforme | K27: =IF(OR(NOT(ISNUMBER($F27)),$J27="—"),"—",IF($J27="● Conforme","Gearing "&FIXED($F27,2)&" x"&" ≤ "&FIXED($S27,2)&" x"&" → structure financière saine → capacité d'endettement résiduelle de "&FIXED((($S27-$F27)*INDEX($E$66:$P$66,$D$5))/1000,0)&" kMAD"&".","Gearing "&FIXED($F27,2)&" x"&" > "&FIXED($S27,2)&" x"&" → poids de la dette sur les fonds propres → désendettement de "&FIXED((($F27-$S27)*INDEX($E$66:$P$66,$D$5))/1000,0)&" kMAD"&" pour revenir au seuil.")) -> Gearing 0.56 x ≤ 0.80 x → structure financière saine → capacité d'endettement résiduelle de 20,229 kMAD. | O27: =IF(NOT(ISNUMBER($F27)),"—",IF($J27="● Conforme","Conserver la marge d'endettement pour le CAPEX.","Rembourser par anticipation ou renforcer les fonds propres.")) -> Conserver la marge d'endettement pour le CAPEX. | S27: 0.8 | T27: 1.5 | U27: — | V27: Plus bas = mieux
B28: Poids des charges financières | C28: Charges financières (CPC V) ÷ CA | F28: =INDEX($E$74:$P$74,$D$5) -> 0.023661426 | G28: ="≤ "&FIXED($S28*100,1)&" %" -> ≤ 2.0 % | H28: =FIXED($S28*100,1)&" %"&" à "&FIXED($T28*100,1)&" %" -> 2.0 % à 3.5 % | I28: ="> "&FIXED($T28*100,1)&" %" -> > 3.5 % | J28: =IF(ISNUMBER($F28),IF($F28<=$S28,"● Conforme",IF($F28<=$T28,"● Vigilance","● Alerte")),"—") -> ● Vigilance | K28: =IF(OR(NOT(ISNUMBER($F28)),$J28="—"),"—",IF($J28="● Conforme","Charges financières "&FIXED(($F28)*100,1)&" %"&" du CA → coût du financement maîtrisé → maintenir la couverture de change.","Écart +"&FIXED(ABS($F28-$S28)*100,1)&" pts"&" → intérêts + pertes de change ("&FIXED((INDEX($E$58:$P$58,$D$5))/1000,0)&" kMAD"&" de pertes de change) → couverture à terme EUR/USD et renégociation : gain visé "&FIXED((($F28-$S28)*INDEX($E$44:$P$44,$D$5))/1000,0)&" kMAD"&"/mois.")) -> Écart +0.4 pts → intérêts + pertes de change (70 kMAD de pertes de change) → couverture à terme EUR/USD et renégociation : gain visé 52 kMAD/mois. | O28: =IF(NOT(ISNUMBER($F28)),"—",IF($J28="● Conforme","Maintenir la politique de couverture.","Couverture à terme EUR/USD et renégociation des marges bancaires.")) -> Couverture à terme EUR/USD et renégociation des marges bancaires. | S28: 0.02 | T28: 0.035 | U28: — | V28: Plus bas = mieux
B29: Coût moyen de la dette (annualisé) | C29: (Intérêts 631 du mois × 12) ÷ Dette moyenne (M-1 ; M) | F29: =INDEX($E$75:$P$75,$D$5) -> 0.061400703 | G29: ="≤ "&FIXED($S29*100,1)&" %" -> ≤ 5.5 % | H29: =FIXED($S29*100,1)&" %"&" à "&FIXED($T29*100,1)&" %" -> 5.5 % à 7.5 % | I29: ="> "&FIXED($T29*100,1)&" %" -> > 7.5 % | J29: =IF(ISNUMBER($F29),IF($F29<=$S29,"● Conforme",IF($F29<=$T29,"● Vigilance","● Alerte")),"—") -> ● Vigilance | K29: =IF(OR(NOT(ISNUMBER($F29)),$J29="—"),"—",IF($J29="● Conforme","Taux "&FIXED(($F29)*100,1)&" %"&" ≤ "&FIXED(($S29)*100,1)&" %"&" → conditions bancaires compétitives → verrouiller les taux fixes.","Taux "&FIXED(($F29)*100,1)&" %"&" > "&FIXED(($S29)*100,1)&" %"&" → conditions bancaires élevées → renégocier au seuil = "&FIXED((($F29-$S29)*INDEX($E$65:$P$65,$D$5)/12)/1000,0)&" kMAD"&"/mois d'intérêts économisés.")) -> Taux 6.1 % > 5.5 % → conditions bancaires élevées → renégocier au seuil = 26 kMAD/mois d'intérêts économisés. | O29: =IF(NOT(ISNUMBER($F29)),"—",IF($J29="● Conforme","Verrouiller des taux fixes sur la dette longue.","Mettre les banques en concurrence ; viser le seuil sectoriel.")) -> Mettre les banques en concurrence ; viser le seuil sectoriel. | S29: 0.055 | T29: 0.075 | U29: — | V29: Plus bas = mieux
B30: BFR en jours de CA | C30: BFR (31+34+39+44) ÷ CA du mois × 30 j | F30: =INDEX($E$76:$P$76,$D$5) -> 54.335873 | G30: ="≤ "&FIXED($S30,0)&" j" -> ≤ 90 j | H30: =FIXED($S30,0)&" j"&" à "&FIXED($T30,0)&" j" -> 90 j à 120 j | I30: ="> "&FIXED($T30,0)&" j" -> > 120 j | J30: =IF(ISNUMBER($F30),IF($F30<=$S30,"● Conforme",IF($F30<=$T30,"● Vigilance","● Alerte")),"—") -> ● Conforme | K30: =IF(OR(NOT(ISNUMBER($F30)),$J30="—"),"—",IF($J30="● Conforme","BFR "&FIXED($F30,0)&" j"&" de CA ("&FIXED((INDEX($E$63:$P$63,$D$5))/1000,0)&" kMAD"&") → cycle d'exploitation maîtrisé → maintenir la discipline stocks/créances.","BFR "&FIXED($F30,0)&" j"&" ("&FIXED((INDEX($E$63:$P$63,$D$5))/1000,0)&" kMAD"&") > "&FIXED($S30,0)&" j"&" → stocks et créances lourds → revenir à "&FIXED($S30,0)&" j"&" libère "&FIXED((($F30-$S30)*INDEX($E$44:$P$44,$D$5)/$L$5)/1000,0)&" kMAD"&" de trésorerie.")) -> BFR 54 j de CA (25,538 kMAD) → cycle d'exploitation maîtrisé → maintenir la discipline stocks/créances. | O30: =IF(NOT(ISNUMBER($F30)),"—",IF($J30="● Conforme","Suivre mensuellement stocks, clients et fournisseurs.","Plan BFR : relances clients, stocks de sécurité optimisés, délais fournisseurs.")) -> Suivre mensuellement stocks, clients et fournisseurs. | S30: 90 | T30: 120 | U30: — | V30: Plus bas = mieux
B31: DSO — délai clients | C31: Clients (342) ÷ CA TTC du mois × 30 j | F31: =INDEX($E$77:$P$77,$D$5) -> 72.59735 | G31: ="≤ "&FIXED($S31,0)&" j" -> ≤ 60 j | H31: =FIXED($S31,0)&" j"&" à "&FIXED($T31,0)&" j" -> 60 j à 90 j | I31: ="> "&FIXED($T31,0)&" j" -> > 90 j | J31: =IF(ISNUMBER($F31),IF($F31<=$S31,"● Conforme",IF($F31<=$T31,"● Vigilance","● Alerte")),"—") -> ● Vigilance | K31: =IF(OR(NOT(ISNUMBER($F31)),$J31="—"),"—",IF($J31="● Conforme","DSO "&FIXED($F31,0)&" j"&" ≤ "&FIXED($S31,0)&" j"&" → recouvrement conforme à la loi 69-21 → poursuivre les relances systématiques.","DSO "&FIXED($F31,0)&" j"&" > "&FIXED($S31,0)&" j"&" → encaissements lents des donneurs d'ordre → revenir à "&FIXED($S31,0)&" j"&" libère "&FIXED((($F31-$S31)*INDEX($E$45:$P$45,$D$5)/$L$5)/1000,0)&" kMAD"&" (relances, affacturage export).")) -> DSO 73 j > 60 j → encaissements lents des donneurs d'ordre → revenir à 60 j libère 6,276 kMAD (relances, affacturage export). | O31: =IF(NOT(ISNUMBER($F31)),"—",IF($J31="● Conforme","Relances systématiques à J+30.","Affacturage export, escompte pour paiement anticipé, relances J+15.")) -> Affacturage export, escompte pour paiement anticipé, relances J+15. | S31: 60 | T31: 90 | U31: — | V31: Plus bas = mieux
B32: DPO — délai fournisseurs (loi 69-21) | C32: Fournisseurs (441) ÷ (Achats + ch. externes) TTC × 30 j | F32: =INDEX($E$78:$P$78,$D$5) -> 78.773027 | G32: =FIXED($S32,0)&" j"&" à "&FIXED($T32,0)&" j" -> 60 j à 90 j | H32: ="< "&FIXED($S32,0)&" j"&" ou "&FIXED($T32,0)&" j"&" à "&FIXED($U32,0)&" j" -> < 60 j ou 90 j à 120 j | I32: ="> "&FIXED($U32,0)&" j" -> > 120 j | J32: =IF(ISNUMBER($F32),IF(AND($F32>=$S32,$F32<=$T32),"● Conforme",IF($F32>$U32,"● Alerte","● Vigilance")),"—") -> ● Conforme | K32: =IF(OR(NOT(ISNUMBER($F32)),$J32="—"),"—",IF($J32="● Conforme","DPO "&FIXED($F32,0)&" j"&" dans la zone "&FIXED($S32,0)&" j"&"–"&FIXED($T32,0)&" j"&" → conforme à la loi 69-21 et favorable à la trésorerie.",IF($F32>$T32,"DPO "&FIXED($F32,0)&" j"&" > "&FIXED($T32,0)&" j"&" → risque de pénalités de retard (loi 69-21) → ramener à "&FIXED($T32,0)&" j"&" = "&FIXED((($F32-$T32)*INDEX($E$59:$P$59,$D$5)/$L$5)/1000,0)&" kMAD"&" à régler en priorité.","DPO "&FIXED($F32,0)&" j"&" < "&FIXED($S32,0)&" j"&" → fournisseurs payés trop vite → allonger à "&FIXED($S32,0)&" j"&" = "&FIXED((($S32-$F32)*INDEX($E$59:$P$59,$D$5)/$L$5)/1000,0)&" kMAD"&" de trésorerie gagnée."))) -> DPO 79 j dans la zone 60 j–90 j → conforme à la loi 69-21 et favorable à la trésorerie. | O32: =IF(NOT(ISNUMBER($F32)),"—",IF($J32="● Conforme","Respecter strictement les 60–90 j (loi 69-21).","Réaligner l'échéancier fournisseurs sur la zone 60–90 j.")) -> Respecter strictement les 60–90 j (loi 69-21). | S32: 60 | T32: 90 | U32: 120 | V32: Zone cible
B33: DIO — rotation des stocks | C33: Stocks (31) ÷ Achats consommés du mois × 30 j | F33: =INDEX($E$79:$P$79,$D$5) -> 82.717216 | G33: ="≤ "&FIXED($S33,0)&" j" -> ≤ 90 j | H33: =FIXED($S33,0)&" j"&" à "&FIXED($T33,0)&" j" -> 90 j à 130 j | I33: ="> "&FIXED($T33,0)&" j" -> > 130 j | J33: =IF(ISNUMBER($F33),IF($F33<=$S33,"● Conforme",IF($F33<=$T33,"● Vigilance","● Alerte")),"—") -> ● Conforme | K33: =IF(OR(NOT(ISNUMBER($F33)),$J33="—"),"—",IF($J33="● Conforme","DIO "&FIXED($F33,0)&" j"&" ≤ "&FIXED($S33,0)&" j"&" → rotation des stocks conforme aux cycles aéronautiques.","DIO "&FIXED($F33,0)&" j"&" > "&FIXED($S33,0)&" j"&" → stocks matières et en-cours lourds pour le niveau d'activité → revenir à "&FIXED($S33,0)&" j"&" libère "&FIXED((($F33-$S33)*INDEX($E$54:$P$54,$D$5)/$L$5)/1000,0)&" kMAD"&".")) -> DIO 83 j ≤ 90 j → rotation des stocks conforme aux cycles aéronautiques. | O33: =IF(NOT(ISNUMBER($F33)),"—",IF($J33="● Conforme","Maintenir la planification MRP.","Réduire les stocks de sécurité, accélérer la sortie des en-cours.")) -> Maintenir la planification MRP. | S33: 90 | T33: 130 | U33: — | V33: Plus bas = mieux
B34: CCC — cycle de conversion du cash | C34: DSO + DIO − DPO | F34: =INDEX($E$80:$P$80,$D$5) -> 76.541539 | G34: ="≤ "&FIXED($S34,0)&" j" -> ≤ 90 j | H34: =FIXED($S34,0)&" j"&" à "&FIXED($T34,0)&" j" -> 90 j à 130 j | I34: ="> "&FIXED($T34,0)&" j" -> > 130 j | J34: =IF(ISNUMBER($F34),IF($F34<=$S34,"● Conforme",IF($F34<=$T34,"● Vigilance","● Alerte")),"—") -> ● Conforme | K34: =IF(OR(NOT(ISNUMBER($F34)),$J34="—"),"—",IF($J34="● Conforme","Cycle "&FIXED($F34,0)&" j"&" ≤ "&FIXED($S34,0)&" j"&" → conversion du cash conforme → chaque jour gagné = "&FIXED((INDEX($E$44:$P$44,$D$5)/$L$5)/1000,0)&" kMAD"&" de trésorerie.","Cycle "&FIXED($F34,0)&" j"&" > "&FIXED($S34,0)&" j"&" → trésorerie immobilisée dans le cycle → réduire de "&FIXED($F34-$S34,0)&" j libère "&FIXED((($F34-$S34)*INDEX($E$44:$P$44,$D$5)/$L$5)/1000,0)&" kMAD"&".")) -> Cycle 77 j ≤ 90 j → conversion du cash conforme → chaque jour gagné = 470 kMAD de trésorerie. | O34: =IF(NOT(ISNUMBER($F34)),"—",IF($J34="● Conforme","Pilotage hebdomadaire du cash.","Agir sur les 3 leviers : DSO ↓, DIO ↓, DPO dans la zone légale.")) -> Pilotage hebdomadaire du cash. | S34: 90 | T34: 130 | U34: — | V34: Plus bas = mieux
B35: REX corrigé du change | C35: REX + (Gains de change 733 − Pertes de change 633) | F35: =INDEX($E$81:$P$81,$D$5) -> 1400951.2 | G35: ="≥ "&FIXED($S35,0)&" MAD" -> ≥ 0 MAD | H35: ="—" -> — | I35: ="< "&FIXED($T35,0)&" MAD" -> < 0 MAD | J35: =IF(ISNUMBER($F35),IF($F35>=$S35,"● Conforme",IF($F35>=$T35,"● Vigilance","● Alerte")),"—") -> ● Conforme | K35: =IF(OR(NOT(ISNUMBER($F35)),$J35="—"),"—",IF($J35="● Conforme","REX y compris change "&FIXED(($F35)/1000,0)&" kMAD"&" (effet change "&FIXED((INDEX($E$57:$P$57,$D$5)-INDEX($E$58:$P$58,$D$5))/1000,0)&" kMAD"&") → performance opérationnelle positive.","REX corrigé négatif ("&FIXED(($F35)/1000,0)&" kMAD"&") → perte d'exploitation sur le mois, aggravée ou non par le change ("&FIXED((INDEX($E$57:$P$57,$D$5)-INDEX($E$58:$P$58,$D$5))/1000,0)&" kMAD"&") → plan d'absorption des charges fixes.")) -> REX y compris change 1,401 kMAD (effet change 70 kMAD) → performance opérationnelle positive. | O35: =IF(NOT(ISNUMBER($F35)),"—",IF($J35="● Conforme","Neutraliser le change par couverture pour lire la vraie performance.","Plan d'absorption des charges fixes sur les mois creux.")) -> Neutraliser le change par couverture pour lire la vraie performance. | S35: 0 | T35: 0 | U35: — | V35: Plus haut = mieux
B36: Impact du change / REX | C36: (Gains de change − Pertes de change) ÷ REX (seuil en valeur absolue) | F36: =INDEX($E$82:$P$82,$D$5) -> 0.052593965 | G36: ="|x| ≤ "&FIXED($S36*100,1)&" %" -> |x| ≤ 5.0 % | H36: =FIXED($S36*100,1)&" %"&" à "&FIXED($T36*100,1)&" %" -> 5.0 % à 10.0 % | I36: ="|x| > "&FIXED($T36*100,1)&" %" -> |x| > 10.0 % | J36: =IF(ISNUMBER($F36),IF(ABS($F36)<=$S36,"● Conforme",IF(ABS($F36)<=$T36,"● Vigilance","● Alerte")),"—") -> ● Vigilance | K36: =IF(OR(NOT(ISNUMBER($F36)),$J36="—"),"—",IF($J36="● Conforme","Effet change "&FIXED(($F36)*100,1)&" %"&" du REX → exposition EUR/USD maîtrisée.","Effet change "&FIXED(($F36)*100,1)&" %"&" du REX ("&FIXED((INDEX($E$57:$P$57,$D$5)-INDEX($E$58:$P$58,$D$5))/1000,0)&" kMAD"&") → exposition EUR/USD non couverte → couvrir 70 % des flux à terme : volatilité réduite d'environ "&FIXED((ABS(INDEX($E$57:$P$57,$D$5)-INDEX($E$58:$P$58,$D$5))*0.7)/1000,0)&" kMAD"&".")) -> Effet change 5.3 % du REX (70 kMAD) → exposition EUR/USD non couverte → couvrir 70 % des flux à terme : volatilité réduite d'environ 49 kMAD. | O36: =IF(NOT(ISNUMBER($F36)),"—",IF($J36="● Conforme","Maintenir la couverture naturelle (achats en EUR/USD).","Couvrir 70 % des flux nets en devises à terme.")) -> Couvrir 70 % des flux nets en devises à terme. | S36: 0.05 | T36: 0.1 | U36: — | V36: |x| bas = mieux
B37: Poids du personnel dans la valeur ajoutée | C37: Charges de personnel ÷ Valeur ajoutée | F37: =INDEX($E$83:$P$83,$D$5) -> 0.67536403 | G37: ="≤ "&FIXED($S37*100,1)&" %" -> ≤ 60.0 % | H37: =FIXED($S37*100,1)&" %"&" à "&FIXED($T37*100,1)&" %" -> 60.0 % à 70.0 % | I37: ="> "&FIXED($T37*100,1)&" %" -> > 70.0 % | J37: =IF(ISNUMBER($F37),IF($F37<=$S37,"● Conforme",IF($F37<=$T37,"● Vigilance","● Alerte")),"—") -> ● Vigilance | K37: =IF(OR(NOT(ISNUMBER($F37)),$J37="—"),"—",IF($J37="● Conforme","Personnel "&FIXED(($F37)*100,1)&" %"&" de la VA → il reste "&FIXED((1-$F37)*100,1)&" %"&" de la VA pour l'État, les banques, l'investissement et les associés.","Écart +"&FIXED(ABS($F37-$S37)*100,1)&" pts"&" → la VA créée est absorbée par les salaires → revenir au seuil exige +"&FIXED((INDEX($E$52:$P$52,$D$5)/$S37-INDEX($E$47:$P$47,$D$5))/1000,0)&" kMAD"&" de VA/mois (prix, productivité).")) -> Écart +7.5 pts → la VA créée est absorbée par les salaires → revenir au seuil exige +773 kMAD de VA/mois (prix, productivité). | O37: =IF(NOT(ISNUMBER($F37)),"—",IF($J37="● Conforme","Investir le surplus de VA dans l'automatisation.","Gains de productivité (TRS machines) et révision tarifaire.")) -> Gains de productivité (TRS machines) et révision tarifaire. | S37: 0.6 | T37: 0.7 | U37: — | V37: Plus bas = mieux
B38: Taux de valeur ajoutée locale | C38: Valeur ajoutée (ESG) ÷ Production de l'exercice | F38: =INDEX($E$84:$P$84,$D$5) -> 0.45099087 | G38: ="≥ "&FIXED($S38*100,1)&" %" -> ≥ 40.0 % | H38: =FIXED($T38*100,1)&" %"&" à "&FIXED($S38*100,1)&" %" -> 30.0 % à 40.0 % | I38: ="< "&FIXED($T38*100,1)&" %" -> < 30.0 % | J38: =IF(ISNUMBER($F38),IF($F38>=$S38,"● Conforme",IF($F38>=$T38,"● Vigilance","● Alerte")),"—") -> ● Conforme | K38: =IF(OR(NOT(ISNUMBER($F38)),$J38="—"),"—",IF($J38="● Conforme","Taux "&FIXED(($F38)*100,1)&" %"&" ≥ "&FIXED(($S38)*100,1)&" %"&" → intégration locale conforme aux objectifs de l'écosystème aéronautique marocain.","Taux "&FIXED(($F38)*100,1)&" %"&" < "&FIXED(($S38)*100,1)&" %"&" → forte dépendance aux matières importées → localiser 5 % des achats = +"&FIXED((INDEX($E$54:$P$54,$D$5)*0.05)/1000,0)&" kMAD"&" de VA/mois.")) -> Taux 45.1 % ≥ 40.0 % → intégration locale conforme aux objectifs de l'écosystème aéronautique marocain. | O38: =IF(NOT(ISNUMBER($F38)),"—",IF($J38="● Conforme","Poursuivre la localisation fournisseurs.","Qualifier des fournisseurs locaux (traitements de surface, outillage).")) -> Poursuivre la localisation fournisseurs. | S38: 0.4 | T38: 0.3 | U38: — | V38: Plus haut = mieux
B39: Benchmark indicatif : sous-traitance aéronautique, Maroc (seuils internes de pilotage, à valider avec l'auditeur — ce ne sont pas des normes officielles). Seuils modifiables en colonnes S à U. DPO : zone cible 60–90 j, plafond légal 120 j (loi 69-21). Montants des commentaires en kMAD.
B41: C. GRILLE MENSUELLE — AGRÉGATS DE CALCUL ET KPI (source du sélecteur et des graphiques)
B42: Indicateur | C42: Unité | D42: Déc. N-1 | E42: Janvier | F42: Février | G42: Mars | H42: Avril | I42: Mai | J42: Juin | K42: Juillet | L42: Août | M42: Septembre | N42: Octobre | O42: Novembre | P42: Décembre | Q42: Exercice 2025
B43: Agrégats de calcul
B44: Chiffre d'affaires | C44: MAD | D44: =CPC!D11 -> 11500000 | E44: =CPC!E11 -> 10800000 | F44: =CPC!F11 -> 11200000 | G44: =CPC!G11 -> 12400000 | H44: =CPC!H11 -> 11900000 | I44: =CPC!I11 -> 12600000 | J44: =CPC!J11 -> 12800000 | K44: =CPC!K11 -> 11600000 | ... P44: =CPC!P11 -> 14100000 | Q44: =SUM(E44:P44) -> 142000000
B45: CA TTC (export HT + local TTC) | C45: MAD | D45: =D44*($H$5+(1-$H$5)*(1+$J$5)) -> 12190000 | E45: =E44*($H$5+(1-$H$5)*(1+$J$5)) -> 11448000 | F45: =F44*($H$5+(1-$H$5)*(1+$J$5)) -> 11872000 | G45: =G44*($H$5+(1-$H$5)*(1+$J$5)) -> 13144000 | H45: =H44*($H$5+(1-$H$5)*(1+$J$5)) -> 12614000 | I45: =I44*($H$5+(1-$H$5)*(1+$J$5)) -> 13356000 | J45: =J44*($H$5+(1-$H$5)*(1+$J$5)) -> 13568000 | K45: =K44*($H$5+(1-$H$5)*(1+$J$5)) -> 12296000 | ... P45: =P44*($H$5+(1-$H$5)*(1+$J$5)) -> 14946000 | Q45: =SUM(E45:P45) -> 150520000
B46: Production de l'exercice (ESG II) | C46: MAD | D46: =ESG!D14 -> 11551240 | E46: =ESG!E14 -> 10853967 | F46: =ESG!F14 -> 11352740 | G46: =ESG!G14 -> 12548633 | H46: =ESG!H14 -> 11951225 | I46: =ESG!I14 -> 12745249 | J46: =ESG!J14 -> 12845689 | K46: =ESG!K14 -> 11852263 | ... P46: =ESG!P14 -> 13641855 | Q46: =SUM(E46:P46) -> 1.4260239e+08
B47: Valeur ajoutée (ESG IV) | C47: MAD | D47: =ESG!D18 -> 5382187.8 | E47: =ESG!E18 -> 5169667.2 | F47: =ESG!F18 -> 5633560.5 | G47: =ESG!G18 -> 6259937.3 | H47: =ESG!H18 -> 5361457.2 | I47: =ESG!I18 -> 6112188.8 | J47: =ESG!J18 -> 6204176.9 | K47: =ESG!K18 -> 5812165.8 | ... P47: =ESG!P18 -> 6152352 | Q47: =SUM(E47:P47) -> 66780000
B48: Excédent brut d'exploitation (ESG V) | C48: MAD | D48: =ESG!D22 -> 1274668.2 | E48: =ESG!E22 -> 1803119.6 | F48: =ESG!F22 -> 2264108.3 | G48: =ESG!G22 -> 2840621.7 | H48: =ESG!H22 -> 1964229.1 | I48: =ESG!I22 -> 2680767.3 | J48: =ESG!J22 -> 3061660.9 | K48: =ESG!K22 -> 2409770.7 | ... P48: =ESG!P22 -> 2122617.9 | Q48: =SUM(E48:P48) -> 25780000
B49: Résultat d'exploitation (CPC III) | C49: MAD | D49: =CPC!D27 -> 503001.5 | E49: =CPC!E27 -> 1111452.9 | F49: =CPC!F27 -> 1572441.6 | G49: =CPC!G27 -> 2298955.1 | H49: =CPC!H27 -> 1272562.4 | I49: =CPC!I27 -> 1989100.6 | J49: =CPC!J27 -> 2269994.2 | K49: =CPC!K27 -> 1718104.1 | ... P49: =CPC!P27 -> 1330951.2 | Q49: =SUM(E49:P49) -> 17480000
B50: Résultat net (CPC XIII) | C50: MAD | D50: =CPC!D60 -> 206839.54 | E50: =CPC!E60 -> 735670.37 | F50: =CPC!F60 -> 1066687.8 | G50: =CPC!G60 -> 1066132.8 | H50: =CPC!H60 -> 855598.55 | I50: =CPC!I60 -> 1430961.9 | J50: =CPC!J60 -> 1681883.2 | K50: =CPC!K60 -> 1184822.4 | ... P50: =CPC!P60 -> 936411.55 | Q50: =SUM(E50:P50) -> 10960000
B51: Capacité d'autofinancement (ESG) | C51: MAD | D51: =ESG!D43 -> 930172.87 | E51: =ESG!E43 -> 1459003.7 | F51: =ESG!F43 -> 1790021.1 | G51: =ESG!G43 -> 1789466.1 | H51: =ESG!H43 -> 1578931.9 | I51: =ESG!I43 -> 2154295.3 | J51: =ESG!J43 -> 2405216.5 | K51: =ESG!K43 -> 1908155.7 | ... P51: =ESG!P43 -> 1659744.9 | Q51: =SUM(E51:P51) -> 19590000
B52: Charges de personnel | C52: MAD | D52: =CPC!D23 -> 3979693.9 | E52: =CPC!E23 -> 3242539.6 | F52: =CPC!F23 -> 3247018.7 | G52: =CPC!G23 -> 3298230 | H52: =CPC!H23 -> 3270907.5 | I52: =CPC!I23 -> 3300900.7 | J52: =CPC!J23 -> 3270750.3 | K52: =CPC!K23 -> 3275585.1 | ... P52: =CPC!P23 -> 4155077.2 | Q52: =SUM(E52:P52) -> 40000000
B53: Autres charges externes | C53: MAD | D53: =CPC!D21 -> 1158379.1 | E53: =CPC!E21 -> 1146546 | F53: =CPC!F21 -> 1122853.7 | G53: =CPC!G21 -> 1209678.1 | H53: =CPC!H21 -> 1164908.9 | I53: =CPC!I21 -> 1197993.7 | J53: =CPC!J21 -> 1185017.4 | K53: =CPC!K21 -> 1169684.8 | ... P53: =CPC!P21 -> 1231499.8 | Q53: =SUM(E53:P53) -> 14000000
B54: Achats consommés de matières et fournitures | C54: MAD | D54: =CPC!D20 -> 5025676.6 | E54: =CPC!E20 -> 4551601.7 | F54: =CPC!F20 -> 4610348.9 | G54: =CPC!G20 -> 5093312 | H54: =CPC!H20 -> 5438439 | I54: =CPC!I20 -> 5452504.5 | J54: =CPC!J20 -> 5473004.6 | K54: =CPC!K20 -> 4884054.7 | ... P54: =CPC!P20 -> 6274389.2 | Q54: =SUM(E54:P54) -> 62000000
B55: Charges financières (CPC V) | C55: MAD | D55: =CPC!D40 -> 395047.51 | E55: =CPC!E40 -> 341447.57 | F55: =CPC!F40 -> 369135.21 | G55: =CPC!G40 -> 1037678.4 | H55: =CPC!H40 -> 384189.39 | I55: =CPC!I40 -> 362002.78 | J55: =CPC!J40 -> 339526.79 | K55: =CPC!K40 -> 377909.57 | ... P55: =CPC!P40 -> 333626.11 | Q55: =SUM(E55:P55) -> 5150000
B56: Charges d'intérêts (631) | C56: MAD | D56: =CPC!D36 -> 282826.99 | E56: =CPC!E36 -> 280012.79 | F56: =CPC!F36 -> 277198.59 | G56: =CPC!G36 -> 274384.39 | H56: =CPC!H36 -> 271570.2 | I56: =CPC!I36 -> 268756 | J56: =CPC!J36 -> 265941.8 | K56: =CPC!K36 -> 265685.96 | ... P56: =CPC!P36 -> 249056.6 | Q56: =SUM(E56:P56) -> 3200000
B57: Gains de change (733) | C57: MAD | D57: =CPC!D31 -> 120000 | E57: =CPC!E31 -> 120000 | F57: =CPC!F31 -> 100000 | G57: =CPC!G31 -> 40000 | H57: =CPC!H31 -> 150000 | I57: =CPC!I31 -> 130000 | J57: =CPC!J31 -> 140000 | K57: =CPC!K31 -> 110000 | ... P57: =CPC!P31 -> 140000 | Q57: =SUM(E57:P57) -> 1400000
B58: Pertes de change (633) | C58: MAD | D58: =CPC!D37 -> 100000 | E58: =CPC!E37 -> 50000 | F58: =CPC!F37 -> 80000 | G58: =CPC!G37 -> 750000 | H58: =CPC!H37 -> 100000 | I58: =CPC!I37 -> 80000 | J58: =CPC!J37 -> 60000 | K58: =CPC!K37 -> 100000 | ... P58: =CPC!P37 -> 70000 | Q58: =SUM(E58:P58) -> 1800000
B59: Achats + charges externes TTC | C59: MAD | D59: =(SUMPRODUCT(((LEFT(Balance!$B$7:$B$400,3)="612"))*Balance!D$7:D$400)-SUMPRODUCT(((LEFT(Balance!$B$7:$B$400,4)="6124"))*Balance!D$7:D$400)+SUMPRODUCT(((LEFT(Balance!$B$7:$B$400,3)="613")+(LEFT(Balance!$B$7:$B$400,3)="614"))*Balance!D$7:D$400))*(1+$J$5) -> 7540866.8 | E59: =(SUMPRODUCT(((LEFT(Balance!$B$7:$B$400,3)="612"))*Balance!E$7:E$400)-SUMPRODUCT(((LEFT(Balance!$B$7:$B$400,4)="6124"))*Balance!E$7:E$400)+SUMPRODUCT(((LEFT(Balance!$B$7:$B$400,3)="613")+(LEFT(Balance!$B$7:$B$400,3)="614"))*Balance!E$7:E$400))*(1+$J$5) -> 7077777.2 | F59: =(SUMPRODUCT(((LEFT(Balance!$B$7:$B$400,3)="612"))*Balance!F$7:F$400)-SUMPRODUCT(((LEFT(Balance!$B$7:$B$400,4)="6124"))*Balance!F$7:F$400)+SUMPRODUCT(((LEFT(Balance!$B$7:$B$400,3)="613")+(LEFT(Balance!$B$7:$B$400,3)="614"))*Balance!F$7:F$400))*(1+$J$5) -> 7239843.1 | G59: =(SUMPRODUCT(((LEFT(Balance!$B$7:$B$400,3)="612"))*Balance!G$7:G$400)-SUMPRODUCT(((LEFT(Balance!$B$7:$B$400,4)="6124"))*Balance!G$7:G$400)+SUMPRODUCT(((LEFT(Balance!$B$7:$B$400,3)="613")+(LEFT(Balance!$B$7:$B$400,3)="614"))*Balance!G$7:G$400))*(1+$J$5) -> 7923588.1 | H59: =(SUMPRODUCT(((LEFT(Balance!$B$7:$B$400,3)="612"))*Balance!H$7:H$400)-SUMPRODUCT(((LEFT(Balance!$B$7:$B$400,4)="6124"))*Balance!H$7:H$400)+SUMPRODUCT(((LEFT(Balance!$B$7:$B$400,3)="613")+(LEFT(Balance!$B$7:$B$400,3)="614"))*Balance!H$7:H$400))*(1+$J$5) -> 7684017.4 | I59: =(SUMPRODUCT(((LEFT(Balance!$B$7:$B$400,3)="612"))*Balance!I$7:I$400)-SUMPRODUCT(((LEFT(Balance!$B$7:$B$400,4)="6124"))*Balance!I$7:I$400)+SUMPRODUCT(((LEFT(Balance!$B$7:$B$400,3)="613")+(LEFT(Balance!$B$7:$B$400,3)="614"))*Balance!I$7:I$400))*(1+$J$5) -> 8100597.8 | J59: =(SUMPRODUCT(((LEFT(Balance!$B$7:$B$400,3)="612"))*Balance!J$7:J$400)-SUMPRODUCT(((LEFT(Balance!$B$7:$B$400,4)="6124"))*Balance!J$7:J$400)+SUMPRODUCT(((LEFT(Balance!$B$7:$B$400,3)="613")+(LEFT(Balance!$B$7:$B$400,3)="614"))*Balance!J$7:J$400))*(1+$J$5) -> 8229626.3 | K59: =(SUMPRODUCT(((LEFT(Balance!$B$7:$B$400,3)="612"))*Balance!K$7:K$400)-SUMPRODUCT(((LEFT(Balance!$B$7:$B$400,4)="6124"))*Balance!K$7:K$400)+SUMPRODUCT(((LEFT(Balance!$B$7:$B$400,3)="613")+(LEFT(Balance!$B$7:$B$400,3)="614"))*Balance!K$7:K$400))*(1+$J$5) -> 7504487.4 | ... P59: =(SUMPRODUCT(((LEFT(Balance!$B$7:$B$400,3)="612"))*Balance!P$7:P$400)-SUMPRODUCT(((LEFT(Balance!$B$7:$B$400,4)="6124"))*Balance!P$7:P$400)+SUMPRODUCT(((LEFT(Balance!$B$7:$B$400,3)="613")+(LEFT(Balance!$B$7:$B$400,3)="614"))*Balance!P$7:P$400))*(1+$J$5) -> 8767066.7 | Q59: =SUM(E59:P59) -> 91560000
B60: Stocks (classe 31) | C60: MAD | D60: =SUMPRODUCT(((LEFT(Balance!$B$7:$B$400,2)="31"))*Balance!D$7:D$400) -> 15800000 | E60: =SUMPRODUCT(((LEFT(Balance!$B$7:$B$400,2)="31"))*Balance!E$7:E$400) -> 16100000 | F60: =SUMPRODUCT(((LEFT(Balance!$B$7:$B$400,2)="31"))*Balance!F$7:F$400) -> 16600000 | G60: =SUMPRODUCT(((LEFT(Balance!$B$7:$B$400,2)="31"))*Balance!G$7:G$400) -> 17100000 | H60: =SUMPRODUCT(((LEFT(Balance!$B$7:$B$400,2)="31"))*Balance!H$7:H$400) -> 17000000 | I60: =SUMPRODUCT(((LEFT(Balance!$B$7:$B$400,2)="31"))*Balance!I$7:I$400) -> 17300000 | J60: =SUMPRODUCT(((LEFT(Balance!$B$7:$B$400,2)="31"))*Balance!J$7:J$400) -> 17600000 | K60: =SUMPRODUCT(((LEFT(Balance!$B$7:$B$400,2)="31"))*Balance!K$7:K$400) -> 18100000 | ... P60: =SUMPRODUCT(((LEFT(Balance!$B$7:$B$400,2)="31"))*Balance!P$7:P$400) -> 17300000 | Q60: =P60 -> 17300000
B61: Clients et comptes rattachés (342) | C61: MAD | D61: =SUMPRODUCT(((LEFT(Balance!$B$7:$B$400,3)="342"))*Balance!D$7:D$400) -> 32617000 | E61: =SUMPRODUCT(((LEFT(Balance!$B$7:$B$400,3)="342"))*Balance!E$7:E$400) -> 31398000 | F61: =SUMPRODUCT(((LEFT(Balance!$B$7:$B$400,3)="342"))*Balance!F$7:F$400) -> 30815000 | G61: =SUMPRODUCT(((LEFT(Balance!$B$7:$B$400,3)="342"))*Balance!G$7:G$400) -> 32140000 | H61: =SUMPRODUCT(((LEFT(Balance!$B$7:$B$400,3)="342"))*Balance!H$7:H$400) -> 33094000 | I61: =SUMPRODUCT(((LEFT(Balance!$B$7:$B$400,3)="342"))*Balance!I$7:I$400) -> 33942000 | J61: =SUMPRODUCT(((LEFT(Balance!$B$7:$B$400,3)="342"))*Balance!J$7:J$400) -> 34631000 | K61: =SUMPRODUCT(((LEFT(Balance!$B$7:$B$400,3)="342"))*Balance!K$7:K$400) -> 33942000 | ... P61: =SUMPRODUCT(((LEFT(Balance!$B$7:$B$400,3)="342"))*Balance!P$7:P$400) -> 36168000 | Q61: =P61 -> 36168000
B62: Fournisseurs et comptes rattachés (441) | C62: MAD | D62: =-SUMPRODUCT(((LEFT(Balance!$B$7:$B$400,3)="441"))*Balance!D$7:D$400) -> 21151545 | E62: =-SUMPRODUCT(((LEFT(Balance!$B$7:$B$400,3)="441"))*Balance!E$7:E$400) -> 20663586 | F62: =-SUMPRODUCT(((LEFT(Balance!$B$7:$B$400,3)="441"))*Balance!F$7:F$400) -> 20302890 | G62: =-SUMPRODUCT(((LEFT(Balance!$B$7:$B$400,3)="441"))*Balance!G$7:G$400) -> 20776587 | H62: =-SUMPRODUCT(((LEFT(Balance!$B$7:$B$400,3)="441"))*Balance!H$7:H$400) -> 21380223 | I62: =-SUMPRODUCT(((LEFT(Balance!$B$7:$B$400,3)="441"))*Balance!I$7:I$400) -> 22062638 | J62: =-SUMPRODUCT(((LEFT(Balance!$B$7:$B$400,3)="441"))*Balance!J$7:J$400) -> 22301406 | K62: =-SUMPRODUCT(((LEFT(Balance!$B$7:$B$400,3)="441"))*Balance!K$7:K$400) -> 22116818 | ... P62: =-SUMPRODUCT(((LEFT(Balance!$B$7:$B$400,3)="441"))*Balance!P$7:P$400) -> 23020279 | Q62: =P62 -> 23020279
B63: BFR (31 + 34 + 39 + 44) | C63: MAD | D63: =SUMPRODUCT(((LEFT(Balance!$B$7:$B$400,2)="31")+(LEFT(Balance!$B$7:$B$400,2)="34")+(LEFT(Balance!$B$7:$B$400,2)="39")+(LEFT(Balance!$B$7:$B$400,2)="44"))*Balance!D$7:D$400) -> 23270357 | E63: =SUMPRODUCT(((LEFT(Balance!$B$7:$B$400,2)="31")+(LEFT(Balance!$B$7:$B$400,2)="34")+(LEFT(Balance!$B$7:$B$400,2)="39")+(LEFT(Balance!$B$7:$B$400,2)="44"))*Balance!E$7:E$400) -> 22971419 | F63: =SUMPRODUCT(((LEFT(Balance!$B$7:$B$400,2)="31")+(LEFT(Balance!$B$7:$B$400,2)="34")+(LEFT(Balance!$B$7:$B$400,2)="39")+(LEFT(Balance!$B$7:$B$400,2)="44"))*Balance!F$7:F$400) -> 22826459 | G63: =SUMPRODUCT(((LEFT(Balance!$B$7:$B$400,2)="31")+(LEFT(Balance!$B$7:$B$400,2)="34")+(LEFT(Balance!$B$7:$B$400,2)="39")+(LEFT(Balance!$B$7:$B$400,2)="44"))*Balance!G$7:G$400) -> 24635769 | H63: =SUMPRODUCT(((LEFT(Balance!$B$7:$B$400,2)="31")+(LEFT(Balance!$B$7:$B$400,2)="34")+(LEFT(Balance!$B$7:$B$400,2)="39")+(LEFT(Balance!$B$7:$B$400,2)="44"))*Balance!H$7:H$400) -> 20177038 | I63: =SUMPRODUCT(((LEFT(Balance!$B$7:$B$400,2)="31")+(LEFT(Balance!$B$7:$B$400,2)="34")+(LEFT(Balance!$B$7:$B$400,2)="39")+(LEFT(Balance!$B$7:$B$400,2)="44"))*Balance!I$7:I$400) -> 22488338 | J63: =SUMPRODUCT(((LEFT(Balance!$B$7:$B$400,2)="31")+(LEFT(Balance!$B$7:$B$400,2)="34")+(LEFT(Balance!$B$7:$B$400,2)="39")+(LEFT(Balance!$B$7:$B$400,2)="44"))*Balance!J$7:J$400) -> 25435352 | K63: =SUMPRODUCT(((LEFT(Balance!$B$7:$B$400,2)="31")+(LEFT(Balance!$B$7:$B$400,2)="34")+(LEFT(Balance!$B$7:$B$400,2)="39")+(LEFT(Balance!$B$7:$B$400,2)="44"))*Balance!K$7:K$400) -> 25167606 | ... P63: =SUMPRODUCT(((LEFT(Balance!$B$7:$B$400,2)="31")+(LEFT(Balance!$B$7:$B$400,2)="34")+(LEFT(Balance!$B$7:$B$400,2)="39")+(LEFT(Balance!$B$7:$B$400,2)="44"))*Balance!P$7:P$400) -> 25537860 | Q63: =P63 -> 25537860
B64: Dettes de financement (148 + 553 + 554) | C64: MAD | D64: =-SUMPRODUCT(((LEFT(Balance!$B$7:$B$400,3)="148")+(LEFT(Balance!$B$7:$B$400,3)="553")+(LEFT(Balance!$B$7:$B$400,3)="554"))*Balance!D$7:D$400) -> 55000000 | E64: =-SUMPRODUCT(((LEFT(Balance!$B$7:$B$400,3)="148")+(LEFT(Balance!$B$7:$B$400,3)="553")+(LEFT(Balance!$B$7:$B$400,3)="554"))*Balance!E$7:E$400) -> 54450000 | F64: =-SUMPRODUCT(((LEFT(Balance!$B$7:$B$400,3)="148")+(LEFT(Balance!$B$7:$B$400,3)="553")+(LEFT(Balance!$B$7:$B$400,3)="554"))*Balance!F$7:F$400) -> 53900000 | G64: =-SUMPRODUCT(((LEFT(Balance!$B$7:$B$400,3)="148")+(LEFT(Balance!$B$7:$B$400,3)="553")+(LEFT(Balance!$B$7:$B$400,3)="554"))*Balance!G$7:G$400) -> 53350000 | H64: =-SUMPRODUCT(((LEFT(Balance!$B$7:$B$400,3)="148")+(LEFT(Balance!$B$7:$B$400,3)="553")+(LEFT(Balance!$B$7:$B$400,3)="554"))*Balance!H$7:H$400) -> 52800000 | I64: =-SUMPRODUCT(((LEFT(Balance!$B$7:$B$400,3)="148")+(LEFT(Balance!$B$7:$B$400,3)="553")+(LEFT(Balance!$B$7:$B$400,3)="554"))*Balance!I$7:I$400) -> 52250000 | J64: =-SUMPRODUCT(((LEFT(Balance!$B$7:$B$400,3)="148")+(LEFT(Balance!$B$7:$B$400,3)="553")+(LEFT(Balance!$B$7:$B$400,3)="554"))*Balance!J$7:J$400) -> 51700000 | K64: =-SUMPRODUCT(((LEFT(Balance!$B$7:$B$400,3)="148")+(LEFT(Balance!$B$7:$B$400,3)="553")+(LEFT(Balance!$B$7:$B$400,3)="554"))*Balance!K$7:K$400) -> 52150000 | ... P64: =-SUMPRODUCT(((LEFT(Balance!$B$7:$B$400,3)="148")+(LEFT(Balance!$B$7:$B$400,3)="553")+(LEFT(Balance!$B$7:$B$400,3)="554"))*Balance!P$7:P$400) -> 48400000 | Q64: =P64 -> 48400000
B65: Dette moyenne (M-1 ; M) | C65: MAD | D65: =(D64+D64)/2 -> 55000000 | E65: =(D64+E64)/2 -> 54725000 | F65: =(E64+F64)/2 -> 54175000 | G65: =(F64+G64)/2 -> 53625000 | H65: =(G64+H64)/2 -> 53075000 | I65: =(H64+I64)/2 -> 52525000 | J65: =(I64+J64)/2 -> 51975000 | K65: =(J64+K64)/2 -> 51925000 | L65: =(K64+L64)/2 -> 52875000 | ... P65: =(O64+P64)/2 -> 48675000 | Q65: =(D64+P64)/2 -> 51700000
B66: Capitaux propres (11 + 13 + résultat) | C66: MAD | D66: =-SUMPRODUCT(((LEFT(Balance!$B$7:$B$400,2)="11")+(LEFT(Balance!$B$7:$B$400,2)="13"))*Balance!D$7:D$400)+D50 -> 74946840 | E66: =-SUMPRODUCT(((LEFT(Balance!$B$7:$B$400,2)="11")+(LEFT(Balance!$B$7:$B$400,2)="13"))*Balance!E$7:E$400)+E50 -> 75672510 | F66: =-SUMPRODUCT(((LEFT(Balance!$B$7:$B$400,2)="11")+(LEFT(Balance!$B$7:$B$400,2)="13"))*Balance!F$7:F$400)+F50 -> 76729198 | G66: =-SUMPRODUCT(((LEFT(Balance!$B$7:$B$400,2)="11")+(LEFT(Balance!$B$7:$B$400,2)="13"))*Balance!G$7:G$400)+G50 -> 77785330 | H66: =-SUMPRODUCT(((LEFT(Balance!$B$7:$B$400,2)="11")+(LEFT(Balance!$B$7:$B$400,2)="13"))*Balance!H$7:H$400)+H50 -> 78630929 | I66: =-SUMPRODUCT(((LEFT(Balance!$B$7:$B$400,2)="11")+(LEFT(Balance!$B$7:$B$400,2)="13"))*Balance!I$7:I$400)+I50 -> 80051891 | J66: =-SUMPRODUCT(((LEFT(Balance!$B$7:$B$400,2)="11")+(LEFT(Balance!$B$7:$B$400,2)="13"))*Balance!J$7:J$400)+J50 -> 81723774 | K66: =-SUMPRODUCT(((LEFT(Balance!$B$7:$B$400,2)="11")+(LEFT(Balance!$B$7:$B$400,2)="13"))*Balance!K$7:K$400)+K50 -> 82898597 | ... P66: =-SUMPRODUCT(((LEFT(Balance!$B$7:$B$400,2)="11")+(LEFT(Balance!$B$7:$B$400,2)="13"))*Balance!P$7:P$400)+P50 -> 85786840 | Q66: =P66 -> 85786840
B67: KPI mensuels (mise en forme selon le benchmark)
B68: Poids de la masse salariale / CA | C68: % | D68: =IFERROR(D52/D44,"—") -> 0.34606034 | E68: =IFERROR(E52/E44,"—") -> 0.30023515 | F68: =IFERROR(F52/F44,"—") -> 0.28991239 | G68: =IFERROR(G52/G44,"—") -> 0.26598629 | H68: =IFERROR(H52/H44,"—") -> 0.27486618 | I68: =IFERROR(I52/I44,"—") -> 0.26197624 | J68: =IFERROR(J52/J44,"—") -> 0.25552737 | K68: =IFERROR(K52/K44,"—") -> 0.28237802 | ... Q68: =IFERROR(Q52/Q44,"—") -> 0.28169014
B69: CAF / CA | C69: % | D69: =IFERROR(D51/D44,"—") -> 0.080884597 | E69: =IFERROR(E51/E44,"—") -> 0.13509294 | F69: =IFERROR(F51/F44,"—") -> 0.15982331 | G69: =IFERROR(G51/G44,"—") -> 0.14431178 | H69: =IFERROR(H51/H44,"—") -> 0.13268335 | I69: =IFERROR(I51/I44,"—") -> 0.17097582 | J69: =IFERROR(J51/J44,"—") -> 0.18790754 | K69: =IFERROR(K51/K44,"—") -> 0.16449618 | ... Q69: =IFERROR(Q51/Q44,"—") -> 0.13795775
B70: Taux de croissance du résultat net | C70: % | D70: =IFERROR(NA(),"—") -> — | E70: =IFERROR((E50-D50)/ABS(D50),"—") -> 2.5567202 | F70: =IFERROR((F50-E50)/ABS(E50),"—") -> 0.44995343 | G70: =IFERROR((G50-F50)/ABS(F50),"—") -> -0.00052028345 | H70: =IFERROR((H50-G50)/ABS(G50),"—") -> -0.1974747 | I70: =IFERROR((I50-H50)/ABS(H50),"—") -> 0.67246888 | J70: =IFERROR((J50-I50)/ABS(I50),"—") -> 0.17535144 | K70: =IFERROR((K50-J50)/ABS(J50),"—") -> -0.29553824 | L70: =IFERROR((L50-K50)/ABS(K50),"—") -> -1.3354803 | ... P70: =IFERROR((P50-O50)/ABS(O50),"—") -> 0.060528667 | Q70: —
B71: Densité des charges externes | C71: % | D71: =IFERROR(D53/D44,"—") -> 0.10072861 | E71: =IFERROR(E53/E44,"—") -> 0.10616166 | F71: =IFERROR(F53/F44,"—") -> 0.1002548 | G71: =IFERROR(G53/G44,"—") -> 0.097554687 | H71: =IFERROR(H53/H44,"—") -> 0.0978915 | I71: =IFERROR(I53/I44,"—") -> 0.095078863 | J71: =IFERROR(J53/J44,"—") -> 0.092579483 | K71: =IFERROR(K53/K44,"—") -> 0.10083489 | ... Q71: =IFERROR(Q53/Q44,"—") -> 0.098591549
B72: Marge d'exploitation (levier opérationnel) | C72: % | D72: =IFERROR(D49/D44,"—") -> 0.043739261 | E72: =IFERROR(E49/E44,"—") -> 0.1029123 | F72: =IFERROR(F49/F44,"—") -> 0.14039657 | G72: =IFERROR(G49/G44,"—") -> 0.1853996 | H72: =IFERROR(H49/H44,"—") -> 0.10693802 | I72: =IFERROR(I49/I44,"—") -> 0.15786513 | J72: =IFERROR(J49/J44,"—") -> 0.1773433 | K72: =IFERROR(K49/K44,"—") -> 0.14811242 | ... Q72: =IFERROR(Q49/Q44,"—") -> 0.12309859
B73: Taux d'endettement (gearing) | C73: x | D73: =IFERROR(D64/D66,"—") -> 0.73385349 | E73: =IFERROR(E64/E66,"—") -> 0.71954796 | F73: =IFERROR(F64/F66,"—") -> 0.70247053 | G73: =IFERROR(G64/G66,"—") -> 0.68586197 | H73: =IFERROR(H64/H66,"—") -> 0.67149149 | I73: =IFERROR(I64/I66,"—") -> 0.65270163 | J73: =IFERROR(J64/J66,"—") -> 0.63261885 | K73: =IFERROR(K64/K66,"—") -> 0.62908182 | ... Q73: =IFERROR(Q64/Q66,"—") -> 0.5641891
B74: Poids des charges financières | C74: % | D74: =IFERROR(D55/D44,"—") -> 0.034351957 | E74: =IFERROR(E55/E44,"—") -> 0.031615516 | F74: =IFERROR(F55/F44,"—") -> 0.032958501 | G74: =IFERROR(G55/G44,"—") -> 0.083683741 | H74: =IFERROR(H55/H44,"—") -> 0.032284823 | I74: =IFERROR(I55/I44,"—") -> 0.028730379 | J74: =IFERROR(J55/J44,"—") -> 0.02652553 | K74: =IFERROR(K55/K44,"—") -> 0.032578411 | ... Q74: =IFERROR(Q55/Q44,"—") -> 0.036267606
B75: Coût moyen de la dette (annualisé) | C75: % | D75: =IFERROR(D56*12/D65,"—") -> 0.061707707 | E75: =IFERROR(E56*12/E65,"—") -> 0.061400703 | F75: =IFERROR(F56*12/F65,"—") -> 0.061400703 | G75: =IFERROR(G56*12/G65,"—") -> 0.061400703 | H75: =IFERROR(H56*12/H65,"—") -> 0.061400705 | I75: =IFERROR(I56*12/I65,"—") -> 0.061400704 | J75: =IFERROR(J56*12/J65,"—") -> 0.061400704 | K75: =IFERROR(K56*12/K65,"—") -> 0.061400703 | ... P75: =IFERROR(P56*12/P65,"—") -> 0.061400703 | Q75: =IFERROR(Q56/Q65,"—") -> 0.061895551
B76: BFR en jours de CA | C76: jours | D76: =IFERROR(D63/D44*$L$5,"—") -> 60.705279 | E76: =IFERROR(E63/E44*$L$5,"—") -> 63.809498 | F76: =IFERROR(F63/F44*$L$5,"—") -> 61.142302 | G76: =IFERROR(G63/G44*$L$5,"—") -> 59.602667 | H76: =IFERROR(H63/H44*$L$5,"—") -> 50.866482 | I76: =IFERROR(I63/I44*$L$5,"—") -> 53.543663 | J76: =IFERROR(J63/J44*$L$5,"—") -> 59.614105 | K76: =IFERROR(K63/K44*$L$5,"—") -> 65.088637 | ... P76: =IFERROR(P63/P44*$L$5,"—") -> 54.335873 | Q76: =IFERROR(Q63/Q44*12*$L$5,"—") -> 64.743871
B77: DSO — délai clients | C77: jours | D77: =IFERROR(D61/D45*$L$5,"—") -> 80.271534 | E77: =IFERROR(E61/E45*$L$5,"—") -> 82.279874 | F77: =IFERROR(F61/F45*$L$5,"—") -> 77.868093 | G77: =IFERROR(G61/G45*$L$5,"—") -> 73.356665 | H77: =IFERROR(H61/H45*$L$5,"—") -> 78.707785 | I77: =IFERROR(I61/I45*$L$5,"—") -> 76.239892 | J77: =IFERROR(J61/J45*$L$5,"—") -> 76.572081 | K77: =IFERROR(K61/K45*$L$5,"—") -> 82.812297 | ... P77: =IFERROR(P61/P45*$L$5,"—") -> 72.59735 | Q77: =IFERROR(Q61/Q45*12*$L$5,"—") -> 86.503322
B78: DPO — délai fournisseurs (loi 69-21) | C78: jours | D78: =IFERROR(D62/D59*$L$5,"—") -> 84.147666 | E78: =IFERROR(E62/E59*$L$5,"—") -> 87.585067 | F78: =IFERROR(F62/F59*$L$5,"—") -> 84.129819 | G78: =IFERROR(G62/G59*$L$5,"—") -> 78.663556 | H78: =IFERROR(H62/H59*$L$5,"—") -> 83.47283 | I78: =IFERROR(I62/I59*$L$5,"—") -> 81.707445 | J78: =IFERROR(J62/J59*$L$5,"—") -> 81.296786 | K78: =IFERROR(K62/K59*$L$5,"—") -> 88.414373 | ... P78: =IFERROR(P62/P59*$L$5,"—") -> 78.773027 | Q78: =IFERROR(Q62/Q59*12*$L$5,"—") -> 90.512239
B79: DIO — rotation des stocks | C79: jours | D79: =IFERROR(D60/D54*$L$5,"—") -> 94.315659 | E79: =IFERROR(E60/E54*$L$5,"—") -> 106.11649 | F79: =IFERROR(F60/F54*$L$5,"—") -> 108.01786 | G79: =IFERROR(G60/G54*$L$5,"—") -> 100.72032 | H79: =IFERROR(H60/H54*$L$5,"—") -> 93.776909 | I79: =IFERROR(I60/I54*$L$5,"—") -> 95.185617 | J79: =IFERROR(J60/J54*$L$5,"—") -> 96.473517 | K79: =IFERROR(K60/K54*$L$5,"—") -> 111.17812 | ... P79: =IFERROR(P60/P54*$L$5,"—") -> 82.717216 | Q79: =IFERROR(Q60/Q54*12*$L$5,"—") -> 100.45161
B80: CCC — cycle de conversion du cash | C80: jours | D80: =IFERROR(D77+D79-D78,"—") -> 90.439527 | E80: =IFERROR(E77+E79-E78,"—") -> 100.8113 | F80: =IFERROR(F77+F79-F78,"—") -> 101.75613 | G80: =IFERROR(G77+G79-G78,"—") -> 95.413427 | H80: =IFERROR(H77+H79-H78,"—") -> 89.011865 | I80: =IFERROR(I77+I79-I78,"—") -> 89.718064 | J80: =IFERROR(J77+J79-J78,"—") -> 91.748812 | K80: =IFERROR(K77+K79-K78,"—") -> 105.57604 | ... Q80: =IFERROR(Q77+Q79-Q78,"—") -> 96.442696
B81: REX corrigé du change | C81: MAD | D81: =IFERROR(D49+D57-D58,"—") -> 523001.5 | E81: =IFERROR(E49+E57-E58,"—") -> 1181452.9 | F81: =IFERROR(F49+F57-F58,"—") -> 1592441.6 | G81: =IFERROR(G49+G57-G58,"—") -> 1588955.1 | H81: =IFERROR(H49+H57-H58,"—") -> 1322562.4 | I81: =IFERROR(I49+I57-I58,"—") -> 2039100.6 | J81: =IFERROR(J49+J57-J58,"—") -> 2349994.2 | K81: =IFERROR(K49+K57-K58,"—") -> 1728104.1 | ... Q81: =IFERROR(Q49+Q57-Q58,"—") -> 17080000
B82: Impact du change / REX | C82: % | D82: =IFERROR((D57-D58)/D49,"—") -> 0.039761313 | E82: =IFERROR((E57-E58)/E49,"—") -> 0.062980627 | F82: =IFERROR((F57-F58)/F49,"—") -> 0.012719073 | G82: =IFERROR((G57-G58)/G49,"—") -> -0.30883596 | H82: =IFERROR((H57-H58)/H49,"—") -> 0.039290804 | I82: =IFERROR((I57-I58)/I49,"—") -> 0.025136989 | J82: =IFERROR((J57-J58)/J49,"—") -> 0.035242381 | K82: =IFERROR((K57-K58)/K49,"—") -> 0.0058203692 | ... Q82: =IFERROR((Q57-Q58)/Q49,"—") -> -0.022883295
B83: Poids du personnel dans la valeur ajoutée | C83: % | D83: =IFERROR(D52/D47,"—") -> 0.73941936 | E83: =IFERROR(E52/E47,"—") -> 0.62722405 | F83: =IFERROR(F52/F47,"—") -> 0.57637061 | G83: =IFERROR(G52/G47,"—") -> 0.52687908 | H83: =IFERROR(H52/H47,"—") -> 0.61007808 | I83: =IFERROR(I52/I47,"—") -> 0.54005214 | J83: =IFERROR(J52/J47,"—") -> 0.52718521 | K83: =IFERROR(K52/K47,"—") -> 0.56357392 | ... Q83: =IFERROR(Q52/Q47,"—") -> 0.59898173
B84: Taux de valeur ajoutée locale | C84: % | D84: =IFERROR(D47/D46,"—") -> 0.46594026 | E84: =IFERROR(E47/E46,"—") -> 0.47629289 | F84: =IFERROR(F47/F46,"—") -> 0.49622917 | G84: =IFERROR(G47/G46,"—") -> 0.49885413 | H84: =IFERROR(H47/H46,"—") -> 0.4486115 | I84: =IFERROR(I47/I46,"—") -> 0.47956607 | J84: =IFERROR(J47/J46,"—") -> 0.48297735 | K84: =IFERROR(K47/K46,"—") -> 0.49038448 | ... Q84: =IFERROR(Q47/Q46,"—") -> 0.46829511

Sheet DASHBOARD
B1: DASHBOARD DIRECTION GÉNÉRALE — PERFORMANCE 2025
B2: ="Société : "&Accueil!$C$8&" │ Exercice : "&Accueil!$C$11&" │ Date d'arrêté : "&Accueil!$C$12&" │ Responsable : "&Accueil!$C$15 -> Société : AéroAtlas Composites SARL │ Exercice : 2025 │ Date d'arrêté : 31/12/2025 │ Responsable : Karim El Fassi (DAF)
B4: ← Accueil | C4: Choisissez le mois dans le sélecteur : cartes et graphiques se mettent à jour (sources : Reporting)
B5: MOIS ▸ | C5: Décembre | F5: Sélecteur propre au Dashboard (indépendant du Reporting) — il lit la grille mensuelle du Reporting. | P5: =MATCH($C$5,Reporting!$E$42:$P$42,0) -> 12
B7: CHIFFRE D'AFFAIRES | F7: DSO — DÉLAI CLIENTS | J7: DPO — DÉLAI FOURNISSEURS | N7: CROISSANCE DU RÉSULTAT NET
B8: =C61 -> 14100000 | F8: =C62 -> 72.59735 | J8: =C63 -> 78.773027 | N8: =C65 -> 0.060528667
B10: =IFERROR(IF(F61>=0,"▲ +","▼ ")&FIXED(F61/ABS(D61)*100,1)&" % vs mois précédent","—") -> ▲ +14.6 % vs mois précédent | F10: =IFERROR(IF(F62>=0,"▲ +","▼ ")&FIXED(F62,0)&" j vs mois précédent","—") -> ▼ -7 j vs mois précédent | J10: =IFERROR(IF(F63>=0,"▲ +","▼ ")&FIXED(F63,0)&" j vs mois précédent","—") -> ▼ -6 j vs mois précédent | N10: =IFERROR("RN du mois : "&FIXED(C64/1000,0)&" kMAD","—") -> RN du mois : 936 kMAD
B11: ="Cumul à fin "&LOWER($C$5)&" : "&FIXED(SUM(Reporting!$E$44:INDEX(Reporting!$E$44:$P$44,$P$5))/1000,0)&" kMAD" -> Cumul à fin décembre : 142,000 kMAD | F11: =IF(ISNUMBER(C62),IF(C62<=Reporting!$S$31,"● Conforme",IF(C62<=Reporting!$T$31,"● Vigilance","● Alerte"))&" (cible ≤ "&Reporting!$S$31&" j)","—") -> ● Vigilance (cible ≤ 60 j) | J11: =IF(ISNUMBER(C63),IF(AND(C63>=Reporting!$S$32,C63<=Reporting!$T$32),"● Conforme",IF(C63>Reporting!$U$32,"● Alerte","● Vigilance"))&" (cible "&Reporting!$S$32&"–"&Reporting!$T$32&" j)","—") -> ● Conforme (cible 60–90 j) | N11: =IF(ISNUMBER(C65),IF(C65>=Reporting!$S$24,"● Conforme",IF(C65>=Reporting!$T$24,"● Vigilance","● Alerte"))&" (cible ≥ +5 %)","—") -> ● Conforme (cible ≥ +5 %)
B51: DONNÉES SOURCES DES GRAPHIQUES ET DES CARTES (formules liées au Reporting — ne pas saisir)
B52: Série | C52: =Reporting!E$42 -> Janvier | D52: =Reporting!F$42 -> Février | E52: =Reporting!G$42 -> Mars | F52: =Reporting!H$42 -> Avril | G52: =Reporting!I$42 -> Mai | H52: =Reporting!J$42 -> Juin | I52: =Reporting!K$42 -> Juillet | J52: =Reporting!L$42 -> Août | ... N52: =Reporting!P$42 -> Décembre
B53: Chiffre d'affaires | C53: =Reporting!E44 -> 10800000 | D53: =Reporting!F44 -> 11200000 | E53: =Reporting!G44 -> 12400000 | F53: =Reporting!H44 -> 11900000 | G53: =Reporting!I44 -> 12600000 | H53: =Reporting!J44 -> 12800000 | I53: =Reporting!K44 -> 11600000 | J53: =Reporting!L44 -> 7400000 | ... N53: =Reporting!P44 -> 14100000
B54: CA mois sélectionné | C54: =IF(C$52=$C$5,C53,0) -> 0 | D54: =IF(D$52=$C$5,D53,0) -> 0 | E54: =IF(E$52=$C$5,E53,0) -> 0 | F54: =IF(F$52=$C$5,F53,0) -> 0 | G54: =IF(G$52=$C$5,G53,0) -> 0 | H54: =IF(H$52=$C$5,H53,0) -> 0 | I54: =IF(I$52=$C$5,I53,0) -> 0 | J54: =IF(J$52=$C$5,J53,0) -> 0 | ... N54: =IF(N$52=$C$5,N53,0) -> 14100000
B55: Résultat net | C55: =Reporting!E50 -> 735670.37 | D55: =Reporting!F50 -> 1066687.8 | E55: =Reporting!G50 -> 1066132.8 | F55: =Reporting!H50 -> 855598.55 | G55: =Reporting!I50 -> 1430961.9 | H55: =Reporting!J50 -> 1681883.2 | I55: =Reporting!K50 -> 1184822.4 | J55: =Reporting!L50 -> -397484.53 | ... N55: =Reporting!P50 -> 936411.55
B56: Valeur ajoutée | C56: =Reporting!E47 -> 5169667.2 | D56: =Reporting!F47 -> 5633560.5 | E56: =Reporting!G47 -> 6259937.3 | F56: =Reporting!H47 -> 5361457.2 | G56: =Reporting!I47 -> 6112188.8 | H56: =Reporting!J47 -> 6204176.9 | I56: =Reporting!K47 -> 5812165.8 | J56: =Reporting!L47 -> 3707489.7 | ... N56: =Reporting!P47 -> 6152352
B57: REX (positif) | C57: =MAX(Reporting!E49,0) -> 1111452.9 | D57: =MAX(Reporting!F49,0) -> 1572441.6 | E57: =MAX(Reporting!G49,0) -> 2298955.1 | F57: =MAX(Reporting!H49,0) -> 1272562.4 | G57: =MAX(Reporting!I49,0) -> 1989100.6 | H57: =MAX(Reporting!J49,0) -> 2269994.2 | I57: =MAX(Reporting!K49,0) -> 1718104.1 | J57: =MAX(Reporting!L49,0) -> 0 | ... N57: =MAX(Reporting!P49,0) -> 1330951.2
B58: REX (négatif) | C58: =MIN(Reporting!E49,0) -> 0 | D58: =MIN(Reporting!F49,0) -> 0 | E58: =MIN(Reporting!G49,0) -> 0 | F58: =MIN(Reporting!H49,0) -> 0 | G58: =MIN(Reporting!I49,0) -> 0 | H58: =MIN(Reporting!J49,0) -> 0 | I58: =MIN(Reporting!K49,0) -> 0 | J58: =MIN(Reporting!L49,0) -> -164627.83 | ... N58: =MIN(Reporting!P49,0) -> 0
B60: Cartes | C60: Mois sélect. | D60: Mois préc. | F60: Écart
B61: CA | C61: =IFERROR(INDEX(Reporting!$E$44:$P$44,$P$5),"—") -> 14100000 | D61: =IFERROR(INDEX(Reporting!$D$44:$O$44,$P$5),"—") -> 12300000 | F61: =IFERROR(C61-D61,"—") -> 1800000
B62: DSO | C62: =IFERROR(INDEX(Reporting!$E$77:$P$77,$P$5),"—") -> 72.59735 | D62: =IFERROR(INDEX(Reporting!$D$77:$O$77,$P$5),"—") -> 79.196963 | F62: =IFERROR(C62-D62,"—") -> -6.5996123
B63: DPO | C63: =IFERROR(INDEX(Reporting!$E$78:$P$78,$P$5),"—") -> 78.773027 | D63: =IFERROR(INDEX(Reporting!$D$78:$O$78,$P$5),"—") -> 84.878706 | F63: =IFERROR(C63-D63,"—") -> -6.1056793
B64: Résultat net | C64: =IFERROR(INDEX(Reporting!$E$50:$P$50,$P$5),"—") -> 936411.55 | D64: =IFERROR(INDEX(Reporting!$D$50:$O$50,$P$5),"—") -> 882966.75 | F64: =IFERROR(C64-D64,"—") -> 53444.8
B65: Croissance RN | C65: =IFERROR(INDEX(Reporting!$E$70:$P$70,$P$5),"—") -> 0.060528667 | D65: =IFERROR(INDEX(Reporting!$D$70:$O$70,$P$5),"—") -> -0.23786906 | F65: =IFERROR(C65-D65,"—") -> 0.29839772

Sheet Lecture
B1: LECTURE — DICTIONNAIRE DES INDICATEURS
B2: ="Société : "&Accueil!$C$8&" │ Exercice : "&Accueil!$C$11&" │ Date d'arrêté : "&Accueil!$C$12&" │ Responsable : "&Accueil!$C$15 -> Société : AéroAtlas Composites SARL │ Exercice : 2025 │ Date d'arrêté : 31/12/2025 │ Responsable : Karim El Fassi (DAF)
B4: ← Accueil | C4: Chaque indicateur expliqué simplement, pour un lecteur non financier
B6: Nom du KPI | C6: Explication ultra simple | D6: Comment lire (bon / mauvais signe) | E6: Formule
B7: Chiffre d'affaires (CA) | C7: Tout l'argent facturé aux clients pour les pièces et services vendus dans le mois. C'est la « taille du gâteau ». | D7: Plus il monte, mieux c'est — à condition que le résultat suive. | E7: Comptes 711 + 712
B8: Valeur ajoutée (VA) | C8: La richesse créée par l'usine : ce que l'on vend moins ce que l'on a acheté à l'extérieur (matières, services). C'est notre vrai travail. | D8: Plus elle est élevée, plus l'entreprise transforme vraiment la matière. | E8: Marge brute + Production − Consommations
B9: EBE | C9: Ce qu'il reste de la valeur ajoutée après avoir payé les salaires et les taxes. C'est le cash « brut » produit par le métier. | D9: Positif et en hausse = le métier est rentable avant amortissements. | E9: VA + Subventions − Impôts et taxes − Personnel
B10: Résultat d'exploitation (REX) | C10: Le bénéfice du métier une fois l'usure des machines (amortissements) prise en compte. Ni la banque ni le change n'y entrent. | D10: Négatif = le mois n'a pas couvert ses frais fixes (ex. août). | E10: Produits − Charges d'exploitation
B11: Résultat net (RN) | C11: Ce qui reste vraiment à l'entreprise à la fin, après banque, change, éléments exceptionnels et impôt. | D11: C'est le bénéfice qui revient aux associés. | E11: RAI − Impôt sur les résultats
B12: CAF | C12: L'argent réellement généré par l'activité, sans tenir compte des écritures « sans cash » (amortissements, provisions). | D12: C'est la cagnotte qui sert à rembourser la dette et à investir. | E12: RN + dotations − reprises − cessions + VNA
B13: BFR | C13: L'argent bloqué dans le cycle : stocks en attente + clients pas encore payés − fournisseurs pas encore réglés. | D13: Un BFR trop élevé « mange » la trésorerie. | E13: Stocks + Créances − Dettes circulantes
B14: Élasticité CA / REX | C14: Combien le bénéfice d'exploitation bouge quand les ventes bougent de 1 %. Comme un levier : petit effort, grand effet. | D14: > 1,2 quand le CA monte = excellent ; > 1,2 quand le CA baisse = alerte. | E14: Variation REX % ÷ Variation CA %
B15: Poids de la masse salariale / CA | C15: Sur 100 MAD vendus, combien partent en salaires et charges sociales. | D15: Bas = bien (≤ 28 %). Haut = trop de salaires pour le niveau de ventes. | E15: Charges de personnel ÷ CA
B16: CAF / CA | C16: Sur 100 MAD vendus, combien deviennent du cash disponible. | D16: Haut = bien (≥ 12 %). | E16: CAF ÷ CA
B17: Taux de croissance du résultat net | C17: Le bénéfice de ce mois comparé à celui du mois précédent. | D17: Positif = le bénéfice progresse ; négatif = il recule. | E17: (RN − RN M-1) ÷ |RN M-1|
... B31: Taux de valeur ajoutée locale | C31: La part de la production réellement créée au Maroc (et non achetée à l'extérieur). | D31: Haut = bien (≥ 40 %) : intégration locale forte. | E31: VA ÷ Production de l'exercice
B33: GLOSSAIRE
B34: CGNC | C34: Code Général de Normalisation Comptable : le « code de la route » de la comptabilité au Maroc.
B35: CPC | C35: Compte de Produits et Charges : le film de l'année, ce qui a été gagné et dépensé.
B36: ESG | C36: État des Soldes de Gestion : le CPC découpé en étapes (marge, VA, EBE, REX, RN) + la CAF.
B37: TFR | C37: Tableau de Formation des Résultats : la première partie de l'ESG.
B38: MAD | C38: Dirham marocain. kMAD = milliers de dirhams ; M = millions.
B39: n.s. | C39: Non significatif : calcul volontairement non affiché (variation du CA < 2 % ou REX précédent ≤ 0).
B40: « — » | C40: Calcul impossible (division par zéro ou donnée manquante) : la cellule n'affiche pas d'erreur.
B41: Codes couleur | C41: Vert = conforme au benchmark │ Bleu = proportionnel / neutre │ Orange = vigilance │ Rouge = alerte.
